Workbook
Name Accrued_Income: AI!$B$3
Name Amex_Loan: AL!$B$5
Name B_S: BS!$B$4
Name ColumnTitle1: #REF!
Name EndingBalance: -FV(InterestRate/12,AP!PaymentNumber,-AP!MonthlyPayment,LoanAmount)
Name EndingBalance: -FV(InterestRate/12,PaymentNumber,-MonthlyPayment,LoanAmount)
Name HeaderRow: ROW(#REF!)
Name I_L: IL!$B$5
Name InterestAmt: -IPMT(InterestRate/12,AP!PaymentNumber,NumberOfPayments,LoanAmount)
Name InterestAmt: -IPMT(InterestRate/12,PaymentNumber,NumberOfPayments,LoanAmount)
Name InterestRate: #REF!
Name LastCol: COUNTA(#REF!)
Name LastRow: MATCH(9.99E+307,#REF!)
Name LoanAmount: #REF!
Name LoanIsGood: IF(LoanAmount*InterestRate*LoanYears*LoanStartDate>0,1,0)
Name LoanIsGood: IF(LoanAmount*InterestRate*LoanYears*LoanStartDate>0,1,0)
Name LoanIsNotPaid: IF(AP!PaymentNumber<=NumberOfPayments,1,0)
Name LoanIsNotPaid: IF(PaymentNumber<=NumberOfPayments,1,0)
Name LoanStartDate: #REF!
Name LoanValue: -FV(InterestRate/12,AP!PaymentNumber-1,-AP!MonthlyPayment,LoanAmount)
Name LoanValue: -FV(InterestRate/12,PaymentNumber-1,-MonthlyPayment,LoanAmount)
Name LoanYears: #REF!
Name MonthlyPayment: -PMT(InterestRate/12,NumberOfPayments,LoanAmount)
Name MonthlyPayment: -PMT(InterestRate/12,NumberOfPayments,LoanAmount)
Name NumberOfPayments: #REF!
Name P_L: 'Profit and Loss by Month'!$B$3
Name PaymentDate: DATE(YEAR(LoanStartDate),MONTH(LoanStartDate)+AP!PaymentNumber,DAY(LoanStartDate))
Name PaymentDate: DATE(YEAR(LoanStartDate),MONTH(LoanStartDate)+PaymentNumber,DAY(LoanStartDate))
Name PaymentNumber: ROW()-HeaderRow
Name PaymentNumber: ROW()-HeaderRow
Name PL_DM: 'Profit & Loss - Division(Month)'!$B$3
Name PL_YTD: 'Profit and Loss - Division(YTD)'!$B$3
Name Principal: -PPMT(InterestRate/12,AP!PaymentNumber,NumberOfPayments,LoanAmount)
Name Principal: -PPMT(InterestRate/12,PaymentNumber,NumberOfPayments,LoanAmount)
Name PrintArea_SET: OFFSET(#REF!,,,LastRow,LastCol)
Name PrintArea_SET: OFFSET(#REF!,,,LastRow,LastCol)
Name R_L: RL!$B$5
Name RowTitleRegion1..D6: #REF!
Name RowTitleRegion2..H6: #REF!
Name Total_Interest: #REF!
Name TotalLoanCost: #REF!

Sheet Project Profitability Points
A1: 1. Improving Project Profitability Reporting
A2: Right now, we have observed that project profitability is not aligning because employees are not entering their full working hours in the toggle.
A4: Here’s what’s happening:
A5: Employees record their time against projects in Toggle.
A6: Payroll is processed separately, and we record total payroll cost directly in P&L.
A7: When working on project profitability, we divide the employee’s payroll cost based on the hours they entered in Toggle.
A9: But here’s the problem:
A10: If an employee works 60 hours in two weeks, and records only 4 hours in Toggle, then all of their pay is being assigned to just those 4 hours for two projects.
A11: This makes the project cost look very high, and the profitability report becomes inaccurate.
A28: Suggested Solution:
A29: Set a Minimum Time Entry Benchmark:
A30: Every employee should enter their full working hours (for example, 8 hours per day or 40 hours per week).
... A37: If they record only 4 hours → cost per hour = $500 → makes the project, look much more expensive than it really is.

Sheet Cover
A3: Pacific Nexus
A5: Financial Workpapers for the
A6: Period Ending 03/31/2026
A9: Prepared by:
A17: Analytix Solutions
A19: For Internal Management Purpose Only

Sheet Index
A1: =Cover!A3 -> Pacific Nexus
A2: =Cover!A6 -> Period Ending 03/31/2026
A4: Financial Statements Index
A6: Sr. No. | B6: Particulars | C6: Reference
A9: 1 | B9: Balance sheet | C9: BS
A11: =+A9+1 -> 2 | B11: Profit and Loss Account-Monthly/Quarterly | C11: PL
A13: =+A11+1 -> 3 | B13: Profit and Loss Account- Division (YTD) | C13: PL-Division (YTD)
A15: 4 | B15: Profit & Loss - Division(Month) | C15: PL-Division (Month)
A17: 5 | B17: Statement of Cash Flow | C17: Cash Flow
A19: 6 | B19: Profit and Loss - YOY Summary | C19: P&L YOY Summary
A21: 7 | B21: Profit and Loss - YOY Detail | C21: P&L YOY Detail
A23: 8 | B23: Project Profitability Report | C23: PPR

Sheet BS
B2: =Index!A1 -> Pacific Nexus | F2: Home
B3: =Index!A2 -> Period Ending 03/31/2026 | F3: Profit & Loss
B4: Balance Sheet | F4: PL-Division (Month)
F5: PL-Division (YTD)
F6: Cash Flow
B7: Particulars | C7: Amount | D7: Schedule | E7: Comments
B8: Assets
B9: Current Assets
B10: Bank Accounts
B11: 1000 CNB Checking #2640 | C11: 93993.55 | E11: Bank is reconciled as of 03/31/2026
B12: Total for Bank Accounts | C12: =C10+C11 -> 93993.55
B13: Accounts Receivable
B14: 1100 Accounts Receivable | C14: 169897.05 | D14: AR | E14: Kindly walk through attached Accounts Receivable aging report for your review and feedback, if any.
B15: Total for Accounts Receivable | C15: =C13+C14 -> 169897.05
B16: Other Current Assets
B17: 1300 Prepaid Expenses | C17: 18571.31 | D17: PE
B18: 1380 Accrued Income | C18: 119875.41 | D18: Accrual Income
B19: Total for Other Current Assets | C19: =C16+C17+C18 -> 138446.72
B20: Total for Current Assets | C20: =C9+C12+C15+C19 -> 402337.32
B21: Fixed Assets
B22: 1425 Computer & Office Equipment | C22: 226991.82 | D22: FA | E22: There was an addition of $8,725.00 in March ’26 related to alarm installation.
B23: 1430 Accumulated Depreciation - Computer & Office Equipment | C23: -91592.16
B24: Total for 1425 Computer & Office Equipment | C24: =C22+C23 -> 135399.66
B25: 1435 Leasehold Improvements | C25: 12840
B26: 1440 Accumulated Depreciation - Leasehold Improvements | C26: -3754.44
B27: Total for 1435 Leasehold Improvements | C27: =C25+C26 -> 9085.56
B28: Total for Fixed Assets | C28: =C21+C24+C27 -> 144485.22
B29: Other Assets
B30: 1505 Goodwill | C30: 2236541.8 | D30: OA
B31: 1510 Accumulated Amortization - Goodwill | C31: -298205.45
B32: Total for 1505 Goodwill | C32: =C30+C31 -> 1938336.3
B33: 1515 Loan Closing Costs | C33: 67628.25
B34: 1520 Accumulated Amortization - Loan Closing Costs | C34: -13525.55
B35: Total for 1515 Loan Closing Costs | C35: =C33+C34 -> 54102.7
B36: 1540 Purchase Cost - NS Printing | C36: 111368.67
B37: 1545 Accumulated Amortization - Purchase Cost - NS Printing | C37: -8739.04
B38: Total for 1540 Purchase Cost - NS Printing | C38: =C36+C37 -> 102629.63
B39: 1600 Security Deposit | C39: 94343.18
B40: Total for Other Assets | C40: =C29+C32+C35+C38+C39 -> 2189411.8
B41: Total for Assets | C41: =C20+C28+C40 -> 2736234.4
B42: Liabilities and Equity
B43: Liabilities
B44: Current Liabilities
B45: Accounts Payable
B46: 2000 Accounts Payable | C46: 117975 | D46: AP | E46: Kindly walk through attached Accounts Payable aging report for your review and feedback, if any.
B47: Total for Accounts Payable | C47: =C45+C46 -> 117975
B48: Credit Cards
B49: 2105 AMEX #1000 | C49: 89608.31 | E49: Credit Card Reconciled as of 03/18/26
B50: 2110 AMEX #1003 | C50: 0
B51: 2115 VISA #7547 | C51: 2011.09 | E51: Credit Card Reconciled as of 03/10/26
B52: Total for Credit Cards | C52: =C48+C49+C50+C51 -> 91619.4
B53: Other Current Liabilities
B54: 2205 Accrued Expenses | C54: 129735.02 | D54: AE
B55: 2215 Accrued Interest on Shareholder's Loan - Zaheer | C55: 174947.03 | D55: AE-SL
B56: 2240 Payroll liabilities
B57: 2241 Payroll Clearing | C57: 4765.17 | E57: Payroll Tax Adjustments (Reconciled as of 03/31/2026): Rippling has recorded a Q1 payroll tax reconciliation adjustment of $2,494.23 and a FUTA credit reduction accrual of $2,270.86 related to Form 940. Both entries impact the payroll clearing account and do not involve an immediate cash debit. We have reviewed and reconciled these balances as of March 31, 2026, and they will be settled through Rippling’s scheduled tax filings and payments.
B58: 2243 Health Deduction payable | C58: -8621 | E58: We noted that employee deductions (medical, vision, dental) and employer medical contributions were initially recorded in the P&L. To ensure accurate reconciliation, these have been reclassified to liability accounts. Monthly insurance bills are now matched against these balances to look into it any overpayment or underpayment.
B59: 2244 401K Withholding | C59: 1396.43
B60: Total for 2240 Payroll liabilities | C60: =C56+C57+C58+C59 -> -2459.4
B61: 2250 Intuit Loan | C61: 22180.63 | D61: IL | E61: We observed that the Intuit loan payment has not been made for December 2025 to March 2026, which is usually paid using your personal VISA card.
B62: 2300 California Department of Tax and Fee Administration Payable | C62: 23647.22
B63: 2220 Other Current Liabilities | C63: 48935.8
B64: Total for Other Current Liabilities | C64: =C53+C54+C55+C60+C61+C62+C63 -> 396986.3
B65: Total for Current Liabilities | C65: =C44+C47+C52+C64 -> 606580.7
B66: Long-term Liabilities
B67: 2515 AMEX Loan #3344 | C67: 41666.7 | D67: AL
B68: 2535 Ricoh Lease - 5120 | C68: 52500 | D68: RL
B69: 2705 Shareholder Loan - Zaheer | C69: 1013228.5 | D69: SL
B70: 2510 FCB Loan #1837 | C70: 2306000
B71: Total for Long-term Liabilities | C71: =C66+C67+C68+C69+C70 -> 3413395.2
B72: Total for Liabilities | C72: =C43+C65+C71 -> 4019975.9
B73: Equity
B74: 3000 Capital Stock | C74: 30
B75: 3020 Retained Earnings | C75: -1140027
B76: Net Income | C76: -143744.52
B77: Total for Equity | C77: =C73+C74+C75+C76 -> -1283741.5
B78: Total for Liabilities and Equity | C78: =C72+C77 -> 2736234.4
B80: Checkpoint | C80: =C41-C78 -> 0

Sheet Charts

Sheet Charts Data
B2: Particulars | C2: 01/2025 | D2: 02/2025 | E2: 03/2025 | F2: 04/2025 | G2: 05/2025 | H2: 06/2025 | I2: 07/2025 | J2: 08/2025 | K2: 09/2025 | L2: YTD
B3: Sales % of change | C3: 0 | D3: =(D4-C4)/C4 -> -0.14481786 | E3: =(E4-D4)/D4 -> -0.24802246 | F3: =(F4-E4)/E4 -> 1.5233796 | G3: =(G4-F4)/F4 -> -0.52972321 | H3: =(H4-G4)/G4 -> 0.81196107 | I3: =(I4-H4)/H4 -> -0.18211049 | J3: =(J4-I4)/I4 -> -0.12695659 | K3: =(K4-J4)/J4 -> 0.30026693
B4: Total Sales | C4: 206276.98 | D4: 176404.39 | E4: 132652.14 | F4: 334731.7 | G4: 157416.55 | H4: 285232.66 | I4: 233288.8 | J4: 203671.25 | K4: 264826.99 | L4: =SUM(C4:K4) -> 1994501.5
B5: Photography % of change | C5: 0 | D5: =(D6-C6)/C6 -> 1.3895737 | E5: =(E6-D6)/D6 -> -0.5536826 | F5: =(F6-E6)/E6 -> 4.3410189 | G5: =(G6-F6)/F6 -> -0.81539028 | H5: =(H6-G6)/G6 -> 1.696871 | I5: =(I6-H6)/H6 -> -0.36305488 | J5: =(J6-I6)/I6 -> -0.18644345 | K5: =(K6-J6)/J6 -> 0.082095012
B6: PN Photography | C6: 39995 | D6: 95571 | E6: 42655 | F6: 227821.16 | G6: 42058 | H6: 113425 | I6: 72245.5 | J6: 58775.8 | K6: 63601 | L6: =SUM(C6:K6) -> 756147.46
B7: Printing % of change | C7: 0 | D7: =(D8-C8)/C8 -> -0.33378721 | E7: =(E8-D8)/D8 -> 0.073260166 | F7: =(F8-E8)/E8 -> 0.59360802 | G7: =(G8-F8)/F8 -> 0.14193989 | H7: =(H8-G8)/G8 -> 0.53100262 | I7: =(I8-H8)/H8 -> -0.068474013 | J7: =(J8-I8)/I8 -> -0.094648448 | K7: =(K8-J8)/J8 -> 0.3887668
B8: PN Printing | C8: 86243 | D8: 57456.19 | E8: 61665.44 | F8: 98270.54 | G8: 112219.05 | H8: 171807.66 | I8: 160043.3 | J8: 144895.45 | K8: 201225.99 | L8: =SUM(C8:K8) -> 1093826.6
B9: Gross Profit | C9: 93355.12 | D9: 85500.19 | E9: -10454.59 | F9: 218949.23 | G9: 11938.71 | H9: 202139.42 | I9: 86590.35 | J9: 109796.02 | K9: 171932.47 | L9: =SUM(C9:K9) -> 969746.92
B10: GP % | C10: =C9/C4 -> 0.45257168 | D10: =D9/D4 -> 0.48468289 | E10: =E9/E4 -> -0.078812072 | F10: =F9/F4 -> 0.65410366 | G10: =G9/G4 -> 0.075841517 | H10: =H9/H4 -> 0.70868259 | I10: =I9/I4 -> 0.37117234 | J10: =J9/J4 -> 0.53908453 | ... L10: =L9/L4 -> 0.48621018
B11: EBITDA | C11: -59483.9 | D11: -56308.1 | E11: -131287.97 | F11: 52520.36 | G11: -80565.19 | H11: 103493.86 | I11: -32039.53 | J11: 16603.65 | K11: 92337.52 | L11: =SUM(C11:K11) -> -94729.3
B12: EBITDA % | C12: =C11/C4 -> -0.28836907 | D12: =D11/D4 -> -0.31919897 | E12: =E11/E4 -> -0.98971619 | F12: =F11/F4 -> 0.15690286 | G12: =G11/G4 -> -0.51179619 | H12: =H11/H4 -> 0.36284015 | I12: =I11/I4 -> -0.13733848 | J12: =J11/J4 -> 0.081521815 | ... L12: =L11/L4 -> -0.047495227
B13: EBIT | C13: -73180.12 | D13: -70004.32 | E13: -145113.19 | F13: 38522.02 | G13: -94563.53 | H13: 89495.52 | I13: -46037.87 | J13: 2605.31 | K13: 78339.18 | L13: =SUM(C13:K13) -> -219937
B14: EBIT % | C14: =C13/C4 -> -0.3547663 | D14: =D13/D4 -> -0.39684001 | E14: =E13/E4 -> -1.0939378 | F14: =F13/F4 -> 0.11508327 | G14: =G13/G4 -> -0.60072165 | H14: =H13/H4 -> 0.31376323 | I14: =I13/I4 -> -0.19734282 | J14: =J13/J4 -> 0.012791742 | ... L14: =L13/L4 -> -0.11027167
B15: PBT/PAT | C15: -97938.46 | D15: -94067.95 | E15: -169679 | F15: 13224.57 | G15: -120325.33 | H15: 64682.21 | I15: -73099.63 | J15: -24017.16 | K15: 52551.81 | L15: =SUM(C15:K15) -> -448668.94
B16: PBT/PAT % | C16: =C15/C4 -> -0.47479103 | D16: =D15/D4 -> -0.53325175 | E16: =E15/E4 -> -1.2791275 | F16: =F15/F4 -> 0.03950797 | G16: =G15/G4 -> -0.76437535 | H16: =H15/H4 -> 0.22677 | I16: =I15/I4 -> -0.31334393 | J16: =J15/J4 -> -0.11792121 | ... L16: =L15/L4 -> -0.22495293
B63: COGS | C63: YTD | D63: %
B64: Cost of Materials | C64: 318180.89 | D64: =C64/$C$67 -> 0.15952903
B65: Travels and Meals | C65: 10319.72 | D65: =C65/$C$67 -> 0.005174085
B66: Wages & Taxes | C66: 696253.93 | D66: =C66/$C$67 -> 0.3490867
B67: Total Sales | C67: 1994501.5 | D67: =C67/$C$67 -> 1
B92: Operating Expenses | C92: YTD | D92: % of Sales | E92: % of Op. Ex
B93: Salaries and Taxes | C93: ='Profit and Loss by Month'!O25 -> 0 | D93: =C93/$C$99 -> 0 | E93: =C93/$C$100 -> #REF!
B94: Shareholder's Compensation | C94: ='Profit and Loss by Month'!O41 -> 1175 | D94: =C94/$C$99 -> 0.0016447405 | E94: =C94/$C$100 -> #REF!
B95: Professional Fees | C95: ='Profit and Loss by Month'!O35 -> 12549.99 | D95: =C95/$C$99 -> 0.017567214 | E95: =C95/$C$100 -> #REF!
B96: Office Expesnes | C96: ='Profit and Loss by Month'!O47 -> 7736.87 | D96: =C96/$C$99 -> 0.010829909 | E96: =C96/$C$100 -> #REF!
B97: Facility Expenses | C97: ='Profit and Loss by Month'!O54 -> 8503.67 | D97: =C97/$C$99 -> 0.01190326 | E97: =C97/$C$100 -> #REF!
B98: Other Operating Expenses | C98: ='Profit and Loss by Month'!O74+13098.54 -> 72647.45 | D98: =C98/$C$99 -> 0.10169038 | E98: =C98/$C$100 -> #REF!
B99: Total Sales | C99: ='Profit and Loss by Month'!O11 -> 714398.42 | D99: =C99/$C$99 -> 1
B100: Total Operating Expenses | C100: ='Profit and Loss by Month'!O75-'Profit and Loss by Month'!#REF! -> #REF!

Sheet Profit and Loss by Month
B2: =Index!A1 -> Pacific Nexus | V2: Home
B3: Profit and Loss | V3: Balance Sheet
B4: =Index!A2 -> Period Ending 03/31/2026 | V4: PL-Division (Month)
V5: PL-Division (YTD)
C6: 46023 | G6: 46054 | K6: 46082 | O6: YTD | S6: Remarks | T6: Actual % on Sales | U6: Projected % on Sales
C7: Actual | D7: Budget | E7: Variance | F7: % of Budget | G7: Actual | H7: Budget | I7: Variance | J7: % of Budget | K7: Actual | L7: Budget | M7: Variance | N7: % of Budget | O7: Actual | P7: Budget | Q7: Variance | R7: % of Budget
B8: Income
B9: 4005 Sales Revenue | C9: =206737.15 -> 206737.15 | D9: =345833.33 -> 345833.33 | E9: =(C9)-(D9) -> -139096.18 | F9: =IF(D9=0,"",(C9)/(D9)) -> 0.59779417 | G9: =221461.62 -> 221461.62 | H9: =345833.33 -> 345833.33 | I9: =(G9)-(H9) -> -124371.71 | J9: =IF(H9=0,"",(G9)/(H9)) -> 0.64037096 | K9: =289563.38 -> 289563.38 | L9: =345833.33 -> 345833.33 | M9: =(K9)-(L9) -> -56269.95 | N9: =IF(L9=0,"",(K9)/(L9)) -> 0.83729171 | O9: =((C9)+(G9))+(K9) -> 717762.15 | P9: =((D9)+(H9))+(L9) -> 1037500 | Q9: =(O9)-(P9) -> -319737.84 | R9: =IF(P9=0,"",(O9)/(P9)) -> 0.69181895
B10: 4010 Sales Discount | C10: =-1952.59 -> -1952.59 | E10: =(C10)-(D10) -> -1952.59 | F10: =IF(D10=0,"",(C10)/(D10)) | G10: =-515.62 -> -515.62 | I10: =(G10)-(H10) -> -515.62 | J10: =IF(H10=0,"",(G10)/(H10)) | K10: =-895.52 -> -895.52 | M10: =(K10)-(L10) -> -895.52 | N10: =IF(L10=0,"",(K10)/(L10)) | O10: =((C10)+(G10))+(K10) -> -3363.73 | P10: =((D10)+(H10))+(L10) -> 0 | Q10: =(O10)-(P10) -> -3363.73 | R10: =IF(P10=0,"",(O10)/(P10))
B11: Total Income | C11: =(C9)+(C10) -> 204784.56 | D11: =(D9)+(D10) -> 345833.33 | E11: =(C11)-(D11) -> -141048.77 | F11: =IF(D11=0,"",(C11)/(D11)) -> 0.59214813 | G11: =(G9)+(G10) -> 220946 | H11: =(H9)+(H10) -> 345833.33 | I11: =(G11)-(H11) -> -124887.33 | J11: =IF(H11=0,"",(G11)/(H11)) -> 0.63888001 | K11: =(K9)+(K10) -> 288667.86 | L11: =(L9)+(L10) -> 345833.33 | M11: =(K11)-(L11) -> -57165.47 | N11: =IF(L11=0,"",(K11)/(L11)) -> 0.83470225 | O11: =((C11)+(G11))+(K11) -> 714398.42 | P11: =((D11)+(H11))+(L11) -> 1037500 | Q11: =(O11)-(P11) -> -323101.57 | R11: =IF(P11=0,"",(O11)/(P11)) -> 0.6885768 | S11: We achieved approximately 83% of the budgeted sales for Mar ’26. Compared to Jan ’26 and Feb ’26, this reflects an improvement and indicates that we are moving closer to the budgeted sales levels.
B12: Cost of Goods Sold
B13: 5005 Cost of Materials | C13: =29209.55 -> 29209.55 | D13: =44958.33 -> 44958.33 | E13: =(C13)-(D13) -> -15748.78 | F13: =IF(D13=0,"",(C13)/(D13)) -> 0.64970274 | G13: =23283.51 -> 23283.51 | H13: =44958.33 -> 44958.33 | I13: =(G13)-(H13) -> -21674.82 | J13: =IF(H13=0,"",(G13)/(H13)) -> 0.5178909 | K13: =34847.91 -> 34847.91 | L13: =44958.33 -> 44958.33 | M13: =(K13)-(L13) -> -10110.42 | N13: =IF(L13=0,"",(K13)/(L13)) -> 0.77511576 | O13: =((C13)+(G13))+(K13) -> 87340.97 | P13: =((D13)+(H13))+(L13) -> 134874.99 | Q13: =(O13)-(P13) -> -47534.02 | R13: =IF(P13=0,"",(O13)/(P13)) -> 0.6475698
B14: 5015 Travels and Meals | E14: =(C14)-(D14) -> 0 | F14: =IF(D14=0,"",(C14)/(D14)) | I14: =(G14)-(H14) -> 0 | J14: =IF(H14=0,"",(G14)/(H14)) | K14: 0 | M14: =(K14)-(L14) -> 0 | N14: =IF(L14=0,"",(K14)/(L14)) | O14: =((C14)+(G14))+(K14) -> 0 | P14: =((D14)+(H14))+(L14) -> 0 | Q14: =(O14)-(P14) -> 0 | R14: =IF(P14=0,"",(O14)/(P14))
B15: 5065 Wages | C15: =90285.21 -> 90285.21 | D15: =76465.59 -> 76465.59 | E15: =(C15)-(D15) -> 13819.62 | F15: =IF(D15=0,"",(C15)/(D15)) -> 1.1807299 | G15: =86016.39 -> 86016.39 | H15: =76465.59 -> 76465.59 | I15: =(G15)-(H15) -> 9550.8 | J15: =IF(H15=0,"",(G15)/(H15)) -> 1.1249032 | K15: =97713.83 -> 97713.83 | L15: =76465.59 -> 76465.59 | M15: =(K15)-(L15) -> 21248.24 | N15: =IF(L15=0,"",(K15)/(L15)) -> 1.2778798 | O15: =((C15)+(G15))+(K15) -> 274015.43 | P15: =((D15)+(H15))+(L15) -> 229396.77 | Q15: =(O15)-(P15) -> 44618.66 | R15: =IF(P15=0,"",(O15)/(P15)) -> 1.1945043
B16: 5070 Payroll Tax Expense | C16: =9791.27 -> 9791.27 | D16: =6117.25 -> 6117.25 | E16: =(C16)-(D16) -> 3674.02 | F16: =IF(D16=0,"",(C16)/(D16)) -> 1.6005999 | G16: =7407.13 -> 7407.13 | H16: =6117.25 -> 6117.25 | I16: =(G16)-(H16) -> 1289.88 | J16: =IF(H16=0,"",(G16)/(H16)) -> 1.2108595 | K16: =8070.23 -> 8070.23 | L16: =6117.25 -> 6117.25 | M16: =(K16)-(L16) -> 1952.98 | N16: =IF(L16=0,"",(K16)/(L16)) -> 1.3192578 | O16: =((C16)+(G16))+(K16) -> 25268.63 | P16: =((D16)+(H16))+(L16) -> 18351.75 | Q16: =(O16)-(P16) -> 6916.88 | R16: =IF(P16=0,"",(O16)/(P16)) -> 1.3769057
B17: 5075 Employee Benefits | C17: =3351.49 -> 3351.49 | D17: =3058.62 -> 3058.62 | E17: =(C17)-(D17) -> 292.87 | F17: =IF(D17=0,"",(C17)/(D17)) -> 1.0957523 | G17: =3877.27 -> 3877.27 | H17: =3058.62 -> 3058.62 | I17: =(G17)-(H17) -> 818.65 | J17: =IF(H17=0,"",(G17)/(H17)) -> 1.2676534 | K17: =4829.13 -> 4829.13 | L17: =3058.62 -> 3058.62 | M17: =(K17)-(L17) -> 1770.51 | N17: =IF(L17=0,"",(K17)/(L17)) -> 1.5788591 | O17: =((C17)+(G17))+(K17) -> 12057.89 | P17: =((D17)+(H17))+(L17) -> 9175.86 | Q17: =(O17)-(P17) -> 2882.03 | R17: =IF(P17=0,"",(O17)/(P17)) -> 1.3140883
B18: Total Cost of Goods Sold | C18: =((((C13)+(C14))+(C15))+(C16))+(C17) -> 132637.52 | D18: =((((D13)+(D14))+(D15))+(D16))+(D17) -> 130599.79 | E18: =(C18)-(D18) -> 2037.73 | F18: =IF(D18=0,"",(C18)/(D18)) -> 1.0156029 | G18: =((((G13)+(G14))+(G15))+(G16))+(G17) -> 120584.3 | H18: =((((H13)+(H14))+(H15))+(H16))+(H17) -> 130599.79 | I18: =(G18)-(H18) -> -10015.49 | J18: =IF(H18=0,"",(G18)/(H18)) -> 0.92331159 | K18: =((((K13)+(K14))+(K15))+(K16))+(K17) -> 145461.1 | L18: =((((L13)+(L14))+(L15))+(L16))+(L17) -> 130599.79 | M18: =(K18)-(L18) -> 14861.31 | N18: =IF(L18=0,"",(K18)/(L18)) -> 1.1137928 | O18: =((C18)+(G18))+(K18) -> 398682.92 | P18: =((D18)+(H18))+(L18) -> 391799.37 | Q18: =(O18)-(P18) -> 6883.55 | R18: =IF(P18=0,"",(O18)/(P18)) -> 1.0175691 | T18: =K18/$K$11 -> 0.50390473 | U18: =L18/$L$11 -> 0.37763795
B19: Gross Profit | C19: =(C11)-(C18) -> 72147.04 | D19: =(D11)-(D18) -> 215233.54 | E19: =(C19)-(D19) -> -143086.5 | F19: =IF(D19=0,"",(C19)/(D19)) -> 0.33520352 | G19: =(G11)-(G18) -> 100361.7 | H19: =(H11)-(H18) -> 215233.54 | I19: =(G19)-(H19) -> -114871.84 | J19: =IF(H19=0,"",(G19)/(H19)) -> 0.4662921 | K19: =(K11)-(K18) -> 143206.76 | L19: =(L11)-(L18) -> 215233.54 | M19: =(K19)-(L19) -> -72026.78 | N19: =IF(L19=0,"",(K19)/(L19)) -> 0.66535522 | O19: =((C19)+(G19))+(K19) -> 315715.5 | P19: =((D19)+(H19))+(L19) -> 645700.62 | Q19: =(O19)-(P19) -> -329985.12 | R19: =IF(P19=0,"",(O19)/(P19)) -> 0.48895028 | S19: We achieved approximately 65% of the targeted gross profit, which is an improvement compared to Jan ’26 and Feb ’26, primarily driven by a 10% increase in sales. The shortfall is largely volume‑driven, and margins are expected to improve as sales continue to pick up. | T19: =K19/$K$11 -> 0.49609527 | U19: =L19/$L$11 -> 0.62236205
B20: Expenses
B21: 6100 Payroll Expenses | E21: =(C21)-(D21) -> 0 | F21: =IF(D21=0,"",(C21)/(D21)) | I21: =(G21)-(H21) -> 0 | J21: =IF(H21=0,"",(G21)/(H21)) | M21: =(K21)-(L21) -> 0 | N21: =IF(L21=0,"",(K21)/(L21)) | O21: =((C21)+(G21))+(K21) -> 0 | P21: =((D21)+(H21))+(L21) -> 0 | Q21: =(O21)-(P21) -> 0 | R21: =IF(P21=0,"",(O21)/(P21))
B22: 6105 Salaries & Wages | C22: =23690.14 -> 23690.14 | D22: =21626.45 -> 21626.45 | E22: =(C22)-(D22) -> 2063.69 | F22: =IF(D22=0,"",(C22)/(D22)) -> 1.0954244 | G22: =19384.61 -> 19384.61 | H22: =21626.45 -> 21626.45 | I22: =(G22)-(H22) -> -2241.84 | J22: =IF(H22=0,"",(G22)/(H22)) -> 0.89633805 | K22: =21461.53 -> 21461.53 | L22: =21626.45 -> 21626.45 | M22: =(K22)-(L22) -> -164.92 | N22: =IF(L22=0,"",(K22)/(L22)) -> 0.99237415 | O22: =((C22)+(G22))+(K22) -> 64536.28 | P22: =((D22)+(H22))+(L22) -> 64879.35 | Q22: =(O22)-(P22) -> -343.07 | R22: =IF(P22=0,"",(O22)/(P22)) -> 0.99471219
B23: 6115 Payroll Tax Expense | C23: =1899.81 -> 1899.81 | D23: =1730.12 -> 1730.12 | E23: =(C23)-(D23) -> 169.69 | F23: =IF(D23=0,"",(C23)/(D23)) -> 1.0980799 | G23: =1358.66 -> 1358.66 | H23: =1730.12 -> 1730.12 | I23: =(G23)-(H23) -> -371.46 | J23: =IF(H23=0,"",(G23)/(H23)) -> 0.78529813 | K23: =3998.69 -> 3998.69 | L23: =1730.12 -> 1730.12 | M23: =(K23)-(L23) -> 2268.57 | N23: =IF(L23=0,"",(K23)/(L23)) -> 2.3112212 | O23: =((C23)+(G23))+(K23) -> 7257.16 | P23: =((D23)+(H23))+(L23) -> 5190.36 | Q23: =(O23)-(P23) -> 2066.8 | R23: =IF(P23=0,"",(O23)/(P23)) -> 1.3981997
B24: 6120 Employee Benefits | C24: =525.64 -> 525.64 | D24: =865.06 -> 865.06 | E24: =(C24)-(D24) -> -339.42 | F24: =IF(D24=0,"",(C24)/(D24)) -> 0.60763415 | G24: =781.15 -> 781.15 | H24: =865.06 -> 865.06 | I24: =(G24)-(H24) -> -83.91 | J24: =IF(H24=0,"",(G24)/(H24)) -> 0.90300095 | K24: =1159.91 -> 1159.91 | L24: =865.06 -> 865.06 | M24: =(K24)-(L24) -> 294.85 | N24: =IF(L24=0,"",(K24)/(L24)) -> 1.3408434 | O24: =((C24)+(G24))+(K24) -> 2466.7 | P24: =((D24)+(H24))+(L24) -> 2595.18 | Q24: =(O24)-(P24) -> -128.48 | R24: =IF(P24=0,"",(O24)/(P24)) -> 0.95049284
B25: 6125 Employee Bonus | D25: =821.81 -> 821.81 | E25: =(C25)-(D25) -> -821.81 | F25: =IF(D25=0,"",(C25)/(D25)) -> 0 | H25: =821.81 -> 821.81 | I25: =(G25)-(H25) -> -821.81 | J25: =IF(H25=0,"",(G25)/(H25)) -> 0 | L25: =821.81 -> 821.81 | M25: =(K25)-(L25) -> -821.81 | N25: =IF(L25=0,"",(K25)/(L25)) -> 0 | O25: =((C25)+(G25))+(K25) -> 0 | P25: =((D25)+(H25))+(L25) -> 2465.43 | Q25: =(O25)-(P25) -> -2465.43 | R25: =IF(P25=0,"",(O25)/(P25)) -> 0
B26: Total 6100 Payroll Expenses | C26: =((((C21)+(C22))+(C23))+(C24))+(C25) -> 26115.59 | D26: =((((D21)+(D22))+(D23))+(D24))+(D25) -> 25043.44 | E26: =(C26)-(D26) -> 1072.15 | F26: =IF(D26=0,"",(C26)/(D26)) -> 1.0428116 | G26: =((((G21)+(G22))+(G23))+(G24))+(G25) -> 21524.42 | H26: =((((H21)+(H22))+(H23))+(H24))+(H25) -> 25043.44 | I26: =(G26)-(H26) -> -3519.02 | J26: =IF(H26=0,"",(G26)/(H26)) -> 0.85948336 | K26: =((((K21)+(K22))+(K23))+(K24))+(K25) -> 26620.13 | L26: =((((L21)+(L22))+(L23))+(L24))+(L25) -> 25043.44 | M26: =(K26)-(L26) -> 1576.69 | N26: =IF(L26=0,"",(K26)/(L26)) -> 1.0629582 | O26: =((C26)+(G26))+(K26) -> 74260.14 | P26: =((D26)+(H26))+(L26) -> 75130.32 | Q26: =(O26)-(P26) -> -870.18 | R26: =IF(P26=0,"",(O26)/(P26)) -> 0.98841773 | T26: =K26/$K$11 -> 0.092217159 | U26: =L26/$L$11 -> 0.072414767
B27: 6130 Staff Training & Development | C27: =1583.92 -> 1583.92 | D27: =100 -> 100 | E27: =(C27)-(D27) -> 1483.92 | F27: =IF(D27=0,"",(C27)/(D27)) -> 15.8392 | G27: =-1083.92 -> -1083.92 | H27: =100 -> 100 | I27: =(G27)-(H27) -> -1183.92 | J27: =IF(H27=0,"",(G27)/(H27)) -> -10.8392 | K27: =2632.67 -> 2632.67 | L27: =100 -> 100 | M27: =(K27)-(L27) -> 2532.67 | N27: =IF(L27=0,"",(K27)/(L27)) -> 26.3267 | O27: =((C27)+(G27))+(K27) -> 3132.67 | P27: =((D27)+(H27))+(L27) -> 300 | Q27: =(O27)-(P27) -> 2832.67 | R27: =IF(P27=0,"",(O27)/(P27)) -> 10.442233
B28: 6135 Payroll Processing Fees | C28: =919.2 -> 919.2 | D28: =830.14 -> 830.14 | E28: =(C28)-(D28) -> 89.06 | F28: =IF(D28=0,"",(C28)/(D28)) -> 1.1072831 | G28: =883.2 -> 883.2 | H28: =830.14 -> 830.14 | I28: =(G28)-(H28) -> 53.06 | J28: =IF(H28=0,"",(G28)/(H28)) -> 1.0639169 | K28: =956 -> 956 | L28: =830.14 -> 830.14 | M28: =(K28)-(L28) -> 125.86 | N28: =IF(L28=0,"",(K28)/(L28)) -> 1.151613 | O28: =((C28)+(G28))+(K28) -> 2758.4 | P28: =((D28)+(H28))+(L28) -> 2490.42 | Q28: =(O28)-(P28) -> 267.98 | R28: =IF(P28=0,"",(O28)/(P28)) -> 1.1076043
B29: 6150 Employee Reimbursements | C29: =767.58 -> 767.58 | D29: =1647.22 -> 1647.22 | E29: =(C29)-(D29) -> -879.64 | F29: =IF(D29=0,"",(C29)/(D29)) -> 0.46598511 | G29: =63.72 -> 63.72 | H29: =1647.22 -> 1647.22 | I29: =(G29)-(H29) -> -1583.5 | J29: =IF(H29=0,"",(G29)/(H29)) -> 0.038683357 | K29: =0 -> 0 | L29: =1647.22 -> 1647.22 | M29: =(K29)-(L29) -> -1647.22 | N29: =IF(L29=0,"",(K29)/(L29)) -> 0 | O29: =((C29)+(G29))+(K29) -> 831.3 | P29: =((D29)+(H29))+(L29) -> 4941.66 | Q29: =(O29)-(P29) -> -4110.36 | R29: =IF(P29=0,"",(O29)/(P29)) -> 0.16822282
B30: 6155 Employee Gift | C30: =103 -> 103 | D30: =250 -> 250 | E30: =(C30)-(D30) -> -147 | F30: =IF(D30=0,"",(C30)/(D30)) -> 0.412 | G30: =103 -> 103 | H30: =250 -> 250 | I30: =(G30)-(H30) -> -147 | J30: =IF(H30=0,"",(G30)/(H30)) -> 0.412 | L30: =250 -> 250 | M30: =(K30)-(L30) -> -250 | N30: =IF(L30=0,"",(K30)/(L30)) -> 0 | O30: =((C30)+(G30))+(K30) -> 206 | P30: =((D30)+(H30))+(L30) -> 750 | Q30: =(O30)-(P30) -> -544 | R30: =IF(P30=0,"",(O30)/(P30)) -> 0.27466667
B31: 6200 Professional Fees | E31: =(C31)-(D31) -> 0 | F31: =IF(D31=0,"",(C31)/(D31)) | I31: =(G31)-(H31) -> 0 | J31: =IF(H31=0,"",(G31)/(H31)) | M31: =(K31)-(L31) -> 0 | N31: =IF(L31=0,"",(K31)/(L31)) | O31: =((C31)+(G31))+(K31) -> 0 | P31: =((D31)+(H31))+(L31) -> 0 | Q31: =(O31)-(P31) -> 0 | R31: =IF(P31=0,"",(O31)/(P31))
B32: 6205 Legal Fees | C32: =31.59 -> 31.59 | D32: =0 -> 0 | E32: =(C32)-(D32) -> 31.59 | F32: =IF(D32=0,"",(C32)/(D32)) | G32: =10.41 -> 10.41 | H32: =0 -> 0 | I32: =(G32)-(H32) -> 10.41 | J32: =IF(H32=0,"",(G32)/(H32)) | K32: =6296.82 -> 6296.82 | L32: =0 -> 0 | M32: =(K32)-(L32) -> 6296.82 | N32: =IF(L32=0,"",(K32)/(L32)) | O32: =((C32)+(G32))+(K32) -> 6338.82 | P32: =((D32)+(H32))+(L32) -> 0 | Q32: =(O32)-(P32) -> 6338.82 | R32: =IF(P32=0,"",(O32)/(P32))
B33: 6210 IT Fees | C33: =2400 -> 2400 | D33: =2400 -> 2400 | E33: =(C33)-(D33) -> 0 | F33: =IF(D33=0,"",(C33)/(D33)) -> 1 | G33: =2400 -> 2400 | H33: =2400 -> 2400 | I33: =(G33)-(H33) -> 0 | J33: =IF(H33=0,"",(G33)/(H33)) -> 1 | K33: =2400 -> 2400 | L33: =2400 -> 2400 | M33: =(K33)-(L33) -> 0 | N33: =IF(L33=0,"",(K33)/(L33)) -> 1 | O33: =((C33)+(G33))+(K33) -> 7200 | P33: =((D33)+(H33))+(L33) -> 7200 | Q33: =(O33)-(P33) -> 0 | R33: =IF(P33=0,"",(O33)/(P33)) -> 1
B34: 6215 Accounting Fees | C34: =1000 -> 1000 | D34: =1000 -> 1000 | E34: =(C34)-(D34) -> 0 | F34: =IF(D34=0,"",(C34)/(D34)) -> 1 | G34: =1000 -> 1000 | H34: =1000 -> 1000 | I34: =(G34)-(H34) -> 0 | J34: =IF(H34=0,"",(G34)/(H34)) -> 1 | K34: =1093 -> 1093 | L34: =1000 -> 1000 | M34: =(K34)-(L34) -> 93 | N34: =IF(L34=0,"",(K34)/(L34)) -> 1.093 | O34: =((C34)+(G34))+(K34) -> 3093 | P34: =((D34)+(H34))+(L34) -> 3000 | Q34: =(O34)-(P34) -> 93 | R34: =IF(P34=0,"",(O34)/(P34)) -> 1.031
B35: 6220 Professional and Consulting Fees | C35: =1710 -> 1710 | D35: =2500 -> 2500 | E35: =(C35)-(D35) -> -790 | F35: =IF(D35=0,"",(C35)/(D35)) -> 0.684 | G35: =7200 -> 7200 | H35: =2500 -> 2500 | I35: =(G35)-(H35) -> 4700 | J35: =IF(H35=0,"",(G35)/(H35)) -> 2.88 | K35: =3639.99 -> 3639.99 | L35: =2500 -> 2500 | M35: =(K35)-(L35) -> 1139.99 | N35: =IF(L35=0,"",(K35)/(L35)) -> 1.455996 | O35: =((C35)+(G35))+(K35) -> 12549.99 | P35: =((D35)+(H35))+(L35) -> 7500 | Q35: =(O35)-(P35) -> 5049.99 | R35: =IF(P35=0,"",(O35)/(P35)) -> 1.673332 | S35: The fees paid to AR CPA for the 2025 tax return, amounting to $5,500, have been recorded here, which is why the cost is higher in Feb ’26. To smooth this impact in 2026, we have started accruing $500.00 per month.
B36: Total 6200 Professional Fees | C36: =((((C31)+(C32))+(C33))+(C34))+(C35) -> 5141.59 | D36: =((((D31)+(D32))+(D33))+(D34))+(D35) -> 5900 | E36: =(C36)-(D36) -> -758.41 | F36: =IF(D36=0,"",(C36)/(D36)) -> 0.87145593 | G36: =((((G31)+(G32))+(G33))+(G34))+(G35) -> 10610.41 | H36: =((((H31)+(H32))+(H33))+(H34))+(H35) -> 5900 | I36: =(G36)-(H36) -> 4710.41 | J36: =IF(H36=0,"",(G36)/(H36)) -> 1.7983746 | K36: =((((K31)+(K32))+(K33))+(K34))+(K35) -> 13429.81 | L36: =((((L31)+(L32))+(L33))+(L34))+(L35) -> 5900 | M36: =(K36)-(L36) -> 7529.81 | N36: =IF(L36=0,"",(K36)/(L36)) -> 2.276239 | O36: =((C36)+(G36))+(K36) -> 29181.81 | P36: =((D36)+(H36))+(L36) -> 17700 | Q36: =(O36)-(P36) -> 11481.81 | R36: =IF(P36=0,"",(O36)/(P36)) -> 1.6486898 | T36: =K36/$K$11 -> 0.046523399 | U36: =L36/$L$11 -> 0.017060241
B37: 6300 Shareholder's Compensation | E37: =(C37)-(D37) -> 0 | F37: =IF(D37=0,"",(C37)/(D37)) | I37: =(G37)-(H37) -> 0 | J37: =IF(H37=0,"",(G37)/(H37)) | M37: =(K37)-(L37) -> 0 | N37: =IF(L37=0,"",(K37)/(L37)) | O37: =((C37)+(G37))+(K37) -> 0 | P37: =((D37)+(H37))+(L37) -> 0 | Q37: =(O37)-(P37) -> 0 | R37: =IF(P37=0,"",(O37)/(P37))
B38: 6305 Shareholder's Wages & Salaries | C38: =12500 -> 12500 | D38: =10000 -> 10000 | E38: =(C38)-(D38) -> 2500 | F38: =IF(D38=0,"",(C38)/(D38)) -> 1.25 | G38: =10000 -> 10000 | H38: =10000 -> 10000 | I38: =(G38)-(H38) -> 0 | J38: =IF(H38=0,"",(G38)/(H38)) -> 1 | K38: =11071.43 -> 11071.43 | L38: =10000 -> 10000 | M38: =(K38)-(L38) -> 1071.43 | N38: =IF(L38=0,"",(K38)/(L38)) -> 1.107143 | O38: =((C38)+(G38))+(K38) -> 33571.43 | P38: =((D38)+(H38))+(L38) -> 30000 | Q38: =(O38)-(P38) -> 3571.43 | R38: =IF(P38=0,"",(O38)/(P38)) -> 1.1190477
B39: 6310 Shareholder's Health Insurance | C39: =252.75 -> 252.75 | D39: =252 -> 252 | E39: =(C39)-(D39) -> 0.75 | F39: =IF(D39=0,"",(C39)/(D39)) -> 1.0029762 | G39: =252.75 -> 252.75 | H39: =252 -> 252 | I39: =(G39)-(H39) -> 0.75 | J39: =IF(H39=0,"",(G39)/(H39)) -> 1.0029762 | K39: =252.75 -> 252.75 | L39: =252 -> 252 | M39: =(K39)-(L39) -> 0.75 | N39: =IF(L39=0,"",(K39)/(L39)) -> 1.0029762 | O39: =((C39)+(G39))+(K39) -> 758.25 | P39: =((D39)+(H39))+(L39) -> 756 | Q39: =(O39)-(P39) -> 2.25 | R39: =IF(P39=0,"",(O39)/(P39)) -> 1.0029762
B40: 6315 Shareholder's Payroll Taxes | C40: =991.15 -> 991.15 | D40: =800 -> 800 | E40: =(C40)-(D40) -> 191.15 | F40: =IF(D40=0,"",(C40)/(D40)) -> 1.2389375 | G40: =765 -> 765 | H40: =800 -> 800 | I40: =(G40)-(H40) -> -35 | J40: =IF(H40=0,"",(G40)/(H40)) -> 0.95625 | K40: =846.96 -> 846.96 | L40: =800 -> 800 | M40: =(K40)-(L40) -> 46.96 | N40: =IF(L40=0,"",(K40)/(L40)) -> 1.0587 | O40: =((C40)+(G40))+(K40) -> 2603.11 | P40: =((D40)+(H40))+(L40) -> 2400 | Q40: =(O40)-(P40) -> 203.11 | R40: =IF(P40=0,"",(O40)/(P40)) -> 1.0846292
B41: 6320 Shareholder's 401(k) Employer Contributions | C41: =437.5 -> 437.5 | D41: =379.17 -> 379.17 | E41: =(C41)-(D41) -> 58.33 | F41: =IF(D41=0,"",(C41)/(D41)) -> 1.153836 | G41: =350 -> 350 | H41: =379.17 -> 379.17 | I41: =(G41)-(H41) -> -29.17 | J41: =IF(H41=0,"",(G41)/(H41)) -> 0.92306881 | K41: =387.5 -> 387.5 | L41: =379.17 -> 379.17 | M41: =(K41)-(L41) -> 8.33 | N41: =IF(L41=0,"",(K41)/(L41)) -> 1.021969 | O41: =((C41)+(G41))+(K41) -> 1175 | P41: =((D41)+(H41))+(L41) -> 1137.51 | Q41: =(O41)-(P41) -> 37.49 | R41: =IF(P41=0,"",(O41)/(P41)) -> 1.032958
B42: Total 6300 Shareholder's Compensation | C42: =((((C37)+(C38))+(C39))+(C40))+(C41) -> 14181.4 | D42: =((((D37)+(D38))+(D39))+(D40))+(D41) -> 11431.17 | E42: =(C42)-(D42) -> 2750.23 | F42: =IF(D42=0,"",(C42)/(D42)) -> 1.2405904 | G42: =((((G37)+(G38))+(G39))+(G40))+(G41) -> 11367.75 | H42: =((((H37)+(H38))+(H39))+(H40))+(H41) -> 11431.17 | I42: =(G42)-(H42) -> -63.42 | J42: =IF(H42=0,"",(G42)/(H42)) -> 0.99445201 | K42: =((((K37)+(K38))+(K39))+(K40))+(K41) -> 12558.64 | L42: =((((L37)+(L38))+(L39))+(L40))+(L41) -> 11431.17 | M42: =(K42)-(L42) -> 1127.47 | N42: =IF(L42=0,"",(K42)/(L42)) -> 1.0986312 | O42: =((C42)+(G42))+(K42) -> 38107.79 | P42: =((D42)+(H42))+(L42) -> 34293.51 | Q42: =(O42)-(P42) -> 3814.28 | R42: =IF(P42=0,"",(O42)/(P42)) -> 1.1112245 | T42: =K42/$K$11 -> 0.043505501 | U42: =L42/$L$11 -> 0.033053986
B43: 6400 Office Expense | E43: =(C43)-(D43) -> 0 | F43: =IF(D43=0,"",(C43)/(D43)) | I43: =(G43)-(H43) -> 0 | J43: =IF(H43=0,"",(G43)/(H43)) | M43: =(K43)-(L43) -> 0 | N43: =IF(L43=0,"",(K43)/(L43)) | O43: =((C43)+(G43))+(K43) -> 0 | P43: =((D43)+(H43))+(L43) -> 0 | Q43: =(O43)-(P43) -> 0 | R43: =IF(P43=0,"",(O43)/(P43))
B44: 6405 Office Equipment | C44: =2828.96 -> 2828.96 | D44: =3458.33 -> 3458.33 | E44: =(C44)-(D44) -> -629.37 | F44: =IF(D44=0,"",(C44)/(D44)) -> 0.81801332 | G44: =12567.45 -> 12567.45 | H44: =3458.33 -> 3458.33 | I44: =(G44)-(H44) -> 9109.12 | J44: =IF(H44=0,"",(G44)/(H44)) -> 3.6339649 | K44: =5427.23 -> 5427.23 | L44: =3458.33 -> 3458.33 | M44: =(K44)-(L44) -> 1968.9 | N44: =IF(L44=0,"",(K44)/(L44)) -> 1.569321 | O44: =((C44)+(G44))+(K44) -> 20823.64 | P44: =((D44)+(H44))+(L44) -> 10374.99 | Q44: =(O44)-(P44) -> 10448.65 | R44: =IF(P44=0,"",(O44)/(P44)) -> 2.0070998 | S44: We have recorded the Amazon transactions of $3,559.00 and $3,038.00 in Feb ’26, as they are below the capitalization threshold and relate to replacement studio equipment following the burglary. The expense reclassification was completed due to delayed responses on the AMEX spreadsheet.
B45: 6410 Office Supplies | C45: =2019.32 -> 2019.32 | D45: =6916.67 -> 6916.67 | E45: =(C45)-(D45) -> -4897.35 | F45: =IF(D45=0,"",(C45)/(D45)) -> 0.29194974 | G45: =2029.23 -> 2029.23 | H45: =6916.67 -> 6916.67 | I45: =(G45)-(H45) -> -4887.44 | J45: =IF(H45=0,"",(G45)/(H45)) -> 0.29338251 | K45: =2096.91 -> 2096.91 | L45: =6916.67 -> 6916.67 | M45: =(K45)-(L45) -> -4819.76 | N45: =IF(L45=0,"",(K45)/(L45)) -> 0.30316756 | O45: =((C45)+(G45))+(K45) -> 6145.46 | P45: =((D45)+(H45))+(L45) -> 20750.01 | Q45: =(O45)-(P45) -> -14604.55 | R45: =IF(P45=0,"",(O45)/(P45)) -> 0.2961666
B46: 6415 Phone and Internet Expense - Office | C46: =304.87 -> 304.87 | D46: =340 -> 340 | E46: =(C46)-(D46) -> -35.13 | F46: =IF(D46=0,"",(C46)/(D46)) -> 0.89667647 | G46: =314.87 -> 314.87 | H46: =340 -> 340 | I46: =(G46)-(H46) -> -25.13 | J46: =IF(H46=0,"",(G46)/(H46)) -> 0.92608824 | K46: =306.91 -> 306.91 | L46: =340 -> 340 | M46: =(K46)-(L46) -> -33.09 | N46: =IF(L46=0,"",(K46)/(L46)) -> 0.90267647 | O46: =((C46)+(G46))+(K46) -> 926.65 | P46: =((D46)+(H46))+(L46) -> 1020 | Q46: =(O46)-(P46) -> -93.35 | R46: =IF(P46=0,"",(O46)/(P46)) -> 0.90848039
B47: 6420 Office Repairs & Maintenance | C47: =4053.35 -> 4053.35 | D47: =1729.17 -> 1729.17 | E47: =(C47)-(D47) -> 2324.18 | F47: =IF(D47=0,"",(C47)/(D47)) -> 2.3441015 | G47: =2209.77 -> 2209.77 | H47: =1729.17 -> 1729.17 | I47: =(G47)-(H47) -> 480.6 | J47: =IF(H47=0,"",(G47)/(H47)) -> 1.2779368 | K47: =1473.75 -> 1473.75 | L47: =1729.17 -> 1729.17 | M47: =(K47)-(L47) -> -255.42 | N47: =IF(L47=0,"",(K47)/(L47)) -> 0.85228751 | O47: =((C47)+(G47))+(K47) -> 7736.87 | P47: =((D47)+(H47))+(L47) -> 5187.51 | Q47: =(O47)-(P47) -> 2549.36 | R47: =IF(P47=0,"",(O47)/(P47)) -> 1.4914419
B48: Total 6400 Office Expense | C48: =((((C43)+(C44))+(C45))+(C46))+(C47) -> 9206.5 | D48: =((((D43)+(D44))+(D45))+(D46))+(D47) -> 12444.17 | E48: =(C48)-(D48) -> -3237.67 | F48: =IF(D48=0,"",(C48)/(D48)) -> 0.73982435 | G48: =((((G43)+(G44))+(G45))+(G46))+(G47) -> 17121.32 | H48: =((((H43)+(H44))+(H45))+(H46))+(H47) -> 12444.17 | I48: =(G48)-(H48) -> 4677.15 | J48: =IF(H48=0,"",(G48)/(H48)) -> 1.3758507 | K48: =((((K43)+(K44))+(K45))+(K46))+(K47) -> 9304.8 | L48: =((((L43)+(L44))+(L45))+(L46))+(L47) -> 12444.17 | M48: =(K48)-(L48) -> -3139.37 | N48: =IF(L48=0,"",(K48)/(L48)) -> 0.74772363 | O48: =((C48)+(G48))+(K48) -> 35632.62 | P48: =((D48)+(H48))+(L48) -> 37332.51 | Q48: =(O48)-(P48) -> -1699.89 | R48: =IF(P48=0,"",(O48)/(P48)) -> 0.95446623 | T48: =K48/$K$11 -> 0.032233585 | U48: =L48/$L$11 -> 0.035983143
B49: 6500 Facility Expense | E49: =(C49)-(D49) -> 0 | F49: =IF(D49=0,"",(C49)/(D49)) | I49: =(G49)-(H49) -> 0 | J49: =IF(H49=0,"",(G49)/(H49)) | M49: =(K49)-(L49) -> 0 | N49: =IF(L49=0,"",(K49)/(L49)) | O49: =((C49)+(G49))+(K49) -> 0 | P49: =((D49)+(H49))+(L49) -> 0 | Q49: =(O49)-(P49) -> 0 | R49: =IF(P49=0,"",(O49)/(P49))
B50: 6505 Rent Expense | C50: =14266.06 -> 14266.06 | D50: =16760.06 -> 16760.06 | E50: =(C50)-(D50) -> -2494 | F50: =IF(D50=0,"",(C50)/(D50)) -> 0.85119385 | G50: =16795.81 -> 16795.81 | H50: =16760.06 -> 16760.06 | I50: =(G50)-(H50) -> 35.75 | J50: =IF(H50=0,"",(G50)/(H50)) -> 1.002133 | K50: =16795.81 -> 16795.81 | L50: =16760.06 -> 16760.06 | M50: =(K50)-(L50) -> 35.75 | N50: =IF(L50=0,"",(K50)/(L50)) -> 1.002133 | O50: =((C50)+(G50))+(K50) -> 47857.68 | P50: =((D50)+(H50))+(L50) -> 50280.18 | Q50: =(O50)-(P50) -> -2422.5 | R50: =IF(P50=0,"",(O50)/(P50)) -> 0.95181998
B51: 6510 CAM Charges | C51: =4341.48 -> 4341.48 | D51: =4341.48 -> 4341.48 | E51: =(C51)-(D51) -> 0 | F51: =IF(D51=0,"",(C51)/(D51)) -> 1 | G51: =4701.4 -> 4701.4 | H51: =4341.48 -> 4341.48 | I51: =(G51)-(H51) -> 359.92 | J51: =IF(H51=0,"",(G51)/(H51)) -> 1.0829026 | K51: =4521.44 -> 4521.44 | L51: =4341.48 -> 4341.48 | M51: =(K51)-(L51) -> 179.96 | N51: =IF(L51=0,"",(K51)/(L51)) -> 1.0414513 | O51: =((C51)+(G51))+(K51) -> 13564.32 | P51: =((D51)+(H51))+(L51) -> 13024.44 | Q51: =(O51)-(P51) -> 539.88 | R51: =IF(P51=0,"",(O51)/(P51)) -> 1.0414513
B52: 6515 Utilities | C52: =4356.62 -> 4356.62 | D52: =6916.67 -> 6916.67 | E52: =(C52)-(D52) -> -2560.05 | F52: =IF(D52=0,"",(C52)/(D52)) -> 0.62987247 | G52: =6180.17 -> 6180.17 | H52: =6916.67 -> 6916.67 | I52: =(G52)-(H52) -> -736.5 | J52: =IF(H52=0,"",(G52)/(H52)) -> 0.89351812 | K52: =7303.23 -> 7303.23 | L52: =6916.67 -> 6916.67 | M52: =(K52)-(L52) -> 386.56 | N52: =IF(L52=0,"",(K52)/(L52)) -> 1.0558882 | O52: =((C52)+(G52))+(K52) -> 17840.02 | P52: =((D52)+(H52))+(L52) -> 20750.01 | Q52: =(O52)-(P52) -> -2909.99 | R52: =IF(P52=0,"",(O52)/(P52)) -> 0.85975959
B53: 6520 Business Insurance | C53: =1232.07 -> 1232.07 | D53: =1232.11 -> 1232.11 | E53: =(C53)-(D53) -> -0.04 | F53: =IF(D53=0,"",(C53)/(D53)) -> 0.99996754 | G53: =1255.58 -> 1255.58 | H53: =1232.11 -> 1232.11 | I53: =(G53)-(H53) -> 23.47 | J53: =IF(H53=0,"",(G53)/(H53)) -> 1.0190486 | K53: =1255.56 -> 1255.56 | L53: =1232.11 -> 1232.11 | M53: =(K53)-(L53) -> 23.45 | N53: =IF(L53=0,"",(K53)/(L53)) -> 1.0190324 | O53: =((C53)+(G53))+(K53) -> 3743.21 | P53: =((D53)+(H53))+(L53) -> 3696.33 | Q53: =(O53)-(P53) -> 46.88 | R53: =IF(P53=0,"",(O53)/(P53)) -> 1.0126829
B54: 6540 HP Lease Expense | D54: =7500 -> 7500 | E54: =(C54)-(D54) -> -7500 | F54: =IF(D54=0,"",(C54)/(D54)) -> 0 | H54: =7500 -> 7500 | I54: =(G54)-(H54) -> -7500 | J54: =IF(H54=0,"",(G54)/(H54)) -> 0 | K54: =8503.67 -> 8503.67 | L54: =7500 -> 7500 | M54: =(K54)-(L54) -> 1003.67 | N54: =IF(L54=0,"",(K54)/(L54)) -> 1.1338227 | O54: =((C54)+(G54))+(K54) -> 8503.67 | P54: =((D54)+(H54))+(L54) -> 22500 | Q54: =(O54)-(P54) -> -13996.33 | R54: =IF(P54=0,"",(O54)/(P54)) -> 0.37794089
B55: Total 6500 Facility Expense | C55: =(((((C49)+(C50))+(C51))+(C52))+(C53))+(C54) -> 24196.23 | D55: =(((((D49)+(D50))+(D51))+(D52))+(D53))+(D54) -> 36750.32 | E55: =(C55)-(D55) -> -12554.09 | F55: =IF(D55=0,"",(C55)/(D55)) -> 0.65839508 | G55: =(((((G49)+(G50))+(G51))+(G52))+(G53))+(G54) -> 28932.96 | H55: =(((((H49)+(H50))+(H51))+(H52))+(H53))+(H54) -> 36750.32 | I55: =(G55)-(H55) -> -7817.36 | J55: =IF(H55=0,"",(G55)/(H55)) -> 0.78728457 | K55: =(((((K49)+(K50))+(K51))+(K52))+(K53))+(K54) -> 38379.71 | L55: =(((((L49)+(L50))+(L51))+(L52))+(L53))+(L54) -> 36750.32 | M55: =(K55)-(L55) -> 1629.39 | N55: =IF(L55=0,"",(K55)/(L55)) -> 1.0443368 | O55: =((C55)+(G55))+(K55) -> 91508.9 | P55: =((D55)+(H55))+(L55) -> 110250.96 | Q55: =(O55)-(P55) -> -18742.06 | R55: =IF(P55=0,"",(O55)/(P55)) -> 0.83000547 | T55: =K55/$K$11 -> 0.13295457 | U55: =L55/$L$11 -> 0.10626599
B56: 6600 Other Operating Expenses | E56: =(C56)-(D56) -> 0 | F56: =IF(D56=0,"",(C56)/(D56)) | I56: =(G56)-(H56) -> 0 | J56: =IF(H56=0,"",(G56)/(H56)) | M56: =(K56)-(L56) -> 0 | N56: =IF(L56=0,"",(K56)/(L56)) | O56: =((C56)+(G56))+(K56) -> 0 | P56: =((D56)+(H56))+(L56) -> 0 | Q56: =(O56)-(P56) -> 0 | R56: =IF(P56=0,"",(O56)/(P56))
B57: 6605 Advertising & Marketing | C57: =1725.05 -> 1725.05 | D57: =5187.5 -> 5187.5 | E57: =(C57)-(D57) -> -3462.45 | F57: =IF(D57=0,"",(C57)/(D57)) -> 0.33253976 | G57: =3643.59 -> 3643.59 | H57: =5187.5 -> 5187.5 | I57: =(G57)-(H57) -> -1543.91 | J57: =IF(H57=0,"",(G57)/(H57)) -> 0.7023788 | K57: =5138.74 -> 5138.74 | L57: =5187.5 -> 5187.5 | M57: =(K57)-(L57) -> -48.76 | N57: =IF(L57=0,"",(K57)/(L57)) -> 0.99060048 | O57: =((C57)+(G57))+(K57) -> 10507.38 | P57: =((D57)+(H57))+(L57) -> 15562.5 | Q57: =(O57)-(P57) -> -5055.12 | R57: =IF(P57=0,"",(O57)/(P57)) -> 0.67517301
B58: 6610 Software Costs | C58: =4441.06 -> 4441.06 | D58: =3376.93 -> 3376.93 | E58: =(C58)-(D58) -> 1064.13 | F58: =IF(D58=0,"",(C58)/(D58)) -> 1.3151176 | G58: =5647.87 -> 5647.87 | H58: =3376.93 -> 3376.93 | I58: =(G58)-(H58) -> 2270.94 | J58: =IF(H58=0,"",(G58)/(H58)) -> 1.6724865 | K58: =3191.08 -> 3191.08 | L58: =3376.93 -> 3376.93 | M58: =(K58)-(L58) -> -185.85 | N58: =IF(L58=0,"",(K58)/(L58)) -> 0.94496481 | O58: =((C58)+(G58))+(K58) -> 13280.01 | P58: =((D58)+(H58))+(L58) -> 10130.79 | Q58: =(O58)-(P58) -> 3149.22 | R58: =IF(P58=0,"",(O58)/(P58)) -> 1.3108563
B59: 6615 Vehicle Expense | C59: =535.32 -> 535.32 | D59: =1729.17 -> 1729.17 | E59: =(C59)-(D59) -> -1193.85 | F59: =IF(D59=0,"",(C59)/(D59)) -> 0.30958205 | G59: =449.88 -> 449.88 | H59: =1729.17 -> 1729.17 | I59: =(G59)-(H59) -> -1279.29 | J59: =IF(H59=0,"",(G59)/(H59)) -> 0.26017106 | K59: =651.25 -> 651.25 | L59: =1729.17 -> 1729.17 | M59: =(K59)-(L59) -> -1077.92 | N59: =IF(L59=0,"",(K59)/(L59)) -> 0.37662578 | O59: =((C59)+(G59))+(K59) -> 1636.45 | P59: =((D59)+(H59))+(L59) -> 5187.51 | Q59: =(O59)-(P59) -> -3551.06 | R59: =IF(P59=0,"",(O59)/(P59)) -> 0.31545963
B60: 6620 Auto Lease Expense | C60: =2320.64 -> 2320.64 | D60: =2320.64 -> 2320.64 | E60: =(C60)-(D60) -> 0 | F60: =IF(D60=0,"",(C60)/(D60)) -> 1 | G60: =2320.64 -> 2320.64 | H60: =2320.64 -> 2320.64 | I60: =(G60)-(H60) -> 0 | J60: =IF(H60=0,"",(G60)/(H60)) -> 1 | K60: =2320.64 -> 2320.64 | L60: =2320.64 -> 2320.64 | M60: =(K60)-(L60) -> 0 | N60: =IF(L60=0,"",(K60)/(L60)) -> 1 | O60: =((C60)+(G60))+(K60) -> 6961.92 | P60: =((D60)+(H60))+(L60) -> 6961.92 | Q60: =(O60)-(P60) -> 0 | R60: =IF(P60=0,"",(O60)/(P60)) -> 1
B61: 6625 Client Gifts | D61: =425 -> 425 | E61: =(C61)-(D61) -> -425 | F61: =IF(D61=0,"",(C61)/(D61)) -> 0 | H61: =425 -> 425 | I61: =(G61)-(H61) -> -425 | J61: =IF(H61=0,"",(G61)/(H61)) -> 0 | L61: =425 -> 425 | M61: =(K61)-(L61) -> -425 | N61: =IF(L61=0,"",(K61)/(L61)) -> 0 | O61: =((C61)+(G61))+(K61) -> 0 | P61: =((D61)+(H61))+(L61) -> 1275 | Q61: =(O61)-(P61) -> -1275 | R61: =IF(P61=0,"",(O61)/(P61)) -> 0
B62: 6630 Shipping & Postage | C62: =1488.33 -> 1488.33 | D62: =691.67 -> 691.67 | E62: =(C62)-(D62) -> 796.66 | F62: =IF(D62=0,"",(C62)/(D62)) -> 2.151792 | G62: =390.63 -> 390.63 | H62: =691.67 -> 691.67 | I62: =(G62)-(H62) -> -301.04 | J62: =IF(H62=0,"",(G62)/(H62)) -> 0.56476354 | K62: =1186.01 -> 1186.01 | L62: =691.67 -> 691.67 | M62: =(K62)-(L62) -> 494.34 | N62: =IF(L62=0,"",(K62)/(L62)) -> 1.714705 | O62: =((C62)+(G62))+(K62) -> 3064.97 | P62: =((D62)+(H62))+(L62) -> 2075.01 | Q62: =(O62)-(P62) -> 989.96 | R62: =IF(P62=0,"",(O62)/(P62)) -> 1.4770869
B63: 6635 Travel - Management | C63: =-655.24 -> -655.24 | D63: =1037.5 -> 1037.5 | E63: =(C63)-(D63) -> -1692.74 | F63: =IF(D63=0,"",(C63)/(D63)) -> -0.63155663 | G63: =1941.62 -> 1941.62 | H63: =1037.5 -> 1037.5 | I63: =(G63)-(H63) -> 904.12 | J63: =IF(H63=0,"",(G63)/(H63)) -> 1.871441 | K63: =5187.04 -> 5187.04 | L63: =1037.5 -> 1037.5 | M63: =(K63)-(L63) -> 4149.54 | N63: =IF(L63=0,"",(K63)/(L63)) -> 4.9995566 | O63: =((C63)+(G63))+(K63) -> 6473.42 | P63: =((D63)+(H63))+(L63) -> 3112.5 | Q63: =(O63)-(P63) -> 3360.92 | R63: =IF(P63=0,"",(O63)/(P63)) -> 2.0798137
B64: 6640 Bank Service Charges | C64: =1734.63 -> 1734.63 | D64: =345.83 -> 345.83 | E64: =(C64)-(D64) -> 1388.8 | F64: =IF(D64=0,"",(C64)/(D64)) -> 5.0158459 | G64: =1457.61 -> 1457.61 | H64: =345.83 -> 345.83 | I64: =(G64)-(H64) -> 1111.78 | J64: =IF(H64=0,"",(G64)/(H64)) -> 4.2148165 | K64: =1721.32 -> 1721.32 | L64: =345.83 -> 345.83 | M64: =(K64)-(L64) -> 1375.49 | N64: =IF(L64=0,"",(K64)/(L64)) -> 4.9773588 | O64: =((C64)+(G64))+(K64) -> 4913.56 | P64: =((D64)+(H64))+(L64) -> 1037.49 | Q64: =(O64)-(P64) -> 3876.07 | R64: =IF(P64=0,"",(O64)/(P64)) -> 4.7360071
B65: 6645 Disability & Life Insurance | C65: =171.54 -> 171.54 | D65: =171.54 -> 171.54 | E65: =(C65)-(D65) -> 0 | F65: =IF(D65=0,"",(C65)/(D65)) -> 1 | G65: =171.54 -> 171.54 | H65: =171.54 -> 171.54 | I65: =(G65)-(H65) -> 0 | J65: =IF(H65=0,"",(G65)/(H65)) -> 1 | K65: =171.54 -> 171.54 | L65: =171.54 -> 171.54 | M65: =(K65)-(L65) -> 0 | N65: =IF(L65=0,"",(K65)/(L65)) -> 1 | O65: =((C65)+(G65))+(K65) -> 514.62 | P65: =((D65)+(H65))+(L65) -> 514.62 | Q65: =(O65)-(P65) -> 0 | R65: =IF(P65=0,"",(O65)/(P65)) -> 1
B66: 6650 Business Tax & Licenses | D66: =345.83 -> 345.83 | E66: =(C66)-(D66) -> -345.83 | F66: =IF(D66=0,"",(C66)/(D66)) -> 0 | H66: =345.83 -> 345.83 | I66: =(G66)-(H66) -> -345.83 | J66: =IF(H66=0,"",(G66)/(H66)) -> 0 | L66: =345.83 -> 345.83 | M66: =(K66)-(L66) -> -345.83 | N66: =IF(L66=0,"",(K66)/(L66)) -> 0 | O66: =((C66)+(G66))+(K66) -> 0 | P66: =((D66)+(H66))+(L66) -> 1037.49 | Q66: =(O66)-(P66) -> -1037.49 | R66: =IF(P66=0,"",(O66)/(P66)) -> 0
B67: 6660 Meals and Entertainment | C67: =921.43 -> 921.43 | D67: =1729.17 -> 1729.17 | E67: =(C67)-(D67) -> -807.74 | F67: =IF(D67=0,"",(C67)/(D67)) -> 0.53287415 | G67: =1158.41 -> 1158.41 | H67: =1729.17 -> 1729.17 | I67: =(G67)-(H67) -> -570.76 | J67: =IF(H67=0,"",(G67)/(H67)) -> 0.66992256 | K67: =1305.19 -> 1305.19 | L67: =1729.17 -> 1729.17 | M67: =(K67)-(L67) -> -423.98 | N67: =IF(L67=0,"",(K67)/(L67)) -> 0.75480722 | O67: =((C67)+(G67))+(K67) -> 3385.03 | P67: =((D67)+(H67))+(L67) -> 5187.51 | Q67: =(O67)-(P67) -> -1802.48 | R67: =IF(P67=0,"",(O67)/(P67)) -> 0.65253465
B68: 6665 Dues & Subscriptions | C68: =521.74 -> 521.74 | D68: =312.32 -> 312.32 | E68: =(C68)-(D68) -> 209.42 | F68: =IF(D68=0,"",(C68)/(D68)) -> 1.6705302 | G68: =330.74 -> 330.74 | H68: =312.32 -> 312.32 | I68: =(G68)-(H68) -> 18.42 | J68: =IF(H68=0,"",(G68)/(H68)) -> 1.058978 | K68: =1225.74 -> 1225.74 | L68: =312.32 -> 312.32 | M68: =(K68)-(L68) -> 913.42 | N68: =IF(L68=0,"",(K68)/(L68)) -> 3.9246286 | O68: =((C68)+(G68))+(K68) -> 2078.22 | P68: =((D68)+(H68))+(L68) -> 936.96 | Q68: =(O68)-(P68) -> 1141.26 | R68: =IF(P68=0,"",(O68)/(P68)) -> 2.2180456
B69: 6670 QuickBooks Payments Fees | C69: =389.67 -> 389.67 | D69: =172.92 -> 172.92 | E69: =(C69)-(D69) -> 216.75 | F69: =IF(D69=0,"",(C69)/(D69)) -> 2.2534698 | G69: =346.4 -> 346.4 | H69: =172.92 -> 172.92 | I69: =(G69)-(H69) -> 173.48 | J69: =IF(H69=0,"",(G69)/(H69)) -> 2.0032385 | L69: =172.92 -> 172.92 | M69: =(K69)-(L69) -> -172.92 | N69: =IF(L69=0,"",(K69)/(L69)) -> 0 | O69: =((C69)+(G69))+(K69) -> 736.07 | P69: =((D69)+(H69))+(L69) -> 518.76 | Q69: =(O69)-(P69) -> 217.31 | R69: =IF(P69=0,"",(O69)/(P69)) -> 1.4189028
B70: 6690 Vehicle Insurance | C70: =722.8 -> 722.8 | D70: =536 -> 536 | E70: =(C70)-(D70) -> 186.8 | F70: =IF(D70=0,"",(C70)/(D70)) -> 1.3485075 | G70: =259.04 -> 259.04 | H70: =536 -> 536 | I70: =(G70)-(H70) -> -276.96 | J70: =IF(H70=0,"",(G70)/(H70)) -> 0.48328358 | K70: =482.82 -> 482.82 | L70: =536 -> 536 | M70: =(K70)-(L70) -> -53.18 | N70: =IF(L70=0,"",(K70)/(L70)) -> 0.90078358 | O70: =((C70)+(G70))+(K70) -> 1464.66 | P70: =((D70)+(H70))+(L70) -> 1608 | Q70: =(O70)-(P70) -> -143.34 | R70: =IF(P70=0,"",(O70)/(P70)) -> 0.91085821
B71: 6700 Donations | D71: =172.92 -> 172.92 | E71: =(C71)-(D71) -> -172.92 | F71: =IF(D71=0,"",(C71)/(D71)) -> 0 | H71: =172.92 -> 172.92 | I71: =(G71)-(H71) -> -172.92 | J71: =IF(H71=0,"",(G71)/(H71)) -> 0 | L71: =172.92 -> 172.92 | M71: =(K71)-(L71) -> -172.92 | N71: =IF(L71=0,"",(K71)/(L71)) -> 0 | O71: =((C71)+(G71))+(K71) -> 0 | P71: =((D71)+(H71))+(L71) -> 518.76 | Q71: =(O71)-(P71) -> -518.76 | R71: =IF(P71=0,"",(O71)/(P71)) -> 0
B72: 6705 Bad Debt Expense | D72: =1729.17 -> 1729.17 | E72: =(C72)-(D72) -> -1729.17 | F72: =IF(D72=0,"",(C72)/(D72)) -> 0 | H72: =1729.17 -> 1729.17 | I72: =(G72)-(H72) -> -1729.17 | J72: =IF(H72=0,"",(G72)/(H72)) -> 0 | L72: =1729.17 -> 1729.17 | M72: =(K72)-(L72) -> -1729.17 | N72: =IF(L72=0,"",(K72)/(L72)) -> 0 | O72: =((C72)+(G72))+(K72) -> 0 | P72: =((D72)+(H72))+(L72) -> 5187.51 | Q72: =(O72)-(P72) -> -5187.51 | R72: =IF(P72=0,"",(O72)/(P72)) -> 0
B73: 6715 Other Miscellaneous Expense | C73: =0 -> 0 | D73: =34.58 -> 34.58 | E73: =(C73)-(D73) -> -34.58 | F73: =IF(D73=0,"",(C73)/(D73)) -> 0 | G73: =4532.6 -> 4532.6 | H73: =34.58 -> 34.58 | I73: =(G73)-(H73) -> 4498.02 | J73: =IF(H73=0,"",(G73)/(H73)) -> 131.07577 | L73: =34.58 -> 34.58 | M73: =(K73)-(L73) -> -34.58 | N73: =IF(L73=0,"",(K73)/(L73)) -> 0 | O73: =((C73)+(G73))+(K73) -> 4532.6 | P73: =((D73)+(H73))+(L73) -> 103.74 | Q73: =(O73)-(P73) -> 4428.86 | R73: =IF(P73=0,"",(O73)/(P73)) -> 43.691922
B74: Total 6600 Other Operating Expenses | C74: =(((((((((((((((((C56)+(C57))+(C58))+(C59))+(C60))+(C61))+(C62))+(C63))+(C64))+(C65))+(C66))+(C67))+(C68))+(C69))+(C70))+(C71))+(C72))+(C73) -> 14316.97 | D74: =(((((((((((((((((D56)+(D57))+(D58))+(D59))+(D60))+(D61))+(D62))+(D63))+(D64))+(D65))+(D66))+(D67))+(D68))+(D69))+(D70))+(D71))+(D72))+(D73) -> 20318.69 | E74: =(C74)-(D74) -> -6001.72 | F74: =IF(D74=0,"",(C74)/(D74)) -> 0.70462072 | G74: =(((((((((((((((((G56)+(G57))+(G58))+(G59))+(G60))+(G61))+(G62))+(G63))+(G64))+(G65))+(G66))+(G67))+(G68))+(G69))+(G70))+(G71))+(G72))+(G73) -> 22650.57 | H74: =(((((((((((((((((H56)+(H57))+(H58))+(H59))+(H60))+(H61))+(H62))+(H63))+(H64))+(H65))+(H66))+(H67))+(H68))+(H69))+(H70))+(H71))+(H72))+(H73) -> 20318.69 | I74: =(G74)-(H74) -> 2331.88 | J74: =IF(H74=0,"",(G74)/(H74)) -> 1.1147653 | K74: =(((((((((((((((((K56)+(K57))+(K58))+(K59))+(K60))+(K61))+(K62))+(K63))+(K64))+(K65))+(K66))+(K67))+(K68))+(K69))+(K70))+(K71))+(K72))+(K73) -> 22581.37 | L74: =(((((((((((((((((L56)+(L57))+(L58))+(L59))+(L60))+(L61))+(L62))+(L63))+(L64))+(L65))+(L66))+(L67))+(L68))+(L69))+(L70))+(L71))+(L72))+(L73) -> 20318.69 | M74: =(K74)-(L74) -> 2262.68 | N74: =IF(L74=0,"",(K74)/(L74)) -> 1.1113595 | O74: =((C74)+(G74))+(K74) -> 59548.91 | P74: =((D74)+(H74))+(L74) -> 60956.07 | Q74: =(O74)-(P74) -> -1407.16 | R74: =IF(P74=0,"",(O74)/(P74)) -> 0.97691518 | T74: =K74/$K$11 -> 0.078226132 | U74: =L74/$L$11 -> 0.058752839
B75: Total Expenses | C75: =(((((((((C26)+(C27))+(C28))+(C29))+(C30))+(C36))+(C42))+(C48))+(C55))+(C74) -> 96531.98 | D75: =(((((((((D26)+(D27))+(D28))+(D29))+(D30))+(D36))+(D42))+(D48))+(D55))+(D74) -> 114715.15 | E75: =(C75)-(D75) -> -18183.17 | F75: =IF(D75=0,"",(C75)/(D75)) -> 0.84149286 | G75: =(((((((((G26)+(G27))+(G28))+(G29))+(G30))+(G36))+(G42))+(G48))+(G55))+(G74) -> 112173.43 | H75: =(((((((((H26)+(H27))+(H28))+(H29))+(H30))+(H36))+(H42))+(H48))+(H55))+(H74) -> 114715.15 | I75: =(G75)-(H75) -> -2541.72 | J75: =IF(H75=0,"",(G75)/(H75)) -> 0.97784321 | K75: =(((((((((K26)+(K27))+(K28))+(K29))+(K30))+(K36))+(K42))+(K48))+(K55))+(K74) -> 126463.13 | L75: =(((((((((L26)+(L27))+(L28))+(L29))+(L30))+(L36))+(L42))+(L48))+(L55))+(L74) -> 114715.15 | M75: =(K75)-(L75) -> 11747.98 | N75: =IF(L75=0,"",(K75)/(L75)) -> 1.10241 | O75: =((C75)+(G75))+(K75) -> 335168.54 | P75: =((D75)+(H75))+(L75) -> 344145.45 | Q75: =(O75)-(P75) -> -8976.91 | R75: =IF(P75=0,"",(O75)/(P75)) -> 0.97391536 | T75: =K75/$K$11 -> 0.43809217 | U75: =L75/$L$11 -> 0.33170646
B76: Net Operating Income | C76: =(C19)-(C75) -> -24384.94 | D76: =(D19)-(D75) -> 100518.39 | E76: =(C76)-(D76) -> -124903.33 | F76: =IF(D76=0,"",(C76)/(D76)) -> -0.24259183 | G76: =(G19)-(G75) -> -11811.73 | H76: =(H19)-(H75) -> 100518.39 | I76: =(G76)-(H76) -> -112330.12 | J76: =IF(H76=0,"",(G76)/(H76)) -> -0.11750815 | K76: =(K19)-(K75) -> 16743.63 | L76: =(L19)-(L75) -> 100518.39 | M76: =(K76)-(L76) -> -83774.76 | N76: =IF(L76=0,"",(K76)/(L76)) -> 0.1665728 | O76: =((C76)+(G76))+(K76) -> -19453.04 | P76: =((D76)+(H76))+(L76) -> 301555.17 | Q76: =(O76)-(P76) -> -321008.21 | R76: =IF(P76=0,"",(O76)/(P76)) -> -0.064509058 | T76: =K76/$K$11 -> 0.058003097 | U76: =L76/$L$11 -> 0.29065559
B77: Other Income
B78: 7005 Other Miscellaneous Income | C78: =15050 -> 15050 | E78: =(C78)-(D78) -> 15050 | F78: =IF(D78=0,"",(C78)/(D78)) | I78: =(G78)-(H78) -> 0 | J78: =IF(H78=0,"",(G78)/(H78)) | K78: =639.99 -> 639.99 | M78: =(K78)-(L78) -> 639.99 | N78: =IF(L78=0,"",(K78)/(L78)) | O78: =((C78)+(G78))+(K78) -> 15689.99 | P78: =((D78)+(H78))+(L78) -> 0 | Q78: =(O78)-(P78) -> 15689.99 | R78: =IF(P78=0,"",(O78)/(P78)) | S78: Deposit received from Philips was coded as Other Income, as per Zaheer’s feedback.
B79: 7010 Other Income – Insurance Proceeds | E79: =(C79)-(D79) -> 0 | F79: =IF(D79=0,"",(C79)/(D79)) | I79: =(G79)-(H79) -> 0 | J79: =IF(H79=0,"",(G79)/(H79)) | K79: =12897.29 -> 12897.29 | M79: =(K79)-(L79) -> 12897.29 | N79: =IF(L79=0,"",(K79)/(L79)) | O79: =((C79)+(G79))+(K79) -> 12897.29 | P79: =((D79)+(H79))+(L79) -> 0 | Q79: =(O79)-(P79) -> 12897.29 | R79: =IF(P79=0,"",(O79)/(P79)) | S79: The insurance reimbursement has been recorded here, as all cameras and other items mentioned in the claim email were recorded under Equipment in the P&L.
B80: Total Other Income | C80: =(C78)+(C79) -> 15050 | D80: =(D78)+(D79) -> 0 | E80: =(C80)-(D80) -> 15050 | F80: =IF(D80=0,"",(C80)/(D80)) | G80: =(G78)+(G79) -> 0 | H80: =(H78)+(H79) -> 0 | I80: =(G80)-(H80) -> 0 | J80: =IF(H80=0,"",(G80)/(H80)) | K80: =(K78)+(K79) -> 13537.28 | L80: =(L78)+(L79) -> 0 | M80: =(K80)-(L80) -> 13537.28 | N80: =IF(L80=0,"",(K80)/(L80)) | O80: =((C80)+(G80))+(K80) -> 28587.28 | P80: =((D80)+(H80))+(L80) -> 0 | Q80: =(O80)-(P80) -> 28587.28 | R80: =IF(P80=0,"",(O80)/(P80)) | T80: =K80/$K$11 -> 0.046895695 | U80: =L80/$L$11 -> 0
B81: Other Expenses
B82: 6195 Late Fees | E82: =(C82)-(D82) -> 0 | F82: =IF(D82=0,"",(C82)/(D82)) | G82: =1816.79 -> 1816.79 | I82: =(G82)-(H82) -> 1816.79 | J82: =IF(H82=0,"",(G82)/(H82)) | K82: =17.04 -> 17.04 | M82: =(K82)-(L82) -> 17.04 | N82: =IF(L82=0,"",(K82)/(L82)) | O82: =((C82)+(G82))+(K82) -> 1833.83 | P82: =((D82)+(H82))+(L82) -> 0 | Q82: =(O82)-(P82) -> 1833.83 | R82: =IF(P82=0,"",(O82)/(P82))
B83: 7100 Interest Expense | C83: =21510.5 -> 21510.5 | D83: =16908.2 -> 16908.2 | E83: =(C83)-(D83) -> 4602.3 | F83: =IF(D83=0,"",(C83)/(D83)) -> 1.2721934 | G83: =20760 -> 20760 | H83: =16882.05 -> 16882.05 | I83: =(G83)-(H83) -> 3877.95 | J83: =IF(H83=0,"",(G83)/(H83)) -> 1.2297085 | K83: =27038.72 -> 27038.72 | L83: =16855.71 -> 16855.71 | M83: =(K83)-(L83) -> 10183.01 | N83: =IF(L83=0,"",(K83)/(L83)) -> 1.6041282 | O83: =((C83)+(G83))+(K83) -> 69309.22 | P83: =((D83)+(H83))+(L83) -> 50645.96 | Q83: =(O83)-(P83) -> 18663.26 | R83: =IF(P83=0,"",(O83)/(P83)) -> 1.3685044
B84: 7105 Interest Expense - Shareholder's Loan | C84: =9720.17 -> 9720.17 | D84: =9034.76 -> 9034.76 | E84: =(C84)-(D84) -> 685.41 | F84: =IF(D84=0,"",(C84)/(D84)) -> 1.0758637 | G84: =8887.16 -> 8887.16 | H84: =8975.11 -> 8975.11 | I84: =(G84)-(H84) -> -87.95 | J84: =IF(H84=0,"",(G84)/(H84)) -> 0.99020068 | K84: =10169.38 -> 10169.38 | L84: =8914.86 -> 8914.86 | M84: =(K84)-(L84) -> 1254.52 | N84: =IF(L84=0,"",(K84)/(L84)) -> 1.1407223 | O84: =((C84)+(G84))+(K84) -> 28776.71 | P84: =((D84)+(H84))+(L84) -> 26924.73 | Q84: =(O84)-(P84) -> 1851.98 | R84: =IF(P84=0,"",(O84)/(P84)) -> 1.0687836
B85: 7200 Depreciation Expense | C85: =4623 -> 4623 | D85: =3621.9 -> 3621.9 | E85: =(C85)-(D85) -> 1001.1 | F85: =IF(D85=0,"",(C85)/(D85)) -> 1.2764019 | G85: =4623 -> 4623 | H85: =3621.9 -> 3621.9 | I85: =(G85)-(H85) -> 1001.1 | J85: =IF(H85=0,"",(G85)/(H85)) -> 1.2764019 | K85: =4746.6 -> 4746.6 | L85: =3621.9 -> 3621.9 | M85: =(K85)-(L85) -> 1124.7 | N85: =IF(L85=0,"",(K85)/(L85)) -> 1.3105276 | O85: =((C85)+(G85))+(K85) -> 13992.6 | P85: =((D85)+(H85))+(L85) -> 10865.7 | Q85: =(O85)-(P85) -> 3126.9 | R85: =IF(P85=0,"",(O85)/(P85)) -> 1.2877771
B86: 7205 Amortization Expense | C86: =12988.8 -> 12988.8 | D86: =12988.8 -> 12988.8 | E86: =(C86)-(D86) -> 0 | F86: =IF(D86=0,"",(C86)/(D86)) -> 1 | G86: =12988.8 -> 12988.8 | H86: =12988.8 -> 12988.8 | I86: =(G86)-(H86) -> 0 | J86: =IF(H86=0,"",(G86)/(H86)) -> 1 | K86: =12988.8 -> 12988.8 | L86: =12988.8 -> 12988.8 | M86: =(K86)-(L86) -> 0 | N86: =IF(L86=0,"",(K86)/(L86)) -> 1 | O86: =((C86)+(G86))+(K86) -> 38966.4 | P86: =((D86)+(H86))+(L86) -> 38966.4 | Q86: =(O86)-(P86) -> 0 | R86: =IF(P86=0,"",(O86)/(P86)) -> 1
B87: Total Other Expenses | C87: =((((C82)+(C83))+(C84))+(C85))+(C86) -> 48842.47 | D87: =((((D82)+(D83))+(D84))+(D85))+(D86) -> 42553.66 | E87: =(C87)-(D87) -> 6288.81 | F87: =IF(D87=0,"",(C87)/(D87)) -> 1.1477854 | G87: =((((G82)+(G83))+(G84))+(G85))+(G86) -> 49075.75 | H87: =((((H82)+(H83))+(H84))+(H85))+(H86) -> 42467.86 | I87: =(G87)-(H87) -> 6607.89 | J87: =IF(H87=0,"",(G87)/(H87)) -> 1.1555974 | K87: =((((K82)+(K83))+(K84))+(K85))+(K86) -> 54960.54 | L87: =((((L82)+(L83))+(L84))+(L85))+(L86) -> 42381.27 | M87: =(K87)-(L87) -> 12579.27 | N87: =IF(L87=0,"",(K87)/(L87)) -> 1.296812 | O87: =((C87)+(G87))+(K87) -> 152878.76 | P87: =((D87)+(H87))+(L87) -> 127402.79 | Q87: =(O87)-(P87) -> 25475.97 | R87: =IF(P87=0,"",(O87)/(P87)) -> 1.199964
B88: Net Other Income | C88: =(C80)-(C87) -> -33792.47 | D88: =(D80)-(D87) -> -42553.66 | E88: =(C88)-(D88) -> 8761.19 | F88: =IF(D88=0,"",(C88)/(D88)) -> 0.7941143 | G88: =(G80)-(G87) -> -49075.75 | H88: =(H80)-(H87) -> -42467.86 | I88: =(G88)-(H88) -> -6607.89 | J88: =IF(H88=0,"",(G88)/(H88)) -> 1.1555974 | K88: =(K80)-(K87) -> -41423.26 | L88: =(L80)-(L87) -> -42381.27 | M88: =(K88)-(L88) -> 958.01 | N88: =IF(L88=0,"",(K88)/(L88)) -> 0.97739544 | O88: =((C88)+(G88))+(K88) -> -124291.48 | P88: =((D88)+(H88))+(L88) -> -127402.79 | Q88: =(O88)-(P88) -> 3111.31 | R88: =IF(P88=0,"",(O88)/(P88)) -> 0.97557895
B89: Net Income | C89: =(C76)+(C88) -> -58177.41 | D89: =(D76)+(D88) -> 57964.73 | E89: =(C89)-(D89) -> -116142.14 | F89: =IF(D89=0,"",(C89)/(D89)) -> -1.0036691 | G89: =(G76)+(G88) -> -60887.48 | H89: =(H76)+(H88) -> 58050.53 | I89: =(G89)-(H89) -> -118938.01 | J89: =IF(H89=0,"",(G89)/(H89)) -> -1.0488704 | K89: =(K76)+(K88) -> -24679.63 | L89: =(L76)+(L88) -> 58137.12 | M89: =(K89)-(L89) -> -82816.75 | N89: =IF(L89=0,"",(K89)/(L89)) -> -0.42450727 | O89: =((C89)+(G89))+(K89) -> -143744.52 | P89: =((D89)+(H89))+(L89) -> 174152.38 | Q89: =(O89)-(P89) -> -317896.9 | R89: =IF(P89=0,"",(O89)/(P89)) -> -0.82539509
B91: Net Operating Income + Other Income = EBITDA | C91: =+C76+C80 -> -9334.94 | D91: =+D76+D80 -> 100518.39 | E91: =+E76+E80 -> -109853.33 | F91: =C91/D91 -> -0.092867982 | G91: =+G76+G80 -> -11811.73 | H91: =+H76+H80 -> 100518.39 | I91: =+I76+I80 -> -112330.12 | J91: =G91/H91 -> -0.11750815 | K91: =+K76+K80 -> 30280.91 | L91: =+L76+L80 -> 100518.39 | M91: =+M76+M80 -> -70237.48 | N91: =K91/L91 -> 0.30124746 | O91: =+O76+O80 -> 9134.24 | P91: =+P76+P80 -> 301555.17 | Q91: =+Q76+Q80 -> -292420.93 | R91: =O91/P91 -> 0.030290444 | T91: =K91/$K$11 -> 0.10489879 | U91: =L91/$L$11 -> 0.29065559
B93: Less: Depreciation & Amortization | C93: =C85+C86 -> 17611.8 | D93: =D85+D86 -> 16610.7 | E93: =E85+E86 -> 1001.1 | F93: =C93/D93 -> 1.0602684 | G93: =G85+G86 -> 17611.8 | H93: =H85+H86 -> 16610.7 | I93: =I85+I86 -> 1001.1 | J93: =G93/H93 -> 1.0602684 | K93: =K85+K86 -> 17735.4 | L93: =L85+L86 -> 16610.7 | M93: =M85+M86 -> 1124.7 | N93: =K93/L93 -> 1.0677094 | O93: =O85+O86 -> 52959 | P93: =P85+P86 -> 49832.1 | Q93: =Q85+Q86 -> 3126.9 | R93: =O93/P93 -> 1.0627487
B94: EBIT (Operating Profit) | C94: =++C91-C93 -> -26946.74 | D94: =++D91-D93 -> 83907.69 | E94: =++E91-E93 -> -110854.43 | F94: =C94/D94 -> -0.32114744 | G94: =++G91-G93 -> -29423.53 | H94: =++H91-H93 -> 83907.69 | I94: =++I91-I93 -> -113331.22 | J94: =G94/H94 -> -0.35066548 | K94: =++K91-K93 -> 12545.51 | L94: =++L91-L93 -> 83907.69 | M94: =++M91-M93 -> -71362.18 | N94: =K94/L94 -> 0.14951562 | O94: =++O91-O93 -> -43824.76 | P94: =++P91-P93 -> 251723.07 | Q94: =++Q91-Q93 -> -295547.83 | R94: =O94/P94 -> -0.1740991 | T94: =K94/$K$11 -> 0.043460017 | U94: =L94/$L$11 -> 0.24262465
B96: Less: Interest Expense + Late Fees | C96: =++C83+C84+C82 -> 31230.67 | D96: =++D83+D84+D82 -> 25942.96 | E96: =++E83+E84+E82 -> 5287.71 | F96: =C96/D96 -> 1.2038206 | G96: =++G83+G84+G82 -> 31463.95 | H96: =++H83+H84+H82 -> 25857.16 | I96: =++I83+I84+I82 -> 5606.79 | J96: =G96/H96 -> 1.216837 | K96: =++K83+K84+K82 -> 37225.14 | L96: =++L83+L84+L82 -> 25770.57 | M96: =++M83+M84+M82 -> 11454.57 | N96: =K96/L96 -> 1.4444826 | O96: =++O83+O84+O82 -> 99919.76 | P96: =++P83+P84+P82 -> 77570.69 | Q96: =++Q83+Q84+Q82 -> 22349.07 | R96: =O96/P96 -> 1.2881123
B97: Profit Before Tax (PBT) | C97: =++C94-C96 -> -58177.41 | D97: =++D94-D96 -> 57964.73 | E97: =++E94-E96 -> -116142.14 | F97: =C97/D97 -> -1.0036691 | G97: =++G94-G96 -> -60887.48 | H97: =++H94-H96 -> 58050.53 | I97: =++I94-I96 -> -118938.01 | J97: =G97/H97 -> -1.0488704 | K97: =++K94-K96 -> -24679.63 | L97: =++L94-L96 -> 58137.12 | M97: =++M94-M96 -> -82816.75 | N97: =K97/L97 -> -0.42450727 | O97: =++O94-O96 -> -143744.52 | P97: =++P94-P96 -> 174152.38 | Q97: =++Q94-Q96 -> -317896.9 | R97: =O97/P97 -> -0.82539509 | T97: =K97/$K$11 -> -0.085494901 | U97: =L97/$L$11 -> 0.16810734
B99: Less: Tax
B100: Profit After Tax (PAT) | C100: =++C97-C99 -> -58177.41 | D100: =++D97-D99 -> 57964.73 | E100: =++E97-E99 -> -116142.14 | F100: =C100/D100 -> -1.0036691 | G100: =++G97-G99 -> -60887.48 | H100: =++H97-H99 -> 58050.53 | I100: =++I97-I99 -> -118938.01 | J100: =G100/H100 -> -1.0488704 | K100: =++K97-K99 -> -24679.63 | L100: =++L97-L99 -> 58137.12 | M100: =++M97-M99 -> -82816.75 | N100: =K100/L100 -> -0.42450727 | O100: =++O97-O99 -> -143744.52 | P100: =++P97-P99 -> 174152.38 | Q100: =++Q97-Q99 -> -317896.9 | R100: =O100/P100 -> -0.82539509 | T100: =K100/$K$11 -> -0.085494901 | U100: =L100/$L$11 -> 0.16810734
B103: Check Point | C103: =++C100-C89 -> 0 | D103: =++D100-D89 -> 0 | E103: =++E100-E89 -> 0 | F103: =++F100-F89 -> 0 | G103: =++G100-G89 -> 0 | H103: =++H100-H89 -> 0 | I103: =++I100-I89 -> 0 | J103: =++J100-J89 -> 0 | ... R103: =++R100-R89 -> 0

Sheet Profit & Loss - Division(Month)
B2: =Cover!A3 -> Pacific Nexus | J2: Home
B3: Profit and Loss by Division | J3: Balance Sheet
B4: =Index!A2 -> Period Ending 03/31/2026 | J4: Profit & Loss
J5: PL-Division (YTD)
C7: Admin & Overhead Cost | G7: NS Printing | K7: PN Agency | O7: PN Photography | S7: PN Printing | W7: YTD
C8: Actual | D8: Budget | E8: Variance | F8: % of Budget | G8: Actual | H8: Budget | I8: Variance | J8: % of Budget | K8: Actual | L8: Budget | M8: Variance | N8: % of Budget | O8: Actual | P8: Budget | Q8: Variance | R8: % of Budget | S8: Actual | T8: Budget | U8: Variance | V8: % of Budget | W8: Actual | X8: Budget | Y8: Variance | Z8: % of Budget
B9: Income
B10: 4005 Sales Revenue | E10: =(C10)-(D10) -> 0 | F10: =IF(D10=0,"",(C10)/(D10)) | G10: =167116.22 -> 167116.22 | H10: =100000 -> 100000 | I10: =(G10)-(H10) -> 67116.22 | J10: =IF(H10=0,"",(G10)/(H10)) -> 1.6711622 | K10: =1550 -> 1550 | L10: =8333.33 -> 8333.33 | M10: =(K10)-(L10) -> -6783.33 | N10: =IF(L10=0,"",(K10)/(L10)) -> 0.18600007 | O10: =45991.14 -> 45991.14 | P10: =104166.67 -> 104166.67 | Q10: =(O10)-(P10) -> -58175.53 | R10: =IF(P10=0,"",(O10)/(P10)) -> 0.44151493 | S10: =74906.02 -> 74906.02 | T10: =133333.33 -> 133333.33 | U10: =(S10)-(T10) -> -58427.31 | V10: =IF(T10=0,"",(S10)/(T10)) -> 0.56179516 | W10: =((((C10)+(G10))+(K10))+(O10))+(S10) -> 289563.38 | X10: =((((D10)+(H10))+(L10))+(P10))+(T10) -> 345833.33 | Y10: =(W10)-(X10) -> -56269.95 | Z10: =IF(X10=0,"",(W10)/(X10)) -> 0.83729171
B11: 4010 Sales Discount | E11: =(C11)-(D11) -> 0 | F11: =IF(D11=0,"",(C11)/(D11)) | I11: =(G11)-(H11) -> 0 | J11: =IF(H11=0,"",(G11)/(H11)) | M11: =(K11)-(L11) -> 0 | N11: =IF(L11=0,"",(K11)/(L11)) | Q11: =(O11)-(P11) -> 0 | R11: =IF(P11=0,"",(O11)/(P11)) | S11: =-895.52 -> -895.52 | U11: =(S11)-(T11) -> -895.52 | V11: =IF(T11=0,"",(S11)/(T11)) | W11: =((((C11)+(G11))+(K11))+(O11))+(S11) -> -895.52 | X11: =((((D11)+(H11))+(L11))+(P11))+(T11) -> 0 | Y11: =(W11)-(X11) -> -895.52 | Z11: =IF(X11=0,"",(W11)/(X11))
B12: Total Income | C12: =(C10)+(C11) -> 0 | D12: =(D10)+(D11) -> 0 | E12: =(C12)-(D12) -> 0 | F12: =IF(D12=0,"",(C12)/(D12)) | G12: =(G10)+(G11) -> 167116.22 | H12: =(H10)+(H11) -> 100000 | I12: =(G12)-(H12) -> 67116.22 | J12: =IF(H12=0,"",(G12)/(H12)) -> 1.6711622 | K12: =(K10)+(K11) -> 1550 | L12: =(L10)+(L11) -> 8333.33 | M12: =(K12)-(L12) -> -6783.33 | N12: =IF(L12=0,"",(K12)/(L12)) -> 0.18600007 | O12: =(O10)+(O11) -> 45991.14 | P12: =(P10)+(P11) -> 104166.67 | Q12: =(O12)-(P12) -> -58175.53 | R12: =IF(P12=0,"",(O12)/(P12)) -> 0.44151493 | S12: =(S10)+(S11) -> 74010.5 | T12: =(T10)+(T11) -> 133333.33 | U12: =(S12)-(T12) -> -59322.83 | V12: =IF(T12=0,"",(S12)/(T12)) -> 0.55507876 | W12: =((((C12)+(G12))+(K12))+(O12))+(S12) -> 288667.86 | X12: =((((D12)+(H12))+(L12))+(P12))+(T12) -> 345833.33 | Y12: =(W12)-(X12) -> -57165.47 | Z12: =IF(X12=0,"",(W12)/(X12)) -> 0.83470225
B13: Cost of Goods Sold
B14: 5005 Cost of Materials | E14: =(C14)-(D14) -> 0 | F14: =IF(D14=0,"",(C14)/(D14)) | G14: =11579.67 -> 11579.67 | H14: =13000 -> 13000 | I14: =(G14)-(H14) -> -1420.33 | J14: =IF(H14=0,"",(G14)/(H14)) -> 0.89074385 | L14: =1083.33 -> 1083.33 | M14: =(K14)-(L14) -> -1083.33 | N14: =IF(L14=0,"",(K14)/(L14)) -> 0 | O14: =4914.15 -> 4914.15 | P14: =13541.67 -> 13541.67 | Q14: =(O14)-(P14) -> -8627.52 | R14: =IF(P14=0,"",(O14)/(P14)) -> 0.36289099 | S14: =18354.09 -> 18354.09 | T14: =17333.33 -> 17333.33 | U14: =(S14)-(T14) -> 1020.76 | V14: =IF(T14=0,"",(S14)/(T14)) -> 1.05889 | W14: =((((C14)+(G14))+(K14))+(O14))+(S14) -> 34847.91 | X14: =((((D14)+(H14))+(L14))+(P14))+(T14) -> 44958.33 | Y14: =(W14)-(X14) -> -10110.42 | Z14: =IF(X14=0,"",(W14)/(X14)) -> 0.77511576
B15: 5015 Travels and Meals | E15: =(C15)-(D15) -> 0 | F15: =IF(D15=0,"",(C15)/(D15)) | I15: =(G15)-(H15) -> 0 | J15: =IF(H15=0,"",(G15)/(H15)) | M15: =(K15)-(L15) -> 0 | N15: =IF(L15=0,"",(K15)/(L15)) | O15: 0 | Q15: =(O15)-(P15) -> 0 | R15: =IF(P15=0,"",(O15)/(P15)) | U15: =(S15)-(T15) -> 0 | V15: =IF(T15=0,"",(S15)/(T15)) | W15: =((((C15)+(G15))+(K15))+(O15))+(S15) -> 0 | X15: =((((D15)+(H15))+(L15))+(P15))+(T15) -> 0 | Y15: =(W15)-(X15) -> 0 | Z15: =IF(X15=0,"",(W15)/(X15))
B16: 5065 Wages | E16: =(C16)-(D16) -> 0 | F16: =IF(D16=0,"",(C16)/(D16)) | G16: =18477.09 -> 18477.09 | H16: =1139.87 -> 1139.87 | I16: =(G16)-(H16) -> 17337.22 | J16: =IF(H16=0,"",(G16)/(H16)) -> 16.209822 | K16: =0 -> 0 | M16: =(K16)-(L16) -> 0 | N16: =IF(L16=0,"",(K16)/(L16)) | O16: =21595.76 -> 21595.76 | P16: =28468.69 -> 28468.69 | Q16: =(O16)-(P16) -> -6872.93 | R16: =IF(P16=0,"",(O16)/(P16)) -> 0.75857934 | S16: =57640.98 -> 57640.98 | T16: =46857.02 -> 46857.02 | U16: =(S16)-(T16) -> 10783.96 | V16: =IF(T16=0,"",(S16)/(T16)) -> 1.2301461 | W16: =((((C16)+(G16))+(K16))+(O16))+(S16) -> 97713.83 | X16: =((((D16)+(H16))+(L16))+(P16))+(T16) -> 76465.58 | Y16: =(W16)-(X16) -> 21248.25 | Z16: =IF(X16=0,"",(W16)/(X16)) -> 1.2778799
B17: 5070 Payroll Tax Expense | E17: =(C17)-(D17) -> 0 | F17: =IF(D17=0,"",(C17)/(D17)) | G17: =1752.46 -> 1752.46 | H17: =91.19 -> 91.19 | I17: =(G17)-(H17) -> 1661.27 | J17: =IF(H17=0,"",(G17)/(H17)) -> 19.217677 | K17: =0 -> 0 | M17: =(K17)-(L17) -> 0 | N17: =IF(L17=0,"",(K17)/(L17)) | O17: =1563.43 -> 1563.43 | P17: =2277.5 -> 2277.5 | Q17: =(O17)-(P17) -> -714.07 | R17: =IF(P17=0,"",(O17)/(P17)) -> 0.68646762 | S17: =4754.34 -> 4754.34 | T17: =3748.56 -> 3748.56 | U17: =(S17)-(T17) -> 1005.78 | V17: =IF(T17=0,"",(S17)/(T17)) -> 1.268311 | W17: =((((C17)+(G17))+(K17))+(O17))+(S17) -> 8070.23 | X17: =((((D17)+(H17))+(L17))+(P17))+(T17) -> 6117.25 | Y17: =(W17)-(X17) -> 1952.98 | Z17: =IF(X17=0,"",(W17)/(X17)) -> 1.3192578
B18: 5075 Employee Benefits | E18: =(C18)-(D18) -> 0 | F18: =IF(D18=0,"",(C18)/(D18)) | G18: =1052.75 -> 1052.75 | I18: =(G18)-(H18) -> 1052.75 | J18: =IF(H18=0,"",(G18)/(H18)) | K18: =0 -> 0 | M18: =(K18)-(L18) -> 0 | N18: =IF(L18=0,"",(K18)/(L18)) | O18: =522.48 -> 522.48 | P18: =1155.98 -> 1155.98 | Q18: =(O18)-(P18) -> -633.5 | R18: =IF(P18=0,"",(O18)/(P18)) -> 0.45198014 | S18: =3253.9 -> 3253.9 | T18: =1902.64 -> 1902.64 | U18: =(S18)-(T18) -> 1351.26 | V18: =IF(T18=0,"",(S18)/(T18)) -> 1.7102027 | W18: =((((C18)+(G18))+(K18))+(O18))+(S18) -> 4829.13 | X18: =((((D18)+(H18))+(L18))+(P18))+(T18) -> 3058.62 | Y18: =(W18)-(X18) -> 1770.51 | Z18: =IF(X18=0,"",(W18)/(X18)) -> 1.5788591
B19: Total Cost of Goods Sold | C19: =((((C14)+(C15))+(C16))+(C17))+(C18) -> 0 | D19: =((((D14)+(D15))+(D16))+(D17))+(D18) -> 0 | E19: =(C19)-(D19) -> 0 | F19: =IF(D19=0,"",(C19)/(D19)) | G19: =((((G14)+(G15))+(G16))+(G17))+(G18) -> 32861.97 | H19: =((((H14)+(H15))+(H16))+(H17))+(H18) -> 14231.06 | I19: =(G19)-(H19) -> 18630.91 | J19: =IF(H19=0,"",(G19)/(H19)) -> 2.3091723 | K19: =((((K14)+(K15))+(K16))+(K17))+(K18) -> 0 | L19: =((((L14)+(L15))+(L16))+(L17))+(L18) -> 1083.33 | M19: =(K19)-(L19) -> -1083.33 | N19: =IF(L19=0,"",(K19)/(L19)) -> 0 | O19: =((((O14)+(O15))+(O16))+(O17))+(O18) -> 28595.82 | P19: =((((P14)+(P15))+(P16))+(P17))+(P18) -> 45443.84 | Q19: =(O19)-(P19) -> -16848.02 | R19: =IF(P19=0,"",(O19)/(P19)) -> 0.62925624 | S19: =((((S14)+(S15))+(S16))+(S17))+(S18) -> 84003.31 | T19: =((((T14)+(T15))+(T16))+(T17))+(T18) -> 69841.55 | U19: =(S19)-(T19) -> 14161.76 | V19: =IF(T19=0,"",(S19)/(T19)) -> 1.2027698 | W19: =((((C19)+(G19))+(K19))+(O19))+(S19) -> 145461.1 | X19: =((((D19)+(H19))+(L19))+(P19))+(T19) -> 130599.78 | Y19: =(W19)-(X19) -> 14861.32 | Z19: =IF(X19=0,"",(W19)/(X19)) -> 1.1137928
B20: Gross Profit | C20: =(C12)-(C19) -> 0 | D20: =(D12)-(D19) -> 0 | E20: =(C20)-(D20) -> 0 | F20: =IF(D20=0,"",(C20)/(D20)) | G20: =(G12)-(G19) -> 134254.25 | H20: =(H12)-(H19) -> 85768.94 | I20: =(G20)-(H20) -> 48485.31 | J20: =IF(H20=0,"",(G20)/(H20)) -> 1.5653015 | K20: =(K12)-(K19) -> 1550 | L20: =(L12)-(L19) -> 7250 | M20: =(K20)-(L20) -> -5700 | N20: =IF(L20=0,"",(K20)/(L20)) -> 0.2137931 | O20: =(O12)-(O19) -> 17395.32 | P20: =(P12)-(P19) -> 58722.83 | Q20: =(O20)-(P20) -> -41327.51 | R20: =IF(P20=0,"",(O20)/(P20)) -> 0.29622755 | S20: =(S12)-(S19) -> -9992.81 | T20: =(T12)-(T19) -> 63491.78 | U20: =(S20)-(T20) -> -73484.59 | V20: =IF(T20=0,"",(S20)/(T20)) -> -0.15738746 | W20: =((((C20)+(G20))+(K20))+(O20))+(S20) -> 143206.76 | X20: =((((D20)+(H20))+(L20))+(P20))+(T20) -> 215233.55 | Y20: =(W20)-(X20) -> -72026.79 | Z20: =IF(X20=0,"",(W20)/(X20)) -> 0.66535519
B21: Expenses
B22: 6100 Payroll Expenses | E22: =(C22)-(D22) -> 0 | F22: =IF(D22=0,"",(C22)/(D22)) | I22: =(G22)-(H22) -> 0 | J22: =IF(H22=0,"",(G22)/(H22)) | M22: =(K22)-(L22) -> 0 | N22: =IF(L22=0,"",(K22)/(L22)) | Q22: =(O22)-(P22) -> 0 | R22: =IF(P22=0,"",(O22)/(P22)) | U22: =(S22)-(T22) -> 0 | V22: =IF(T22=0,"",(S22)/(T22)) | W22: =((((C22)+(G22))+(K22))+(O22))+(S22) -> 0 | X22: =((((D22)+(H22))+(L22))+(P22))+(T22) -> 0 | Y22: =(W22)-(X22) -> 0 | Z22: =IF(X22=0,"",(W22)/(X22))
B23: 6105 Salaries & Wages | C23: =0 -> 0 | D23: =0 -> 0 | E23: =(C23)-(D23) -> 0 | F23: =IF(D23=0,"",(C23)/(D23)) | G23: =14307.67 -> 14307.67 | H23: =13846.18 -> 13846.18 | I23: =(G23)-(H23) -> 461.49 | J23: =IF(H23=0,"",(G23)/(H23)) -> 1.0333298 | K23: =1021.99 -> 1021.99 | L23: =989.01 -> 989.01 | M23: =(K23)-(L23) -> 32.98 | N23: =IF(L23=0,"",(K23)/(L23)) -> 1.0333465 | O23: =6131.87 -> 6131.87 | P23: =5934.08 -> 5934.08 | Q23: =(O23)-(P23) -> 197.79 | R23: =IF(P23=0,"",(O23)/(P23)) -> 1.0333312 | S23: =0 -> 0 | T23: =857.17 -> 857.17 | U23: =(S23)-(T23) -> -857.17 | V23: =IF(T23=0,"",(S23)/(T23)) -> 0 | W23: =((((C23)+(G23))+(K23))+(O23))+(S23) -> 21461.53 | X23: =((((D23)+(H23))+(L23))+(P23))+(T23) -> 21626.44 | Y23: =(W23)-(X23) -> -164.91 | Z23: =IF(X23=0,"",(W23)/(X23)) -> 0.99237461
B24: 6115 Payroll Tax Expense | C24: =104.92 -> 104.92 | D24: =0 -> 0 | E24: =(C24)-(D24) -> 104.92 | F24: =IF(D24=0,"",(C24)/(D24)) | G24: =1306.25 -> 1306.25 | H24: =1107.7 -> 1107.7 | I24: =(G24)-(H24) -> 198.55 | J24: =IF(H24=0,"",(G24)/(H24)) -> 1.1792453 | K24: =285.76 -> 285.76 | L24: =79.12 -> 79.12 | M24: =(K24)-(L24) -> 206.64 | N24: =IF(L24=0,"",(K24)/(L24)) -> 3.611729 | O24: =992.23 -> 992.23 | P24: =474.73 -> 474.73 | Q24: =(O24)-(P24) -> 517.5 | R24: =IF(P24=0,"",(O24)/(P24)) -> 2.0900933 | S24: =1309.53 -> 1309.53 | T24: =68.57 -> 68.57 | U24: =(S24)-(T24) -> 1240.96 | V24: =IF(T24=0,"",(S24)/(T24)) -> 19.09771 | W24: =((((C24)+(G24))+(K24))+(O24))+(S24) -> 3998.69 | X24: =((((D24)+(H24))+(L24))+(P24))+(T24) -> 1730.12 | Y24: =(W24)-(X24) -> 2268.57 | Z24: =IF(X24=0,"",(W24)/(X24)) -> 2.3112212
B25: 6120 Employee Benefits | C25: =0 -> 0 | D25: =0 -> 0 | E25: =(C25)-(D25) -> 0 | F25: =IF(D25=0,"",(C25)/(D25)) | G25: =855.9 -> 855.9 | H25: =553.85 -> 553.85 | I25: =(G25)-(H25) -> 302.05 | J25: =IF(H25=0,"",(G25)/(H25)) -> 1.5453643 | K25: =43.44 -> 43.44 | L25: =39.56 -> 39.56 | M25: =(K25)-(L25) -> 3.88 | N25: =IF(L25=0,"",(K25)/(L25)) -> 1.0980789 | O25: =260.57 -> 260.57 | P25: =237.36 -> 237.36 | Q25: =(O25)-(P25) -> 23.21 | R25: =IF(P25=0,"",(O25)/(P25)) -> 1.097784 | S25: =0 -> 0 | T25: =34.29 -> 34.29 | U25: =(S25)-(T25) -> -34.29 | V25: =IF(T25=0,"",(S25)/(T25)) -> 0 | W25: =((((C25)+(G25))+(K25))+(O25))+(S25) -> 1159.91 | X25: =((((D25)+(H25))+(L25))+(P25))+(T25) -> 865.06 | Y25: =(W25)-(X25) -> 294.85 | Z25: =IF(X25=0,"",(W25)/(X25)) -> 1.3408434
B26: 6125 Employee Bonus | D26: =0 -> 0 | E26: =(C26)-(D26) -> 0 | F26: =IF(D26=0,"",(C26)/(D26)) | H26: =526.16 -> 526.16 | I26: =(G26)-(H26) -> -526.16 | J26: =IF(H26=0,"",(G26)/(H26)) -> 0 | L26: =37.58 -> 37.58 | M26: =(K26)-(L26) -> -37.58 | N26: =IF(L26=0,"",(K26)/(L26)) -> 0 | P26: =225.5 -> 225.5 | Q26: =(O26)-(P26) -> -225.5 | R26: =IF(P26=0,"",(O26)/(P26)) -> 0 | T26: =32.57 -> 32.57 | U26: =(S26)-(T26) -> -32.57 | V26: =IF(T26=0,"",(S26)/(T26)) -> 0 | W26: =((((C26)+(G26))+(K26))+(O26))+(S26) -> 0 | X26: =((((D26)+(H26))+(L26))+(P26))+(T26) -> 821.81 | Y26: =(W26)-(X26) -> -821.81 | Z26: =IF(X26=0,"",(W26)/(X26)) -> 0
B27: Total 6100 Payroll Expenses | C27: =((((C22)+(C23))+(C24))+(C25))+(C26) -> 104.92 | D27: =((((D22)+(D23))+(D24))+(D25))+(D26) -> 0 | E27: =(C27)-(D27) -> 104.92 | F27: =IF(D27=0,"",(C27)/(D27)) | G27: =((((G22)+(G23))+(G24))+(G25))+(G26) -> 16469.82 | H27: =((((H22)+(H23))+(H24))+(H25))+(H26) -> 16033.89 | I27: =(G27)-(H27) -> 435.93 | J27: =IF(H27=0,"",(G27)/(H27)) -> 1.027188 | K27: =((((K22)+(K23))+(K24))+(K25))+(K26) -> 1351.19 | L27: =((((L22)+(L23))+(L24))+(L25))+(L26) -> 1145.27 | M27: =(K27)-(L27) -> 205.92 | N27: =IF(L27=0,"",(K27)/(L27)) -> 1.1798004 | O27: =((((O22)+(O23))+(O24))+(O25))+(O26) -> 7384.67 | P27: =((((P22)+(P23))+(P24))+(P25))+(P26) -> 6871.67 | Q27: =(O27)-(P27) -> 513 | R27: =IF(P27=0,"",(O27)/(P27)) -> 1.0746543 | S27: =((((S22)+(S23))+(S24))+(S25))+(S26) -> 1309.53 | T27: =((((T22)+(T23))+(T24))+(T25))+(T26) -> 992.6 | U27: =(S27)-(T27) -> 316.93 | V27: =IF(T27=0,"",(S27)/(T27)) -> 1.3192928 | W27: =((((C27)+(G27))+(K27))+(O27))+(S27) -> 26620.13 | X27: =((((D27)+(H27))+(L27))+(P27))+(T27) -> 25043.43 | Y27: =(W27)-(X27) -> 1576.7 | Z27: =IF(X27=0,"",(W27)/(X27)) -> 1.0629586
B28: 6130 Staff Training & Development | C28: =2632.67 -> 2632.67 | D28: =100 -> 100 | E28: =(C28)-(D28) -> 2532.67 | F28: =IF(D28=0,"",(C28)/(D28)) -> 26.3267 | I28: =(G28)-(H28) -> 0 | J28: =IF(H28=0,"",(G28)/(H28)) | M28: =(K28)-(L28) -> 0 | N28: =IF(L28=0,"",(K28)/(L28)) | Q28: =(O28)-(P28) -> 0 | R28: =IF(P28=0,"",(O28)/(P28)) | U28: =(S28)-(T28) -> 0 | V28: =IF(T28=0,"",(S28)/(T28)) | W28: =((((C28)+(G28))+(K28))+(O28))+(S28) -> 2632.67 | X28: =((((D28)+(H28))+(L28))+(P28))+(T28) -> 100 | Y28: =(W28)-(X28) -> 2532.67 | Z28: =IF(X28=0,"",(W28)/(X28)) -> 26.3267
B29: 6135 Payroll Processing Fees | C29: =956 -> 956 | D29: =830.14 -> 830.14 | E29: =(C29)-(D29) -> 125.86 | F29: =IF(D29=0,"",(C29)/(D29)) -> 1.151613 | I29: =(G29)-(H29) -> 0 | J29: =IF(H29=0,"",(G29)/(H29)) | M29: =(K29)-(L29) -> 0 | N29: =IF(L29=0,"",(K29)/(L29)) | Q29: =(O29)-(P29) -> 0 | R29: =IF(P29=0,"",(O29)/(P29)) | U29: =(S29)-(T29) -> 0 | V29: =IF(T29=0,"",(S29)/(T29)) | W29: =((((C29)+(G29))+(K29))+(O29))+(S29) -> 956 | X29: =((((D29)+(H29))+(L29))+(P29))+(T29) -> 830.14 | Y29: =(W29)-(X29) -> 125.86 | Z29: =IF(X29=0,"",(W29)/(X29)) -> 1.151613
B30: 6150 Employee Reimbursements | C30: =0 -> 0 | D30: =1647.22 -> 1647.22 | E30: =(C30)-(D30) -> -1647.22 | F30: =IF(D30=0,"",(C30)/(D30)) -> 0 | G30: =0 -> 0 | I30: =(G30)-(H30) -> 0 | J30: =IF(H30=0,"",(G30)/(H30)) | K30: =0 -> 0 | M30: =(K30)-(L30) -> 0 | N30: =IF(L30=0,"",(K30)/(L30)) | O30: =0 -> 0 | Q30: =(O30)-(P30) -> 0 | R30: =IF(P30=0,"",(O30)/(P30)) | S30: =0 -> 0 | U30: =(S30)-(T30) -> 0 | V30: =IF(T30=0,"",(S30)/(T30)) | W30: =((((C30)+(G30))+(K30))+(O30))+(S30) -> 0 | X30: =((((D30)+(H30))+(L30))+(P30))+(T30) -> 1647.22 | Y30: =(W30)-(X30) -> -1647.22 | Z30: =IF(X30=0,"",(W30)/(X30)) -> 0
B31: 6155 Employee Gift | D31: =250 -> 250 | E31: =(C31)-(D31) -> -250 | F31: =IF(D31=0,"",(C31)/(D31)) -> 0 | I31: =(G31)-(H31) -> 0 | J31: =IF(H31=0,"",(G31)/(H31)) | M31: =(K31)-(L31) -> 0 | N31: =IF(L31=0,"",(K31)/(L31)) | Q31: =(O31)-(P31) -> 0 | R31: =IF(P31=0,"",(O31)/(P31)) | U31: =(S31)-(T31) -> 0 | V31: =IF(T31=0,"",(S31)/(T31)) | W31: =((((C31)+(G31))+(K31))+(O31))+(S31) -> 0 | X31: =((((D31)+(H31))+(L31))+(P31))+(T31) -> 250 | Y31: =(W31)-(X31) -> -250 | Z31: =IF(X31=0,"",(W31)/(X31)) -> 0
B32: 6200 Professional Fees | E32: =(C32)-(D32) -> 0 | F32: =IF(D32=0,"",(C32)/(D32)) | I32: =(G32)-(H32) -> 0 | J32: =IF(H32=0,"",(G32)/(H32)) | M32: =(K32)-(L32) -> 0 | N32: =IF(L32=0,"",(K32)/(L32)) | Q32: =(O32)-(P32) -> 0 | R32: =IF(P32=0,"",(O32)/(P32)) | U32: =(S32)-(T32) -> 0 | V32: =IF(T32=0,"",(S32)/(T32)) | W32: =((((C32)+(G32))+(K32))+(O32))+(S32) -> 0 | X32: =((((D32)+(H32))+(L32))+(P32))+(T32) -> 0 | Y32: =(W32)-(X32) -> 0 | Z32: =IF(X32=0,"",(W32)/(X32))
B33: 6205 Legal Fees | C33: =6296.82 -> 6296.82 | E33: =(C33)-(D33) -> 6296.82 | F33: =IF(D33=0,"",(C33)/(D33)) | I33: =(G33)-(H33) -> 0 | J33: =IF(H33=0,"",(G33)/(H33)) | M33: =(K33)-(L33) -> 0 | N33: =IF(L33=0,"",(K33)/(L33)) | Q33: =(O33)-(P33) -> 0 | R33: =IF(P33=0,"",(O33)/(P33)) | U33: =(S33)-(T33) -> 0 | V33: =IF(T33=0,"",(S33)/(T33)) | W33: =((((C33)+(G33))+(K33))+(O33))+(S33) -> 6296.82 | X33: =((((D33)+(H33))+(L33))+(P33))+(T33) -> 0 | Y33: =(W33)-(X33) -> 6296.82 | Z33: =IF(X33=0,"",(W33)/(X33))
B34: 6210 IT Fees | C34: =2400 -> 2400 | D34: =2400 -> 2400 | E34: =(C34)-(D34) -> 0 | F34: =IF(D34=0,"",(C34)/(D34)) -> 1 | I34: =(G34)-(H34) -> 0 | J34: =IF(H34=0,"",(G34)/(H34)) | M34: =(K34)-(L34) -> 0 | N34: =IF(L34=0,"",(K34)/(L34)) | Q34: =(O34)-(P34) -> 0 | R34: =IF(P34=0,"",(O34)/(P34)) | U34: =(S34)-(T34) -> 0 | V34: =IF(T34=0,"",(S34)/(T34)) | W34: =((((C34)+(G34))+(K34))+(O34))+(S34) -> 2400 | X34: =((((D34)+(H34))+(L34))+(P34))+(T34) -> 2400 | Y34: =(W34)-(X34) -> 0 | Z34: =IF(X34=0,"",(W34)/(X34)) -> 1
B35: 6215 Accounting Fees | C35: =1093 -> 1093 | D35: =1000 -> 1000 | E35: =(C35)-(D35) -> 93 | F35: =IF(D35=0,"",(C35)/(D35)) -> 1.093 | I35: =(G35)-(H35) -> 0 | J35: =IF(H35=0,"",(G35)/(H35)) | M35: =(K35)-(L35) -> 0 | N35: =IF(L35=0,"",(K35)/(L35)) | Q35: =(O35)-(P35) -> 0 | R35: =IF(P35=0,"",(O35)/(P35)) | U35: =(S35)-(T35) -> 0 | V35: =IF(T35=0,"",(S35)/(T35)) | W35: =((((C35)+(G35))+(K35))+(O35))+(S35) -> 1093 | X35: =((((D35)+(H35))+(L35))+(P35))+(T35) -> 1000 | Y35: =(W35)-(X35) -> 93 | Z35: =IF(X35=0,"",(W35)/(X35)) -> 1.093
B36: 6220 Professional and Consulting Fees | C36: =2139.99 -> 2139.99 | D36: =2500 -> 2500 | E36: =(C36)-(D36) -> -360.01 | F36: =IF(D36=0,"",(C36)/(D36)) -> 0.855996 | I36: =(G36)-(H36) -> 0 | J36: =IF(H36=0,"",(G36)/(H36)) | M36: =(K36)-(L36) -> 0 | N36: =IF(L36=0,"",(K36)/(L36)) | O36: =1500 -> 1500 | Q36: =(O36)-(P36) -> 1500 | R36: =IF(P36=0,"",(O36)/(P36)) | U36: =(S36)-(T36) -> 0 | V36: =IF(T36=0,"",(S36)/(T36)) | W36: =((((C36)+(G36))+(K36))+(O36))+(S36) -> 3639.99 | X36: =((((D36)+(H36))+(L36))+(P36))+(T36) -> 2500 | Y36: =(W36)-(X36) -> 1139.99 | Z36: =IF(X36=0,"",(W36)/(X36)) -> 1.455996
B37: Total 6200 Professional Fees | C37: =((((C32)+(C33))+(C34))+(C35))+(C36) -> 11929.81 | D37: =((((D32)+(D33))+(D34))+(D35))+(D36) -> 5900 | E37: =(C37)-(D37) -> 6029.81 | F37: =IF(D37=0,"",(C37)/(D37)) -> 2.0220017 | G37: =((((G32)+(G33))+(G34))+(G35))+(G36) -> 0 | H37: =((((H32)+(H33))+(H34))+(H35))+(H36) -> 0 | I37: =(G37)-(H37) -> 0 | J37: =IF(H37=0,"",(G37)/(H37)) | K37: =((((K32)+(K33))+(K34))+(K35))+(K36) -> 0 | L37: =((((L32)+(L33))+(L34))+(L35))+(L36) -> 0 | M37: =(K37)-(L37) -> 0 | N37: =IF(L37=0,"",(K37)/(L37)) | O37: =((((O32)+(O33))+(O34))+(O35))+(O36) -> 1500 | P37: =((((P32)+(P33))+(P34))+(P35))+(P36) -> 0 | Q37: =(O37)-(P37) -> 1500 | R37: =IF(P37=0,"",(O37)/(P37)) | S37: =((((S32)+(S33))+(S34))+(S35))+(S36) -> 0 | T37: =((((T32)+(T33))+(T34))+(T35))+(T36) -> 0 | U37: =(S37)-(T37) -> 0 | V37: =IF(T37=0,"",(S37)/(T37)) | W37: =((((C37)+(G37))+(K37))+(O37))+(S37) -> 13429.81 | X37: =((((D37)+(H37))+(L37))+(P37))+(T37) -> 5900 | Y37: =(W37)-(X37) -> 7529.81 | Z37: =IF(X37=0,"",(W37)/(X37)) -> 2.276239
B38: 6300 Shareholder's Compensation | E38: =(C38)-(D38) -> 0 | F38: =IF(D38=0,"",(C38)/(D38)) | I38: =(G38)-(H38) -> 0 | J38: =IF(H38=0,"",(G38)/(H38)) | M38: =(K38)-(L38) -> 0 | N38: =IF(L38=0,"",(K38)/(L38)) | Q38: =(O38)-(P38) -> 0 | R38: =IF(P38=0,"",(O38)/(P38)) | U38: =(S38)-(T38) -> 0 | V38: =IF(T38=0,"",(S38)/(T38)) | W38: =((((C38)+(G38))+(K38))+(O38))+(S38) -> 0 | X38: =((((D38)+(H38))+(L38))+(P38))+(T38) -> 0 | Y38: =(W38)-(X38) -> 0 | Z38: =IF(X38=0,"",(W38)/(X38))
B39: 6305 Shareholder's Wages & Salaries | C39: =11071.43 -> 11071.43 | D39: =10000 -> 10000 | E39: =(C39)-(D39) -> 1071.43 | F39: =IF(D39=0,"",(C39)/(D39)) -> 1.107143 | I39: =(G39)-(H39) -> 0 | J39: =IF(H39=0,"",(G39)/(H39)) | M39: =(K39)-(L39) -> 0 | N39: =IF(L39=0,"",(K39)/(L39)) | Q39: =(O39)-(P39) -> 0 | R39: =IF(P39=0,"",(O39)/(P39)) | U39: =(S39)-(T39) -> 0 | V39: =IF(T39=0,"",(S39)/(T39)) | W39: =((((C39)+(G39))+(K39))+(O39))+(S39) -> 11071.43 | X39: =((((D39)+(H39))+(L39))+(P39))+(T39) -> 10000 | Y39: =(W39)-(X39) -> 1071.43 | Z39: =IF(X39=0,"",(W39)/(X39)) -> 1.107143
B40: 6310 Shareholder's Health Insurance | C40: =252.75 -> 252.75 | D40: =252 -> 252 | E40: =(C40)-(D40) -> 0.75 | F40: =IF(D40=0,"",(C40)/(D40)) -> 1.0029762 | I40: =(G40)-(H40) -> 0 | J40: =IF(H40=0,"",(G40)/(H40)) | M40: =(K40)-(L40) -> 0 | N40: =IF(L40=0,"",(K40)/(L40)) | Q40: =(O40)-(P40) -> 0 | R40: =IF(P40=0,"",(O40)/(P40)) | U40: =(S40)-(T40) -> 0 | V40: =IF(T40=0,"",(S40)/(T40)) | W40: =((((C40)+(G40))+(K40))+(O40))+(S40) -> 252.75 | X40: =((((D40)+(H40))+(L40))+(P40))+(T40) -> 252 | Y40: =(W40)-(X40) -> 0.75 | Z40: =IF(X40=0,"",(W40)/(X40)) -> 1.0029762
B41: 6315 Shareholder's Payroll Taxes | C41: =846.96 -> 846.96 | D41: =800 -> 800 | E41: =(C41)-(D41) -> 46.96 | F41: =IF(D41=0,"",(C41)/(D41)) -> 1.0587 | I41: =(G41)-(H41) -> 0 | J41: =IF(H41=0,"",(G41)/(H41)) | M41: =(K41)-(L41) -> 0 | N41: =IF(L41=0,"",(K41)/(L41)) | Q41: =(O41)-(P41) -> 0 | R41: =IF(P41=0,"",(O41)/(P41)) | U41: =(S41)-(T41) -> 0 | V41: =IF(T41=0,"",(S41)/(T41)) | W41: =((((C41)+(G41))+(K41))+(O41))+(S41) -> 846.96 | X41: =((((D41)+(H41))+(L41))+(P41))+(T41) -> 800 | Y41: =(W41)-(X41) -> 46.96 | Z41: =IF(X41=0,"",(W41)/(X41)) -> 1.0587
B42: 6320 Shareholder's 401(k) Employer Contributions | C42: =387.5 -> 387.5 | D42: =379.17 -> 379.17 | E42: =(C42)-(D42) -> 8.33 | F42: =IF(D42=0,"",(C42)/(D42)) -> 1.021969 | I42: =(G42)-(H42) -> 0 | J42: =IF(H42=0,"",(G42)/(H42)) | M42: =(K42)-(L42) -> 0 | N42: =IF(L42=0,"",(K42)/(L42)) | Q42: =(O42)-(P42) -> 0 | R42: =IF(P42=0,"",(O42)/(P42)) | U42: =(S42)-(T42) -> 0 | V42: =IF(T42=0,"",(S42)/(T42)) | W42: =((((C42)+(G42))+(K42))+(O42))+(S42) -> 387.5 | X42: =((((D42)+(H42))+(L42))+(P42))+(T42) -> 379.17 | Y42: =(W42)-(X42) -> 8.33 | Z42: =IF(X42=0,"",(W42)/(X42)) -> 1.021969
B43: Total 6300 Shareholder's Compensation | C43: =((((C38)+(C39))+(C40))+(C41))+(C42) -> 12558.64 | D43: =((((D38)+(D39))+(D40))+(D41))+(D42) -> 11431.17 | E43: =(C43)-(D43) -> 1127.47 | F43: =IF(D43=0,"",(C43)/(D43)) -> 1.0986312 | G43: =((((G38)+(G39))+(G40))+(G41))+(G42) -> 0 | H43: =((((H38)+(H39))+(H40))+(H41))+(H42) -> 0 | I43: =(G43)-(H43) -> 0 | J43: =IF(H43=0,"",(G43)/(H43)) | K43: =((((K38)+(K39))+(K40))+(K41))+(K42) -> 0 | L43: =((((L38)+(L39))+(L40))+(L41))+(L42) -> 0 | M43: =(K43)-(L43) -> 0 | N43: =IF(L43=0,"",(K43)/(L43)) | O43: =((((O38)+(O39))+(O40))+(O41))+(O42) -> 0 | P43: =((((P38)+(P39))+(P40))+(P41))+(P42) -> 0 | Q43: =(O43)-(P43) -> 0 | R43: =IF(P43=0,"",(O43)/(P43)) | S43: =((((S38)+(S39))+(S40))+(S41))+(S42) -> 0 | T43: =((((T38)+(T39))+(T40))+(T41))+(T42) -> 0 | U43: =(S43)-(T43) -> 0 | V43: =IF(T43=0,"",(S43)/(T43)) | W43: =((((C43)+(G43))+(K43))+(O43))+(S43) -> 12558.64 | X43: =((((D43)+(H43))+(L43))+(P43))+(T43) -> 11431.17 | Y43: =(W43)-(X43) -> 1127.47 | Z43: =IF(X43=0,"",(W43)/(X43)) -> 1.0986312
B44: 6400 Office Expense | E44: =(C44)-(D44) -> 0 | F44: =IF(D44=0,"",(C44)/(D44)) | I44: =(G44)-(H44) -> 0 | J44: =IF(H44=0,"",(G44)/(H44)) | M44: =(K44)-(L44) -> 0 | N44: =IF(L44=0,"",(K44)/(L44)) | Q44: =(O44)-(P44) -> 0 | R44: =IF(P44=0,"",(O44)/(P44)) | U44: =(S44)-(T44) -> 0 | V44: =IF(T44=0,"",(S44)/(T44)) | W44: =((((C44)+(G44))+(K44))+(O44))+(S44) -> 0 | X44: =((((D44)+(H44))+(L44))+(P44))+(T44) -> 0 | Y44: =(W44)-(X44) -> 0 | Z44: =IF(X44=0,"",(W44)/(X44))
B45: 6405 Office Equipment | C45: =5427.23 -> 5427.23 | D45: =3458.33 -> 3458.33 | E45: =(C45)-(D45) -> 1968.9 | F45: =IF(D45=0,"",(C45)/(D45)) -> 1.569321 | I45: =(G45)-(H45) -> 0 | J45: =IF(H45=0,"",(G45)/(H45)) | M45: =(K45)-(L45) -> 0 | N45: =IF(L45=0,"",(K45)/(L45)) | Q45: =(O45)-(P45) -> 0 | R45: =IF(P45=0,"",(O45)/(P45)) | U45: =(S45)-(T45) -> 0 | V45: =IF(T45=0,"",(S45)/(T45)) | W45: =((((C45)+(G45))+(K45))+(O45))+(S45) -> 5427.23 | X45: =((((D45)+(H45))+(L45))+(P45))+(T45) -> 3458.33 | Y45: =(W45)-(X45) -> 1968.9 | Z45: =IF(X45=0,"",(W45)/(X45)) -> 1.569321
B46: 6410 Office Supplies | C46: =1624.84 -> 1624.84 | D46: =2583.33 -> 2583.33 | E46: =(C46)-(D46) -> -958.49 | F46: =IF(D46=0,"",(C46)/(D46)) -> 0.62897113 | H46: =3000 -> 3000 | I46: =(G46)-(H46) -> -3000 | J46: =IF(H46=0,"",(G46)/(H46)) -> 0 | M46: =(K46)-(L46) -> 0 | N46: =IF(L46=0,"",(K46)/(L46)) | O46: =457.14 -> 457.14 | Q46: =(O46)-(P46) -> 457.14 | R46: =IF(P46=0,"",(O46)/(P46)) | S46: =14.93 -> 14.93 | T46: =1333.33 -> 1333.33 | U46: =(S46)-(T46) -> -1318.4 | V46: =IF(T46=0,"",(S46)/(T46)) -> 0.011197528 | W46: =((((C46)+(G46))+(K46))+(O46))+(S46) -> 2096.91 | X46: =((((D46)+(H46))+(L46))+(P46))+(T46) -> 6916.66 | Y46: =(W46)-(X46) -> -4819.75 | Z46: =IF(X46=0,"",(W46)/(X46)) -> 0.303168
B47: 6415 Phone and Internet Expense - Office | C47: =306.91 -> 306.91 | D47: =340 -> 340 | E47: =(C47)-(D47) -> -33.09 | F47: =IF(D47=0,"",(C47)/(D47)) -> 0.90267647 | I47: =(G47)-(H47) -> 0 | J47: =IF(H47=0,"",(G47)/(H47)) | M47: =(K47)-(L47) -> 0 | N47: =IF(L47=0,"",(K47)/(L47)) | Q47: =(O47)-(P47) -> 0 | R47: =IF(P47=0,"",(O47)/(P47)) | U47: =(S47)-(T47) -> 0 | V47: =IF(T47=0,"",(S47)/(T47)) | W47: =((((C47)+(G47))+(K47))+(O47))+(S47) -> 306.91 | X47: =((((D47)+(H47))+(L47))+(P47))+(T47) -> 340 | Y47: =(W47)-(X47) -> -33.09 | Z47: =IF(X47=0,"",(W47)/(X47)) -> 0.90267647
B48: 6420 Office Repairs & Maintenance | C48: =575.03 -> 575.03 | D48: =1062.5 -> 1062.5 | E48: =(C48)-(D48) -> -487.47 | F48: =IF(D48=0,"",(C48)/(D48)) -> 0.54120471 | G48: =128.72 -> 128.72 | I48: =(G48)-(H48) -> 128.72 | J48: =IF(H48=0,"",(G48)/(H48)) | M48: =(K48)-(L48) -> 0 | N48: =IF(L48=0,"",(K48)/(L48)) | Q48: =(O48)-(P48) -> 0 | R48: =IF(P48=0,"",(O48)/(P48)) | S48: =770 -> 770 | T48: =666.67 -> 666.67 | U48: =(S48)-(T48) -> 103.33 | V48: =IF(T48=0,"",(S48)/(T48)) -> 1.1549942 | W48: =((((C48)+(G48))+(K48))+(O48))+(S48) -> 1473.75 | X48: =((((D48)+(H48))+(L48))+(P48))+(T48) -> 1729.17 | Y48: =(W48)-(X48) -> -255.42 | Z48: =IF(X48=0,"",(W48)/(X48)) -> 0.85228751
B49: Total 6400 Office Expense | C49: =((((C44)+(C45))+(C46))+(C47))+(C48) -> 7934.01 | D49: =((((D44)+(D45))+(D46))+(D47))+(D48) -> 7444.16 | E49: =(C49)-(D49) -> 489.85 | F49: =IF(D49=0,"",(C49)/(D49)) -> 1.0658033 | G49: =((((G44)+(G45))+(G46))+(G47))+(G48) -> 128.72 | H49: =((((H44)+(H45))+(H46))+(H47))+(H48) -> 3000 | I49: =(G49)-(H49) -> -2871.28 | J49: =IF(H49=0,"",(G49)/(H49)) -> 0.042906667 | K49: =((((K44)+(K45))+(K46))+(K47))+(K48) -> 0 | L49: =((((L44)+(L45))+(L46))+(L47))+(L48) -> 0 | M49: =(K49)-(L49) -> 0 | N49: =IF(L49=0,"",(K49)/(L49)) | O49: =((((O44)+(O45))+(O46))+(O47))+(O48) -> 457.14 | P49: =((((P44)+(P45))+(P46))+(P47))+(P48) -> 0 | Q49: =(O49)-(P49) -> 457.14 | R49: =IF(P49=0,"",(O49)/(P49)) | S49: =((((S44)+(S45))+(S46))+(S47))+(S48) -> 784.93 | T49: =((((T44)+(T45))+(T46))+(T47))+(T48) -> 2000 | U49: =(S49)-(T49) -> -1215.07 | V49: =IF(T49=0,"",(S49)/(T49)) -> 0.392465 | W49: =((((C49)+(G49))+(K49))+(O49))+(S49) -> 9304.8 | X49: =((((D49)+(H49))+(L49))+(P49))+(T49) -> 12444.16 | Y49: =(W49)-(X49) -> -3139.36 | Z49: =IF(X49=0,"",(W49)/(X49)) -> 0.74772423
B50: 6500 Facility Expense | E50: =(C50)-(D50) -> 0 | F50: =IF(D50=0,"",(C50)/(D50)) | I50: =(G50)-(H50) -> 0 | J50: =IF(H50=0,"",(G50)/(H50)) | M50: =(K50)-(L50) -> 0 | N50: =IF(L50=0,"",(K50)/(L50)) | Q50: =(O50)-(P50) -> 0 | R50: =IF(P50=0,"",(O50)/(P50)) | U50: =(S50)-(T50) -> 0 | V50: =IF(T50=0,"",(S50)/(T50)) | W50: =((((C50)+(G50))+(K50))+(O50))+(S50) -> 0 | X50: =((((D50)+(H50))+(L50))+(P50))+(T50) -> 0 | Y50: =(W50)-(X50) -> 0 | Z50: =IF(X50=0,"",(W50)/(X50))
B51: 6505 Rent Expense | C51: =16795.81 -> 16795.81 | D51: =16760.06 -> 16760.06 | E51: =(C51)-(D51) -> 35.75 | F51: =IF(D51=0,"",(C51)/(D51)) -> 1.002133 | I51: =(G51)-(H51) -> 0 | J51: =IF(H51=0,"",(G51)/(H51)) | M51: =(K51)-(L51) -> 0 | N51: =IF(L51=0,"",(K51)/(L51)) | Q51: =(O51)-(P51) -> 0 | R51: =IF(P51=0,"",(O51)/(P51)) | U51: =(S51)-(T51) -> 0 | V51: =IF(T51=0,"",(S51)/(T51)) | W51: =((((C51)+(G51))+(K51))+(O51))+(S51) -> 16795.81 | X51: =((((D51)+(H51))+(L51))+(P51))+(T51) -> 16760.06 | Y51: =(W51)-(X51) -> 35.75 | Z51: =IF(X51=0,"",(W51)/(X51)) -> 1.002133
B52: 6510 CAM Charges | C52: =4521.44 -> 4521.44 | D52: =4341.48 -> 4341.48 | E52: =(C52)-(D52) -> 179.96 | F52: =IF(D52=0,"",(C52)/(D52)) -> 1.0414513 | I52: =(G52)-(H52) -> 0 | J52: =IF(H52=0,"",(G52)/(H52)) | M52: =(K52)-(L52) -> 0 | N52: =IF(L52=0,"",(K52)/(L52)) | Q52: =(O52)-(P52) -> 0 | R52: =IF(P52=0,"",(O52)/(P52)) | U52: =(S52)-(T52) -> 0 | V52: =IF(T52=0,"",(S52)/(T52)) | W52: =((((C52)+(G52))+(K52))+(O52))+(S52) -> 4521.44 | X52: =((((D52)+(H52))+(L52))+(P52))+(T52) -> 4341.48 | Y52: =(W52)-(X52) -> 179.96 | Z52: =IF(X52=0,"",(W52)/(X52)) -> 1.0414513
B53: 6515 Utilities | C53: =7303.23 -> 7303.23 | D53: =6916.67 -> 6916.67 | E53: =(C53)-(D53) -> 386.56 | F53: =IF(D53=0,"",(C53)/(D53)) -> 1.0558882 | I53: =(G53)-(H53) -> 0 | J53: =IF(H53=0,"",(G53)/(H53)) | M53: =(K53)-(L53) -> 0 | N53: =IF(L53=0,"",(K53)/(L53)) | Q53: =(O53)-(P53) -> 0 | R53: =IF(P53=0,"",(O53)/(P53)) | U53: =(S53)-(T53) -> 0 | V53: =IF(T53=0,"",(S53)/(T53)) | W53: =((((C53)+(G53))+(K53))+(O53))+(S53) -> 7303.23 | X53: =((((D53)+(H53))+(L53))+(P53))+(T53) -> 6916.67 | Y53: =(W53)-(X53) -> 386.56 | Z53: =IF(X53=0,"",(W53)/(X53)) -> 1.0558882
B54: 6520 Business Insurance | C54: =1255.56 -> 1255.56 | D54: =1232.11 -> 1232.11 | E54: =(C54)-(D54) -> 23.45 | F54: =IF(D54=0,"",(C54)/(D54)) -> 1.0190324 | I54: =(G54)-(H54) -> 0 | J54: =IF(H54=0,"",(G54)/(H54)) | M54: =(K54)-(L54) -> 0 | N54: =IF(L54=0,"",(K54)/(L54)) | Q54: =(O54)-(P54) -> 0 | R54: =IF(P54=0,"",(O54)/(P54)) | U54: =(S54)-(T54) -> 0 | V54: =IF(T54=0,"",(S54)/(T54)) | W54: =((((C54)+(G54))+(K54))+(O54))+(S54) -> 1255.56 | X54: =((((D54)+(H54))+(L54))+(P54))+(T54) -> 1232.11 | Y54: =(W54)-(X54) -> 23.45 | Z54: =IF(X54=0,"",(W54)/(X54)) -> 1.0190324
B55: 6540 HP Lease Expense | E55: =(C55)-(D55) -> 0 | F55: =IF(D55=0,"",(C55)/(D55)) | G55: =8503.67 -> 8503.67 | H55: =7500 -> 7500 | I55: =(G55)-(H55) -> 1003.67 | J55: =IF(H55=0,"",(G55)/(H55)) -> 1.1338227 | M55: =(K55)-(L55) -> 0 | N55: =IF(L55=0,"",(K55)/(L55)) | Q55: =(O55)-(P55) -> 0 | R55: =IF(P55=0,"",(O55)/(P55)) | T55: =0 -> 0 | U55: =(S55)-(T55) -> 0 | V55: =IF(T55=0,"",(S55)/(T55)) | W55: =((((C55)+(G55))+(K55))+(O55))+(S55) -> 8503.67 | X55: =((((D55)+(H55))+(L55))+(P55))+(T55) -> 7500 | Y55: =(W55)-(X55) -> 1003.67 | Z55: =IF(X55=0,"",(W55)/(X55)) -> 1.1338227
B56: Total 6500 Facility Expense | C56: =(((((C50)+(C51))+(C52))+(C53))+(C54))+(C55) -> 29876.04 | D56: =(((((D50)+(D51))+(D52))+(D53))+(D54))+(D55) -> 29250.32 | E56: =(C56)-(D56) -> 625.72 | F56: =IF(D56=0,"",(C56)/(D56)) -> 1.0213919 | G56: =(((((G50)+(G51))+(G52))+(G53))+(G54))+(G55) -> 8503.67 | H56: =(((((H50)+(H51))+(H52))+(H53))+(H54))+(H55) -> 7500 | I56: =(G56)-(H56) -> 1003.67 | J56: =IF(H56=0,"",(G56)/(H56)) -> 1.1338227 | K56: =(((((K50)+(K51))+(K52))+(K53))+(K54))+(K55) -> 0 | L56: =(((((L50)+(L51))+(L52))+(L53))+(L54))+(L55) -> 0 | M56: =(K56)-(L56) -> 0 | N56: =IF(L56=0,"",(K56)/(L56)) | O56: =(((((O50)+(O51))+(O52))+(O53))+(O54))+(O55) -> 0 | P56: =(((((P50)+(P51))+(P52))+(P53))+(P54))+(P55) -> 0 | Q56: =(O56)-(P56) -> 0 | R56: =IF(P56=0,"",(O56)/(P56)) | S56: =(((((S50)+(S51))+(S52))+(S53))+(S54))+(S55) -> 0 | T56: =(((((T50)+(T51))+(T52))+(T53))+(T54))+(T55) -> 0 | U56: =(S56)-(T56) -> 0 | V56: =IF(T56=0,"",(S56)/(T56)) | W56: =((((C56)+(G56))+(K56))+(O56))+(S56) -> 38379.71 | X56: =((((D56)+(H56))+(L56))+(P56))+(T56) -> 36750.32 | Y56: =(W56)-(X56) -> 1629.39 | Z56: =IF(X56=0,"",(W56)/(X56)) -> 1.0443368
B57: 6600 Other Operating Expenses | E57: =(C57)-(D57) -> 0 | F57: =IF(D57=0,"",(C57)/(D57)) | I57: =(G57)-(H57) -> 0 | J57: =IF(H57=0,"",(G57)/(H57)) | M57: =(K57)-(L57) -> 0 | N57: =IF(L57=0,"",(K57)/(L57)) | Q57: =(O57)-(P57) -> 0 | R57: =IF(P57=0,"",(O57)/(P57)) | U57: =(S57)-(T57) -> 0 | V57: =IF(T57=0,"",(S57)/(T57)) | W57: =((((C57)+(G57))+(K57))+(O57))+(S57) -> 0 | X57: =((((D57)+(H57))+(L57))+(P57))+(T57) -> 0 | Y57: =(W57)-(X57) -> 0 | Z57: =IF(X57=0,"",(W57)/(X57))
B58: 6605 Advertising & Marketing | C58: =4138.74 -> 4138.74 | D58: =5187.5 -> 5187.5 | E58: =(C58)-(D58) -> -1048.76 | F58: =IF(D58=0,"",(C58)/(D58)) -> 0.7978294 | G58: =500 -> 500 | I58: =(G58)-(H58) -> 500 | J58: =IF(H58=0,"",(G58)/(H58)) | M58: =(K58)-(L58) -> 0 | N58: =IF(L58=0,"",(K58)/(L58)) | Q58: =(O58)-(P58) -> 0 | R58: =IF(P58=0,"",(O58)/(P58)) | S58: =500 -> 500 | U58: =(S58)-(T58) -> 500 | V58: =IF(T58=0,"",(S58)/(T58)) | W58: =((((C58)+(G58))+(K58))+(O58))+(S58) -> 5138.74 | X58: =((((D58)+(H58))+(L58))+(P58))+(T58) -> 5187.5 | Y58: =(W58)-(X58) -> -48.76 | Z58: =IF(X58=0,"",(W58)/(X58)) -> 0.99060048
B59: 6610 Software Costs | C59: =2771.16 -> 2771.16 | D59: =2335.26 -> 2335.26 | E59: =(C59)-(D59) -> 435.9 | F59: =IF(D59=0,"",(C59)/(D59)) -> 1.1866602 | I59: =(G59)-(H59) -> 0 | J59: =IF(H59=0,"",(G59)/(H59)) | M59: =(K59)-(L59) -> 0 | N59: =IF(L59=0,"",(K59)/(L59)) | O59: =85 -> 85 | P59: =1041.67 -> 1041.67 | Q59: =(O59)-(P59) -> -956.67 | R59: =IF(P59=0,"",(O59)/(P59)) -> 0.081599739 | S59: =334.92 -> 334.92 | U59: =(S59)-(T59) -> 334.92 | V59: =IF(T59=0,"",(S59)/(T59)) | W59: =((((C59)+(G59))+(K59))+(O59))+(S59) -> 3191.08 | X59: =((((D59)+(H59))+(L59))+(P59))+(T59) -> 3376.93 | Y59: =(W59)-(X59) -> -185.85 | Z59: =IF(X59=0,"",(W59)/(X59)) -> 0.94496481
B60: 6615 Vehicle Expense | C60: =576.25 -> 576.25 | D60: =1729.17 -> 1729.17 | E60: =(C60)-(D60) -> -1152.92 | F60: =IF(D60=0,"",(C60)/(D60)) -> 0.33325237 | I60: =(G60)-(H60) -> 0 | J60: =IF(H60=0,"",(G60)/(H60)) | M60: =(K60)-(L60) -> 0 | N60: =IF(L60=0,"",(K60)/(L60)) | O60: 75 | Q60: =(O60)-(P60) -> 75 | R60: =IF(P60=0,"",(O60)/(P60)) | U60: =(S60)-(T60) -> 0 | V60: =IF(T60=0,"",(S60)/(T60)) | W60: =((((C60)+(G60))+(K60))+(O60))+(S60) -> 651.25 | X60: =((((D60)+(H60))+(L60))+(P60))+(T60) -> 1729.17 | Y60: =(W60)-(X60) -> -1077.92 | Z60: =IF(X60=0,"",(W60)/(X60)) -> 0.37662578
B61: 6620 Auto Lease Expense | C61: =2320.64 -> 2320.64 | D61: =2320.64 -> 2320.64 | E61: =(C61)-(D61) -> 0 | F61: =IF(D61=0,"",(C61)/(D61)) -> 1 | I61: =(G61)-(H61) -> 0 | J61: =IF(H61=0,"",(G61)/(H61)) | M61: =(K61)-(L61) -> 0 | N61: =IF(L61=0,"",(K61)/(L61)) | Q61: =(O61)-(P61) -> 0 | R61: =IF(P61=0,"",(O61)/(P61)) | U61: =(S61)-(T61) -> 0 | V61: =IF(T61=0,"",(S61)/(T61)) | W61: =((((C61)+(G61))+(K61))+(O61))+(S61) -> 2320.64 | X61: =((((D61)+(H61))+(L61))+(P61))+(T61) -> 2320.64 | Y61: =(W61)-(X61) -> 0 | Z61: =IF(X61=0,"",(W61)/(X61)) -> 1
B62: 6625 Client Gifts | D62: =425 -> 425 | E62: =(C62)-(D62) -> -425 | F62: =IF(D62=0,"",(C62)/(D62)) -> 0 | I62: =(G62)-(H62) -> 0 | J62: =IF(H62=0,"",(G62)/(H62)) | M62: =(K62)-(L62) -> 0 | N62: =IF(L62=0,"",(K62)/(L62)) | Q62: =(O62)-(P62) -> 0 | R62: =IF(P62=0,"",(O62)/(P62)) | U62: =(S62)-(T62) -> 0 | V62: =IF(T62=0,"",(S62)/(T62)) | W62: =((((C62)+(G62))+(K62))+(O62))+(S62) -> 0 | X62: =((((D62)+(H62))+(L62))+(P62))+(T62) -> 425 | Y62: =(W62)-(X62) -> -425 | Z62: =IF(X62=0,"",(W62)/(X62)) -> 0
B63: 6630 Shipping & Postage | C63: =1186.01 -> 1186.01 | D63: =691.67 -> 691.67 | E63: =(C63)-(D63) -> 494.34 | F63: =IF(D63=0,"",(C63)/(D63)) -> 1.714705 | I63: =(G63)-(H63) -> 0 | J63: =IF(H63=0,"",(G63)/(H63)) | M63: =(K63)-(L63) -> 0 | N63: =IF(L63=0,"",(K63)/(L63)) | Q63: =(O63)-(P63) -> 0 | R63: =IF(P63=0,"",(O63)/(P63)) | U63: =(S63)-(T63) -> 0 | V63: =IF(T63=0,"",(S63)/(T63)) | W63: =((((C63)+(G63))+(K63))+(O63))+(S63) -> 1186.01 | X63: =((((D63)+(H63))+(L63))+(P63))+(T63) -> 691.67 | Y63: =(W63)-(X63) -> 494.34 | Z63: =IF(X63=0,"",(W63)/(X63)) -> 1.714705
B64: 6635 Travel - Management | C64: =5187.04 -> 5187.04 | D64: =516.67 -> 516.67 | E64: =(C64)-(D64) -> 4670.37 | F64: =IF(D64=0,"",(C64)/(D64)) -> 10.039367 | I64: =(G64)-(H64) -> 0 | J64: =IF(H64=0,"",(G64)/(H64)) | M64: =(K64)-(L64) -> 0 | N64: =IF(L64=0,"",(K64)/(L64)) | P64: =520.83 -> 520.83 | Q64: =(O64)-(P64) -> -520.83 | R64: =IF(P64=0,"",(O64)/(P64)) -> 0 | U64: =(S64)-(T64) -> 0 | V64: =IF(T64=0,"",(S64)/(T64)) | W64: =((((C64)+(G64))+(K64))+(O64))+(S64) -> 5187.04 | X64: =((((D64)+(H64))+(L64))+(P64))+(T64) -> 1037.5 | Y64: =(W64)-(X64) -> 4149.54 | Z64: =IF(X64=0,"",(W64)/(X64)) -> 4.9995566
B65: 6640 Bank Service Charges | C65: =272.7 -> 272.7 | D65: =345.83 -> 345.83 | E65: =(C65)-(D65) -> -73.13 | F65: =IF(D65=0,"",(C65)/(D65)) -> 0.78853772 | G65: =1425.52 -> 1425.52 | I65: =(G65)-(H65) -> 1425.52 | J65: =IF(H65=0,"",(G65)/(H65)) | M65: =(K65)-(L65) -> 0 | N65: =IF(L65=0,"",(K65)/(L65)) | Q65: =(O65)-(P65) -> 0 | R65: =IF(P65=0,"",(O65)/(P65)) | S65: =23.1 -> 23.1 | U65: =(S65)-(T65) -> 23.1 | V65: =IF(T65=0,"",(S65)/(T65)) | W65: =((((C65)+(G65))+(K65))+(O65))+(S65) -> 1721.32 | X65: =((((D65)+(H65))+(L65))+(P65))+(T65) -> 345.83 | Y65: =(W65)-(X65) -> 1375.49 | Z65: =IF(X65=0,"",(W65)/(X65)) -> 4.9773588
B66: 6645 Disability & Life Insurance | C66: =171.54 -> 171.54 | D66: =171.54 -> 171.54 | E66: =(C66)-(D66) -> 0 | F66: =IF(D66=0,"",(C66)/(D66)) -> 1 | I66: =(G66)-(H66) -> 0 | J66: =IF(H66=0,"",(G66)/(H66)) | M66: =(K66)-(L66) -> 0 | N66: =IF(L66=0,"",(K66)/(L66)) | Q66: =(O66)-(P66) -> 0 | R66: =IF(P66=0,"",(O66)/(P66)) | U66: =(S66)-(T66) -> 0 | V66: =IF(T66=0,"",(S66)/(T66)) | W66: =((((C66)+(G66))+(K66))+(O66))+(S66) -> 171.54 | X66: =((((D66)+(H66))+(L66))+(P66))+(T66) -> 171.54 | Y66: =(W66)-(X66) -> 0 | Z66: =IF(X66=0,"",(W66)/(X66)) -> 1
B67: 6650 Business Tax & Licenses | D67: =345.83 -> 345.83 | E67: =(C67)-(D67) -> -345.83 | F67: =IF(D67=0,"",(C67)/(D67)) -> 0 | I67: =(G67)-(H67) -> 0 | J67: =IF(H67=0,"",(G67)/(H67)) | M67: =(K67)-(L67) -> 0 | N67: =IF(L67=0,"",(K67)/(L67)) | Q67: =(O67)-(P67) -> 0 | R67: =IF(P67=0,"",(O67)/(P67)) | U67: =(S67)-(T67) -> 0 | V67: =IF(T67=0,"",(S67)/(T67)) | W67: =((((C67)+(G67))+(K67))+(O67))+(S67) -> 0 | X67: =((((D67)+(H67))+(L67))+(P67))+(T67) -> 345.83 | Y67: =(W67)-(X67) -> -345.83 | Z67: =IF(X67=0,"",(W67)/(X67)) -> 0
B68: 6660 Meals and Entertainment | C68: =723.7 -> 723.7 | D68: =1729.17 -> 1729.17 | E68: =(C68)-(D68) -> -1005.47 | F68: =IF(D68=0,"",(C68)/(D68)) -> 0.41852449 | I68: =(G68)-(H68) -> 0 | J68: =IF(H68=0,"",(G68)/(H68)) | M68: =(K68)-(L68) -> 0 | N68: =IF(L68=0,"",(K68)/(L68)) | O68: =581.49 -> 581.49 | Q68: =(O68)-(P68) -> 581.49 | R68: =IF(P68=0,"",(O68)/(P68)) | U68: =(S68)-(T68) -> 0 | V68: =IF(T68=0,"",(S68)/(T68)) | W68: =((((C68)+(G68))+(K68))+(O68))+(S68) -> 1305.19 | X68: =((((D68)+(H68))+(L68))+(P68))+(T68) -> 1729.17 | Y68: =(W68)-(X68) -> -423.98 | Z68: =IF(X68=0,"",(W68)/(X68)) -> 0.75480722
B69: 6665 Dues & Subscriptions | C69: =1058.99 -> 1058.99 | D69: =312.32 -> 312.32 | E69: =(C69)-(D69) -> 746.67 | F69: =IF(D69=0,"",(C69)/(D69)) -> 3.3907211 | G69: =166.75 -> 166.75 | I69: =(G69)-(H69) -> 166.75 | J69: =IF(H69=0,"",(G69)/(H69)) | M69: =(K69)-(L69) -> 0 | N69: =IF(L69=0,"",(K69)/(L69)) | Q69: =(O69)-(P69) -> 0 | R69: =IF(P69=0,"",(O69)/(P69)) | U69: =(S69)-(T69) -> 0 | V69: =IF(T69=0,"",(S69)/(T69)) | W69: =((((C69)+(G69))+(K69))+(O69))+(S69) -> 1225.74 | X69: =((((D69)+(H69))+(L69))+(P69))+(T69) -> 312.32 | Y69: =(W69)-(X69) -> 913.42 | Z69: =IF(X69=0,"",(W69)/(X69)) -> 3.9246286
B70: 6670 QuickBooks Payments Fees | D70: =172.92 -> 172.92 | E70: =(C70)-(D70) -> -172.92 | F70: =IF(D70=0,"",(C70)/(D70)) -> 0 | I70: =(G70)-(H70) -> 0 | J70: =IF(H70=0,"",(G70)/(H70)) | M70: =(K70)-(L70) -> 0 | N70: =IF(L70=0,"",(K70)/(L70)) | Q70: =(O70)-(P70) -> 0 | R70: =IF(P70=0,"",(O70)/(P70)) | U70: =(S70)-(T70) -> 0 | V70: =IF(T70=0,"",(S70)/(T70)) | W70: =((((C70)+(G70))+(K70))+(O70))+(S70) -> 0 | X70: =((((D70)+(H70))+(L70))+(P70))+(T70) -> 172.92 | Y70: =(W70)-(X70) -> -172.92 | Z70: =IF(X70=0,"",(W70)/(X70)) -> 0
B71: 6690 Vehicle Insurance | C71: =482.82 -> 482.82 | D71: =536 -> 536 | E71: =(C71)-(D71) -> -53.18 | F71: =IF(D71=0,"",(C71)/(D71)) -> 0.90078358 | I71: =(G71)-(H71) -> 0 | J71: =IF(H71=0,"",(G71)/(H71)) | M71: =(K71)-(L71) -> 0 | N71: =IF(L71=0,"",(K71)/(L71)) | Q71: =(O71)-(P71) -> 0 | R71: =IF(P71=0,"",(O71)/(P71)) | U71: =(S71)-(T71) -> 0 | V71: =IF(T71=0,"",(S71)/(T71)) | W71: =((((C71)+(G71))+(K71))+(O71))+(S71) -> 482.82 | X71: =((((D71)+(H71))+(L71))+(P71))+(T71) -> 536 | Y71: =(W71)-(X71) -> -53.18 | Z71: =IF(X71=0,"",(W71)/(X71)) -> 0.90078358
B72: 6700 Donations | D72: =172.92 -> 172.92 | E72: =(C72)-(D72) -> -172.92 | F72: =IF(D72=0,"",(C72)/(D72)) -> 0 | I72: =(G72)-(H72) -> 0 | J72: =IF(H72=0,"",(G72)/(H72)) | M72: =(K72)-(L72) -> 0 | N72: =IF(L72=0,"",(K72)/(L72)) | Q72: =(O72)-(P72) -> 0 | R72: =IF(P72=0,"",(O72)/(P72)) | U72: =(S72)-(T72) -> 0 | V72: =IF(T72=0,"",(S72)/(T72)) | W72: =((((C72)+(G72))+(K72))+(O72))+(S72) -> 0 | X72: =((((D72)+(H72))+(L72))+(P72))+(T72) -> 172.92 | Y72: =(W72)-(X72) -> -172.92 | Z72: =IF(X72=0,"",(W72)/(X72)) -> 0
B73: 6705 Bad Debt Expense | D73: =1729.17 -> 1729.17 | E73: =(C73)-(D73) -> -1729.17 | F73: =IF(D73=0,"",(C73)/(D73)) -> 0 | I73: =(G73)-(H73) -> 0 | J73: =IF(H73=0,"",(G73)/(H73)) | M73: =(K73)-(L73) -> 0 | N73: =IF(L73=0,"",(K73)/(L73)) | Q73: =(O73)-(P73) -> 0 | R73: =IF(P73=0,"",(O73)/(P73)) | U73: =(S73)-(T73) -> 0 | V73: =IF(T73=0,"",(S73)/(T73)) | W73: =((((C73)+(G73))+(K73))+(O73))+(S73) -> 0 | X73: =((((D73)+(H73))+(L73))+(P73))+(T73) -> 1729.17 | Y73: =(W73)-(X73) -> -1729.17 | Z73: =IF(X73=0,"",(W73)/(X73)) -> 0
B74: 6715 Other Miscellaneous Expense | D74: =34.58 -> 34.58 | E74: =(C74)-(D74) -> -34.58 | F74: =IF(D74=0,"",(C74)/(D74)) -> 0 | I74: =(G74)-(H74) -> 0 | J74: =IF(H74=0,"",(G74)/(H74)) | M74: =(K74)-(L74) -> 0 | N74: =IF(L74=0,"",(K74)/(L74)) | Q74: =(O74)-(P74) -> 0 | R74: =IF(P74=0,"",(O74)/(P74)) | U74: =(S74)-(T74) -> 0 | V74: =IF(T74=0,"",(S74)/(T74)) | W74: =((((C74)+(G74))+(K74))+(O74))+(S74) -> 0 | X74: =((((D74)+(H74))+(L74))+(P74))+(T74) -> 34.58 | Y74: =(W74)-(X74) -> -34.58 | Z74: =IF(X74=0,"",(W74)/(X74)) -> 0
B75: Total 6600 Other Operating Expenses | C75: =(((((((((((((((((C57)+(C58))+(C59))+(C60))+(C61))+(C62))+(C63))+(C64))+(C65))+(C66))+(C67))+(C68))+(C69))+(C70))+(C71))+(C72))+(C73))+(C74) -> 18889.59 | D75: =(((((((((((((((((D57)+(D58))+(D59))+(D60))+(D61))+(D62))+(D63))+(D64))+(D65))+(D66))+(D67))+(D68))+(D69))+(D70))+(D71))+(D72))+(D73))+(D74) -> 18756.19 | E75: =(C75)-(D75) -> 133.4 | F75: =IF(D75=0,"",(C75)/(D75)) -> 1.0071123 | G75: =(((((((((((((((((G57)+(G58))+(G59))+(G60))+(G61))+(G62))+(G63))+(G64))+(G65))+(G66))+(G67))+(G68))+(G69))+(G70))+(G71))+(G72))+(G73))+(G74) -> 2092.27 | H75: =(((((((((((((((((H57)+(H58))+(H59))+(H60))+(H61))+(H62))+(H63))+(H64))+(H65))+(H66))+(H67))+(H68))+(H69))+(H70))+(H71))+(H72))+(H73))+(H74) -> 0 | I75: =(G75)-(H75) -> 2092.27 | J75: =IF(H75=0,"",(G75)/(H75)) | K75: =(((((((((((((((((K57)+(K58))+(K59))+(K60))+(K61))+(K62))+(K63))+(K64))+(K65))+(K66))+(K67))+(K68))+(K69))+(K70))+(K71))+(K72))+(K73))+(K74) -> 0 | L75: =(((((((((((((((((L57)+(L58))+(L59))+(L60))+(L61))+(L62))+(L63))+(L64))+(L65))+(L66))+(L67))+(L68))+(L69))+(L70))+(L71))+(L72))+(L73))+(L74) -> 0 | M75: =(K75)-(L75) -> 0 | N75: =IF(L75=0,"",(K75)/(L75)) | O75: =(((((((((((((((((O57)+(O58))+(O59))+(O60))+(O61))+(O62))+(O63))+(O64))+(O65))+(O66))+(O67))+(O68))+(O69))+(O70))+(O71))+(O72))+(O73))+(O74) -> 741.49 | P75: =(((((((((((((((((P57)+(P58))+(P59))+(P60))+(P61))+(P62))+(P63))+(P64))+(P65))+(P66))+(P67))+(P68))+(P69))+(P70))+(P71))+(P72))+(P73))+(P74) -> 1562.5 | Q75: =(O75)-(P75) -> -821.01 | R75: =IF(P75=0,"",(O75)/(P75)) -> 0.4745536 | S75: =(((((((((((((((((S57)+(S58))+(S59))+(S60))+(S61))+(S62))+(S63))+(S64))+(S65))+(S66))+(S67))+(S68))+(S69))+(S70))+(S71))+(S72))+(S73))+(S74) -> 858.02 | T75: =(((((((((((((((((T57)+(T58))+(T59))+(T60))+(T61))+(T62))+(T63))+(T64))+(T65))+(T66))+(T67))+(T68))+(T69))+(T70))+(T71))+(T72))+(T73))+(T74) -> 0 | U75: =(S75)-(T75) -> 858.02 | V75: =IF(T75=0,"",(S75)/(T75)) | W75: =((((C75)+(G75))+(K75))+(O75))+(S75) -> 22581.37 | X75: =((((D75)+(H75))+(L75))+(P75))+(T75) -> 20318.69 | Y75: =(W75)-(X75) -> 2262.68 | Z75: =IF(X75=0,"",(W75)/(X75)) -> 1.1113595
B76: Total Expenses | C76: =(((((((((C27)+(C28))+(C29))+(C30))+(C31))+(C37))+(C43))+(C49))+(C56))+(C75) -> 84881.68 | D76: =(((((((((D27)+(D28))+(D29))+(D30))+(D31))+(D37))+(D43))+(D49))+(D56))+(D75) -> 75609.2 | E76: =(C76)-(D76) -> 9272.48 | F76: =IF(D76=0,"",(C76)/(D76)) -> 1.1226369 | G76: =(((((((((G27)+(G28))+(G29))+(G30))+(G31))+(G37))+(G43))+(G49))+(G56))+(G75) -> 27194.48 | H76: =(((((((((H27)+(H28))+(H29))+(H30))+(H31))+(H37))+(H43))+(H49))+(H56))+(H75) -> 26533.89 | I76: =(G76)-(H76) -> 660.59 | J76: =IF(H76=0,"",(G76)/(H76)) -> 1.0248961 | K76: =(((((((((K27)+(K28))+(K29))+(K30))+(K31))+(K37))+(K43))+(K49))+(K56))+(K75) -> 1351.19 | L76: =(((((((((L27)+(L28))+(L29))+(L30))+(L31))+(L37))+(L43))+(L49))+(L56))+(L75) -> 1145.27 | M76: =(K76)-(L76) -> 205.92 | N76: =IF(L76=0,"",(K76)/(L76)) -> 1.1798004 | O76: =(((((((((O27)+(O28))+(O29))+(O30))+(O31))+(O37))+(O43))+(O49))+(O56))+(O75) -> 10083.3 | P76: =(((((((((P27)+(P28))+(P29))+(P30))+(P31))+(P37))+(P43))+(P49))+(P56))+(P75) -> 8434.17 | Q76: =(O76)-(P76) -> 1649.13 | R76: =IF(P76=0,"",(O76)/(P76)) -> 1.1955296 | S76: =(((((((((S27)+(S28))+(S29))+(S30))+(S31))+(S37))+(S43))+(S49))+(S56))+(S75) -> 2952.48 | T76: =(((((((((T27)+(T28))+(T29))+(T30))+(T31))+(T37))+(T43))+(T49))+(T56))+(T75) -> 2992.6 | U76: =(S76)-(T76) -> -40.12 | V76: =IF(T76=0,"",(S76)/(T76)) -> 0.9865936 | W76: =((((C76)+(G76))+(K76))+(O76))+(S76) -> 126463.13 | X76: =((((D76)+(H76))+(L76))+(P76))+(T76) -> 114715.13 | Y76: =(W76)-(X76) -> 11748 | Z76: =IF(X76=0,"",(W76)/(X76)) -> 1.1024102
B77: Net Operating Income | C77: =(C20)-(C76) -> -84881.68 | D77: =(D20)-(D76) -> -75609.2 | E77: =(C77)-(D77) -> -9272.48 | F77: =IF(D77=0,"",(C77)/(D77)) -> 1.1226369 | G77: =(G20)-(G76) -> 107059.77 | H77: =(H20)-(H76) -> 59235.05 | I77: =(G77)-(H77) -> 47824.72 | J77: =IF(H77=0,"",(G77)/(H77)) -> 1.807372 | K77: =(K20)-(K76) -> 198.81 | L77: =(L20)-(L76) -> 6104.73 | M77: =(K77)-(L77) -> -5905.92 | N77: =IF(L77=0,"",(K77)/(L77)) -> 0.032566551 | O77: =(O20)-(O76) -> 7312.02 | P77: =(P20)-(P76) -> 50288.66 | Q77: =(O77)-(P77) -> -42976.64 | R77: =IF(P77=0,"",(O77)/(P77)) -> 0.14540097 | S77: =(S20)-(S76) -> -12945.29 | T77: =(T20)-(T76) -> 60499.18 | U77: =(S77)-(T77) -> -73444.47 | V77: =IF(T77=0,"",(S77)/(T77)) -> -0.21397464 | W77: =((((C77)+(G77))+(K77))+(O77))+(S77) -> 16743.63 | X77: =((((D77)+(H77))+(L77))+(P77))+(T77) -> 100518.42 | Y77: =(W77)-(X77) -> -83774.79 | Z77: =IF(X77=0,"",(W77)/(X77)) -> 0.16657275
B78: Other Income
B79: 7005 Other Miscellaneous Income | C79: =639.99 -> 639.99 | E79: =(C79)-(D79) -> 639.99 | F79: =IF(D79=0,"",(C79)/(D79)) | I79: =(G79)-(H79) -> 0 | J79: =IF(H79=0,"",(G79)/(H79)) | M79: =(K79)-(L79) -> 0 | N79: =IF(L79=0,"",(K79)/(L79)) | Q79: =(O79)-(P79) -> 0 | R79: =IF(P79=0,"",(O79)/(P79)) | U79: =(S79)-(T79) -> 0 | V79: =IF(T79=0,"",(S79)/(T79)) | W79: =((((C79)+(G79))+(K79))+(O79))+(S79) -> 639.99 | X79: =((((D79)+(H79))+(L79))+(P79))+(T79) -> 0 | Y79: =(W79)-(X79) -> 639.99 | Z79: =IF(X79=0,"",(W79)/(X79))
B80: 7010 Other Income – Insurance Proceeds | C80: =12897.29 -> 12897.29 | E80: =(C80)-(D80) -> 12897.29 | F80: =IF(D80=0,"",(C80)/(D80)) | I80: =(G80)-(H80) -> 0 | J80: =IF(H80=0,"",(G80)/(H80)) | M80: =(K80)-(L80) -> 0 | N80: =IF(L80=0,"",(K80)/(L80)) | Q80: =(O80)-(P80) -> 0 | R80: =IF(P80=0,"",(O80)/(P80)) | U80: =(S80)-(T80) -> 0 | V80: =IF(T80=0,"",(S80)/(T80)) | W80: =((((C80)+(G80))+(K80))+(O80))+(S80) -> 12897.29 | X80: =((((D80)+(H80))+(L80))+(P80))+(T80) -> 0 | Y80: =(W80)-(X80) -> 12897.29 | Z80: =IF(X80=0,"",(W80)/(X80))
B81: Total Other Income | C81: =(C79)+(C80) -> 13537.28 | D81: =(D79)+(D80) -> 0 | E81: =(C81)-(D81) -> 13537.28 | F81: =IF(D81=0,"",(C81)/(D81)) | G81: =(G79)+(G80) -> 0 | H81: =(H79)+(H80) -> 0 | I81: =(G81)-(H81) -> 0 | J81: =IF(H81=0,"",(G81)/(H81)) | K81: =(K79)+(K80) -> 0 | L81: =(L79)+(L80) -> 0 | M81: =(K81)-(L81) -> 0 | N81: =IF(L81=0,"",(K81)/(L81)) | O81: =(O79)+(O80) -> 0 | P81: =(P79)+(P80) -> 0 | Q81: =(O81)-(P81) -> 0 | R81: =IF(P81=0,"",(O81)/(P81)) | S81: =(S79)+(S80) -> 0 | T81: =(T79)+(T80) -> 0 | U81: =(S81)-(T81) -> 0 | V81: =IF(T81=0,"",(S81)/(T81)) | W81: =((((C81)+(G81))+(K81))+(O81))+(S81) -> 13537.28 | X81: =((((D81)+(H81))+(L81))+(P81))+(T81) -> 0 | Y81: =(W81)-(X81) -> 13537.28 | Z81: =IF(X81=0,"",(W81)/(X81))
B82: Other Expenses
B83: 6195 Late Fees | E83: =(C83)-(D83) -> 0 | F83: =IF(D83=0,"",(C83)/(D83)) | G83: =17.04 -> 17.04 | I83: =(G83)-(H83) -> 17.04 | J83: =IF(H83=0,"",(G83)/(H83)) | M83: =(K83)-(L83) -> 0 | N83: =IF(L83=0,"",(K83)/(L83)) | Q83: =(O83)-(P83) -> 0 | R83: =IF(P83=0,"",(O83)/(P83)) | U83: =(S83)-(T83) -> 0 | V83: =IF(T83=0,"",(S83)/(T83)) | W83: =((((C83)+(G83))+(K83))+(O83))+(S83) -> 17.04 | X83: =((((D83)+(H83))+(L83))+(P83))+(T83) -> 0 | Y83: =(W83)-(X83) -> 17.04 | Z83: =IF(X83=0,"",(W83)/(X83))
B84: 7100 Interest Expense | C84: =27038.72 -> 27038.72 | D84: =16855.71 -> 16855.71 | E84: =(C84)-(D84) -> 10183.01 | F84: =IF(D84=0,"",(C84)/(D84)) -> 1.6041282 | I84: =(G84)-(H84) -> 0 | J84: =IF(H84=0,"",(G84)/(H84)) | M84: =(K84)-(L84) -> 0 | N84: =IF(L84=0,"",(K84)/(L84)) | Q84: =(O84)-(P84) -> 0 | R84: =IF(P84=0,"",(O84)/(P84)) | U84: =(S84)-(T84) -> 0 | V84: =IF(T84=0,"",(S84)/(T84)) | W84: =((((C84)+(G84))+(K84))+(O84))+(S84) -> 27038.72 | X84: =((((D84)+(H84))+(L84))+(P84))+(T84) -> 16855.71 | Y84: =(W84)-(X84) -> 10183.01 | Z84: =IF(X84=0,"",(W84)/(X84)) -> 1.6041282
B85: 7105 Interest Expense - Shareholder's Loan | C85: =10169.38 -> 10169.38 | D85: 8914.86 | E85: =(C85)-(D85) -> 1254.52 | F85: =IF(D85=0,"",(C85)/(D85)) -> 1.1407223 | I85: =(G85)-(H85) -> 0 | J85: =IF(H85=0,"",(G85)/(H85)) | M85: =(K85)-(L85) -> 0 | N85: =IF(L85=0,"",(K85)/(L85)) | Q85: =(O85)-(P85) -> 0 | R85: =IF(P85=0,"",(O85)/(P85)) | U85: =(S85)-(T85) -> 0 | V85: =IF(T85=0,"",(S85)/(T85)) | W85: =((((C85)+(G85))+(K85))+(O85))+(S85) -> 10169.38 | X85: =((((D85)+(H85))+(L85))+(P85))+(T85) -> 8914.86 | Y85: =(W85)-(X85) -> 1254.52 | Z85: =IF(X85=0,"",(W85)/(X85)) -> 1.1407223
B86: 7200 Depreciation Expense | C86: =4746.6 -> 4746.6 | D86: =3621.9 -> 3621.9 | E86: =(C86)-(D86) -> 1124.7 | F86: =IF(D86=0,"",(C86)/(D86)) -> 1.3105276 | I86: =(G86)-(H86) -> 0 | J86: =IF(H86=0,"",(G86)/(H86)) | M86: =(K86)-(L86) -> 0 | N86: =IF(L86=0,"",(K86)/(L86)) | Q86: =(O86)-(P86) -> 0 | R86: =IF(P86=0,"",(O86)/(P86)) | U86: =(S86)-(T86) -> 0 | V86: =IF(T86=0,"",(S86)/(T86)) | W86: =((((C86)+(G86))+(K86))+(O86))+(S86) -> 4746.6 | X86: =((((D86)+(H86))+(L86))+(P86))+(T86) -> 3621.9 | Y86: =(W86)-(X86) -> 1124.7 | Z86: =IF(X86=0,"",(W86)/(X86)) -> 1.3105276
B87: 7205 Amortization Expense | C87: =12988.8 -> 12988.8 | D87: =12988.8 -> 12988.8 | E87: =(C87)-(D87) -> 0 | F87: =IF(D87=0,"",(C87)/(D87)) -> 1 | I87: =(G87)-(H87) -> 0 | J87: =IF(H87=0,"",(G87)/(H87)) | M87: =(K87)-(L87) -> 0 | N87: =IF(L87=0,"",(K87)/(L87)) | Q87: =(O87)-(P87) -> 0 | R87: =IF(P87=0,"",(O87)/(P87)) | U87: =(S87)-(T87) -> 0 | V87: =IF(T87=0,"",(S87)/(T87)) | W87: =((((C87)+(G87))+(K87))+(O87))+(S87) -> 12988.8 | X87: =((((D87)+(H87))+(L87))+(P87))+(T87) -> 12988.8 | Y87: =(W87)-(X87) -> 0 | Z87: =IF(X87=0,"",(W87)/(X87)) -> 1
B88: Total Other Expenses | C88: =((((C83)+(C84))+(C85))+(C86))+(C87) -> 54943.5 | D88: =((((D83)+(D84))+(D85))+(D86))+(D87) -> 42381.27 | E88: =(C88)-(D88) -> 12562.23 | F88: =IF(D88=0,"",(C88)/(D88)) -> 1.2964099 | G88: =((((G83)+(G84))+(G85))+(G86))+(G87) -> 17.04 | H88: =((((H83)+(H84))+(H85))+(H86))+(H87) -> 0 | I88: =(G88)-(H88) -> 17.04 | J88: =IF(H88=0,"",(G88)/(H88)) | K88: =((((K83)+(K84))+(K85))+(K86))+(K87) -> 0 | L88: =((((L83)+(L84))+(L85))+(L86))+(L87) -> 0 | M88: =(K88)-(L88) -> 0 | N88: =IF(L88=0,"",(K88)/(L88)) | O88: =((((O83)+(O84))+(O85))+(O86))+(O87) -> 0 | P88: =((((P83)+(P84))+(P85))+(P86))+(P87) -> 0 | Q88: =(O88)-(P88) -> 0 | R88: =IF(P88=0,"",(O88)/(P88)) | S88: =((((S83)+(S84))+(S85))+(S86))+(S87) -> 0 | T88: =((((T83)+(T84))+(T85))+(T86))+(T87) -> 0 | U88: =(S88)-(T88) -> 0 | V88: =IF(T88=0,"",(S88)/(T88)) | W88: =((((C88)+(G88))+(K88))+(O88))+(S88) -> 54960.54 | X88: =((((D88)+(H88))+(L88))+(P88))+(T88) -> 42381.27 | Y88: =(W88)-(X88) -> 12579.27 | Z88: =IF(X88=0,"",(W88)/(X88)) -> 1.296812
B89: Net Other Income | C89: =(C81)-(C88) -> -41406.22 | D89: =(D81)-(D88) -> -42381.27 | E89: =(C89)-(D89) -> 975.05 | F89: =IF(D89=0,"",(C89)/(D89)) -> 0.97699337 | G89: =(G81)-(G88) -> -17.04 | H89: =(H81)-(H88) -> 0 | I89: =(G89)-(H89) -> -17.04 | J89: =IF(H89=0,"",(G89)/(H89)) | K89: =(K81)-(K88) -> 0 | L89: =(L81)-(L88) -> 0 | M89: =(K89)-(L89) -> 0 | N89: =IF(L89=0,"",(K89)/(L89)) | O89: =(O81)-(O88) -> 0 | P89: =(P81)-(P88) -> 0 | Q89: =(O89)-(P89) -> 0 | R89: =IF(P89=0,"",(O89)/(P89)) | S89: =(S81)-(S88) -> 0 | T89: =(T81)-(T88) -> 0 | U89: =(S89)-(T89) -> 0 | V89: =IF(T89=0,"",(S89)/(T89)) | W89: =((((C89)+(G89))+(K89))+(O89))+(S89) -> -41423.26 | X89: =((((D89)+(H89))+(L89))+(P89))+(T89) -> -42381.27 | Y89: =(W89)-(X89) -> 958.01 | Z89: =IF(X89=0,"",(W89)/(X89)) -> 0.97739544
B90: Net Income | C90: =(C77)+(C89) -> -126287.9 | D90: =(D77)+(D89) -> -117990.47 | E90: =(C90)-(D90) -> -8297.43 | F90: =IF(D90=0,"",(C90)/(D90)) -> 1.0703229 | G90: =(G77)+(G89) -> 107042.73 | H90: =(H77)+(H89) -> 59235.05 | I90: =(G90)-(H90) -> 47807.68 | J90: =IF(H90=0,"",(G90)/(H90)) -> 1.8070843 | K90: =(K77)+(K89) -> 198.81 | L90: =(L77)+(L89) -> 6104.73 | M90: =(K90)-(L90) -> -5905.92 | N90: =IF(L90=0,"",(K90)/(L90)) -> 0.032566551 | O90: =(O77)+(O89) -> 7312.02 | P90: =(P77)+(P89) -> 50288.66 | Q90: =(O90)-(P90) -> -42976.64 | R90: =IF(P90=0,"",(O90)/(P90)) -> 0.14540097 | S90: =(S77)+(S89) -> -12945.29 | T90: =(T77)+(T89) -> 60499.18 | U90: =(S90)-(T90) -> -73444.47 | V90: =IF(T90=0,"",(S90)/(T90)) -> -0.21397464 | W90: =((((C90)+(G90))+(K90))+(O90))+(S90) -> -24679.63 | X90: =((((D90)+(H90))+(L90))+(P90))+(T90) -> 58137.15 | Y90: =(W90)-(X90) -> -82816.78 | Z90: =IF(X90=0,"",(W90)/(X90)) -> -0.42450705
B92: Net Operating Income + Other Income = EBITDA | C92: =+C77+C81 -> -71344.4 | D92: =+D77+D81 -> -75609.2 | E92: =+E77+E81 -> 4264.8 | F92: =C92/D92 -> 0.94359417 | G92: =+G77+G81 -> 107059.77 | H92: =+H77+H81 -> 59235.05 | I92: =+I77+I81 -> 47824.72 | J92: =G92/H92 -> 1.807372 | K92: =+K77+K81 -> 198.81 | L92: =+L77+L81 -> 6104.73 | M92: =+M77+M81 -> -5905.92 | N92: =K92/L92 -> 0.032566551 | O92: =+O77+O81 -> 7312.02 | P92: =+P77+P81 -> 50288.66 | Q92: =+Q77+Q81 -> -42976.64 | R92: =O92/P92 -> 0.14540097 | S92: =+S77+S81 -> -12945.29 | T92: =+T77+T81 -> 60499.18 | U92: =+U77+U81 -> -73444.47 | V92: =S92/T92 -> -0.21397464 | W92: =+W77+W81 -> 30280.91 | X92: =+X77+X81 -> 100518.42 | Y92: =+Y77+Y81 -> -70237.51 | Z92: =W92/X92 -> 0.30124737
B94: Less: Depreciation & Amortization | C94: =C86+C87 -> 17735.4 | D94: =D86+D87 -> 16610.7 | E94: =E86+E87 -> 1124.7 | F94: =C94/D94 -> 1.0677094 | G94: =G86+G87 -> 0 | H94: =H86+H87 -> 0 | I94: =I86+I87 -> 0 | J94: 0 | K94: =K86+K87 -> 0 | L94: =L86+L87 -> 0 | M94: =M86+M87 -> 0 | N94: 0 | O94: =O86+O87 -> 0 | P94: =P86+P87 -> 0 | Q94: =Q86+Q87 -> 0 | R94: 0 | S94: =S86+S87 -> 0 | T94: =T86+T87 -> 0 | U94: =U86+U87 -> 0 | V94: 0 | W94: =W86+W87 -> 17735.4 | X94: =X86+X87 -> 16610.7 | Y94: =Y86+Y87 -> 1124.7 | Z94: 0
B95: EBIT (Operating Profit) | C95: =++C92-C94 -> -89079.8 | D95: =++D92-D94 -> -92219.9 | E95: =++E92-E94 -> 3140.1 | F95: =C95/D95 -> 0.96594987 | G95: =++G92-G94 -> 107059.77 | H95: =++H92-H94 -> 59235.05 | I95: =++I92-I94 -> 47824.72 | J95: =G95/H95 -> 1.807372 | K95: =++K92-K94 -> 198.81 | L95: =++L92-L94 -> 6104.73 | M95: =++M92-M94 -> -5905.92 | N95: =K95/L95 -> 0.032566551 | O95: =++O92-O94 -> 7312.02 | P95: =++P92-P94 -> 50288.66 | Q95: =++Q92-Q94 -> -42976.64 | R95: =O95/P95 -> 0.14540097 | S95: =++S92-S94 -> -12945.29 | T95: =++T92-T94 -> 60499.18 | U95: =++U92-U94 -> -73444.47 | V95: =S95/T95 -> -0.21397464 | W95: =++W92-W94 -> 12545.51 | X95: =++X92-X94 -> 83907.72 | Y95: =++Y92-Y94 -> -71362.21 | Z95: =W95/X95 -> 0.14951556
B97: Less: Interest Expense + Late Fees | C97: =++C84+C85+C83 -> 37208.1 | D97: =++D84+D85+D83 -> 25770.57 | E97: =++E84+E85+E83 -> 11437.53 | F97: =C97/D97 -> 1.4438214 | G97: =++G84+G85+G83 -> 17.04 | H97: =++H84+H85+H83 -> 0 | I97: =++I84+I85+I83 -> 17.04 | J97: 0 | K97: =++K84+K85+K83 -> 0 | L97: =++L84+L85+L83 -> 0 | M97: =++M84+M85+M83 -> 0 | N97: 0 | O97: =++O84+O85+O83 -> 0 | P97: =++P84+P85+P83 -> 0 | Q97: =++Q84+Q85+Q83 -> 0 | R97: 0 | S97: =++S84+S85+S83 -> 0 | T97: =++T84+T85+T83 -> 0 | U97: =++U84+U85+U83 -> 0 | V97: 0 | W97: =++W84+W85+W83 -> 37225.14 | X97: =++X84+X85+X83 -> 25770.57 | Y97: =++Y84+Y85+Y83 -> 11454.57 | Z97: 0
B98: Profit Before Tax (PBT) | C98: =++C95-C97 -> -126287.9 | D98: =++D95-D97 -> -117990.47 | E98: =++E95-E97 -> -8297.43 | F98: =C98/D98 -> 1.0703229 | G98: =++G95-G97 -> 107042.73 | H98: =++H95-H97 -> 59235.05 | I98: =++I95-I97 -> 47807.68 | J98: =G98/H98 -> 1.8070843 | K98: =++K95-K97 -> 198.81 | L98: =++L95-L97 -> 6104.73 | M98: =++M95-M97 -> -5905.92 | N98: =K98/L98 -> 0.032566551 | O98: =++O95-O97 -> 7312.02 | P98: =++P95-P97 -> 50288.66 | Q98: =++Q95-Q97 -> -42976.64 | R98: =O98/P98 -> 0.14540097 | S98: =++S95-S97 -> -12945.29 | T98: =++T95-T97 -> 60499.18 | U98: =++U95-U97 -> -73444.47 | V98: =S98/T98 -> -0.21397464 | W98: =++W95-W97 -> -24679.63 | X98: =++X95-X97 -> 58137.15 | Y98: =++Y95-Y97 -> -82816.78 | Z98: =W98/X98 -> -0.42450705
B100: Less: Tax
B101: Profit After Tax (PAT) | C101: =++C98-C100 -> -126287.9 | D101: =++D98-D100 -> -117990.47 | E101: =++E98-E100 -> -8297.43 | F101: =C101/D101 -> 1.0703229 | G101: =++G98-G100 -> 107042.73 | H101: =++H98-H100 -> 59235.05 | I101: =++I98-I100 -> 47807.68 | J101: =G101/H101 -> 1.8070843 | K101: =++K98-K100 -> 198.81 | L101: =++L98-L100 -> 6104.73 | M101: =++M98-M100 -> -5905.92 | N101: =K101/L101 -> 0.032566551 | O101: =++O98-O100 -> 7312.02 | P101: =++P98-P100 -> 50288.66 | Q101: =++Q98-Q100 -> -42976.64 | R101: =O101/P101 -> 0.14540097 | S101: =++S98-S100 -> -12945.29 | T101: =++T98-T100 -> 60499.18 | U101: =++U98-U100 -> -73444.47 | V101: =S101/T101 -> -0.21397464 | W101: =++W98-W100 -> -24679.63 | X101: =++X98-X100 -> 58137.15 | Y101: =++Y98-Y100 -> -82816.78 | Z101: =W101/X101 -> -0.42450705
B104: Check Point | C104: =++C101-C90 -> 0 | D104: =++D101-D90 -> 0 | E104: =++E101-E90 -> 0 | F104: =++F101-F90 -> 0 | G104: =++G101-G90 -> 0 | H104: =++H101-H90 -> 0 | I104: =++I101-I90 -> 0 | J104: =IFERROR((++J101-J90),0) -> 0 | K104: =++K101-K90 -> 0 | L104: =++L101-L90 -> 0 | M104: =++M101-M90 -> 0 | N104: =IFERROR((++N101-N90),0) -> 0 | O104: =++O101-O90 -> 0 | P104: =++P101-P90 -> 0 | Q104: =++Q101-Q90 -> 0 | R104: =IFERROR((++R101-R90),0) -> 0 | S104: =++S101-S90 -> 0 | T104: =++T101-T90 -> 0 | U104: =++U101-U90 -> 0 | V104: =IFERROR((++V101-V90),0) -> 0 | W104: =++W101-W90 -> 0 | X104: =++X101-X90 -> 0 | Y104: =++Y101-Y90 -> 0 | Z104: =++Z101-Z90 -> 0

Sheet Profit and Loss - Division(YTD)
B2: =Cover!A3 -> Pacific Nexus | P2: Home
B3: Profit and Loss by Division | P3: Balance Sheet
B4: =Index!A2 -> Period Ending 03/31/2026 | P4: Profit & Loss
P5: PL-Division (Month)
C8: Admin & Overhead Cost - YTD | G8: NS Printing - YTD | K8: PN Agency - YTD | O8: PN Photography - YTD | S8: PN Printing - YTD | W8: YTD
C9: Actual | D9: Budget | E9: Variance | F9: % of Budget | G9: Actual | H9: Budget | I9: Variance | J9: % of Budget | K9: Actual | L9: Budget | M9: Variance | N9: % of Budget | O9: Actual | P9: Budget | Q9: Variance | R9: % of Budget | S9: Actual | T9: Budget | U9: Variance | V9: % of Budget | W9: Actual | X9: Budget | Y9: Variance | Z9: % of Budget
B10: Income
B11: 4005 Sales Revenue | E11: =(C11)-(D11) -> 0 | F11: =IF(D11=0,"",(C11)/(D11)) | G11: =341703.51 -> 341703.51 | H11: =300000 -> 300000 | I11: =(G11)-(H11) -> 41703.51 | J11: =IF(H11=0,"",(G11)/(H11)) -> 1.1390117 | K11: =1189.19 -> 1189.19 | L11: =24999.99 -> 24999.99 | M11: =(K11)-(L11) -> -23810.8 | N11: =IF(L11=0,"",(K11)/(L11)) -> 0.047567619 | O11: =187005.08 -> 187005.08 | P11: =312500.01 -> 312500.01 | Q11: =(O11)-(P11) -> -125494.93 | R11: =IF(P11=0,"",(O11)/(P11)) -> 0.59841624 | S11: =187864.37 -> 187864.37 | T11: =399999.99 -> 399999.99 | U11: =(S11)-(T11) -> -212135.62 | V11: =IF(T11=0,"",(S11)/(T11)) -> 0.46966094 | W11: =((((C11)+(G11))+(K11))+(O11))+(S11) -> 717762.15 | X11: =((((D11)+(H11))+(L11))+(P11))+(T11) -> 1037500 | Y11: =(W11)-(X11) -> -319737.84 | Z11: =IF(X11=0,"",(W11)/(X11)) -> 0.69181895
B12: 4010 Sales Discount | E12: =(C12)-(D12) -> 0 | F12: =IF(D12=0,"",(C12)/(D12)) | I12: =(G12)-(H12) -> 0 | J12: =IF(H12=0,"",(G12)/(H12)) | M12: =(K12)-(L12) -> 0 | N12: =IF(L12=0,"",(K12)/(L12)) | Q12: =(O12)-(P12) -> 0 | R12: =IF(P12=0,"",(O12)/(P12)) | S12: =-3363.73 -> -3363.73 | U12: =(S12)-(T12) -> -3363.73 | V12: =IF(T12=0,"",(S12)/(T12)) | W12: =((((C12)+(G12))+(K12))+(O12))+(S12) -> -3363.73 | X12: =((((D12)+(H12))+(L12))+(P12))+(T12) -> 0 | Y12: =(W12)-(X12) -> -3363.73 | Z12: =IF(X12=0,"",(W12)/(X12))
B13: Total Income | C13: =(C11)+(C12) -> 0 | D13: =(D11)+(D12) -> 0 | E13: =(C13)-(D13) -> 0 | F13: =IF(D13=0,"",(C13)/(D13)) | G13: =(G11)+(G12) -> 341703.51 | H13: =(H11)+(H12) -> 300000 | I13: =(G13)-(H13) -> 41703.51 | J13: =IF(H13=0,"",(G13)/(H13)) -> 1.1390117 | K13: =(K11)+(K12) -> 1189.19 | L13: =(L11)+(L12) -> 24999.99 | M13: =(K13)-(L13) -> -23810.8 | N13: =IF(L13=0,"",(K13)/(L13)) -> 0.047567619 | O13: =(O11)+(O12) -> 187005.08 | P13: =(P11)+(P12) -> 312500.01 | Q13: =(O13)-(P13) -> -125494.93 | R13: =IF(P13=0,"",(O13)/(P13)) -> 0.59841624 | S13: =(S11)+(S12) -> 184500.64 | T13: =(T11)+(T12) -> 399999.99 | U13: =(S13)-(T13) -> -215499.35 | V13: =IF(T13=0,"",(S13)/(T13)) -> 0.46125161 | W13: =((((C13)+(G13))+(K13))+(O13))+(S13) -> 714398.42 | X13: =((((D13)+(H13))+(L13))+(P13))+(T13) -> 1037500 | Y13: =(W13)-(X13) -> -323101.57 | Z13: =IF(X13=0,"",(W13)/(X13)) -> 0.6885768
B14: Cost of Goods Sold
B15: 5005 Cost of Materials | C15: =293.54 -> 293.54 | E15: =(C15)-(D15) -> 293.54 | F15: =IF(D15=0,"",(C15)/(D15)) | G15: =27679.2 -> 27679.2 | H15: =39000 -> 39000 | I15: =(G15)-(H15) -> -11320.8 | J15: =IF(H15=0,"",(G15)/(H15)) -> 0.70972308 | L15: =3249.99 -> 3249.99 | M15: =(K15)-(L15) -> -3249.99 | N15: =IF(L15=0,"",(K15)/(L15)) -> 0 | O15: =9458.81 -> 9458.81 | P15: =40625.01 -> 40625.01 | Q15: =(O15)-(P15) -> -31166.2 | R15: =IF(P15=0,"",(O15)/(P15)) -> 0.23283219 | S15: =49909.42 -> 49909.42 | T15: =51999.99 -> 51999.99 | U15: =(S15)-(T15) -> -2090.57 | V15: =IF(T15=0,"",(S15)/(T15)) -> 0.95979672 | W15: =((((C15)+(G15))+(K15))+(O15))+(S15) -> 87340.97 | X15: =((((D15)+(H15))+(L15))+(P15))+(T15) -> 134874.99 | Y15: =(W15)-(X15) -> -47534.02 | Z15: =IF(X15=0,"",(W15)/(X15)) -> 0.6475698
B16: 5015 Travels and Meals | E16: =(C16)-(D16) -> 0 | F16: =IF(D16=0,"",(C16)/(D16)) | I16: =(G16)-(H16) -> 0 | J16: =IF(H16=0,"",(G16)/(H16)) | M16: =(K16)-(L16) -> 0 | N16: =IF(L16=0,"",(K16)/(L16)) | O16: 0 | Q16: =(O16)-(P16) -> 0 | R16: =IF(P16=0,"",(O16)/(P16)) | U16: =(S16)-(T16) -> 0 | V16: =IF(T16=0,"",(S16)/(T16)) | W16: =((((C16)+(G16))+(K16))+(O16))+(S16) -> 0 | X16: =((((D16)+(H16))+(L16))+(P16))+(T16) -> 0 | Y16: =(W16)-(X16) -> 0 | Z16: =IF(X16=0,"",(W16)/(X16))
B17: 5065 Wages | E17: =(C17)-(D17) -> 0 | F17: =IF(D17=0,"",(C17)/(D17)) | G17: =44070.92 -> 44070.92 | H17: =3419.61 -> 3419.61 | I17: =(G17)-(H17) -> 40651.31 | J17: =IF(H17=0,"",(G17)/(H17)) -> 12.887704 | K17: =0 -> 0 | M17: =(K17)-(L17) -> 0 | N17: =IF(L17=0,"",(K17)/(L17)) | O17: =72626.48 -> 72626.48 | P17: =85406.07 -> 85406.07 | Q17: =(O17)-(P17) -> -12779.59 | R17: =IF(P17=0,"",(O17)/(P17)) -> 0.85036672 | S17: =157318.03 -> 157318.03 | T17: =140571.06 -> 140571.06 | U17: =(S17)-(T17) -> 16746.97 | V17: =IF(T17=0,"",(S17)/(T17)) -> 1.1191353 | W17: =((((C17)+(G17))+(K17))+(O17))+(S17) -> 274015.43 | X17: =((((D17)+(H17))+(L17))+(P17))+(T17) -> 229396.74 | Y17: =(W17)-(X17) -> 44618.69 | Z17: =IF(X17=0,"",(W17)/(X17)) -> 1.1945045
B18: 5070 Payroll Tax Expense | E18: =(C18)-(D18) -> 0 | F18: =IF(D18=0,"",(C18)/(D18)) | G18: =4316.76 -> 4316.76 | H18: =273.57 -> 273.57 | I18: =(G18)-(H18) -> 4043.19 | J18: =IF(H18=0,"",(G18)/(H18)) -> 15.779362 | K18: =0 -> 0 | M18: =(K18)-(L18) -> 0 | N18: =IF(L18=0,"",(K18)/(L18)) | O18: =6218.69 -> 6218.69 | P18: =6832.5 -> 6832.5 | Q18: =(O18)-(P18) -> -613.81 | R18: =IF(P18=0,"",(O18)/(P18)) -> 0.91016319 | S18: =14733.18 -> 14733.18 | T18: =11245.68 -> 11245.68 | U18: =(S18)-(T18) -> 3487.5 | V18: =IF(T18=0,"",(S18)/(T18)) -> 1.3101191 | W18: =((((C18)+(G18))+(K18))+(O18))+(S18) -> 25268.63 | X18: =((((D18)+(H18))+(L18))+(P18))+(T18) -> 18351.75 | Y18: =(W18)-(X18) -> 6916.88 | Z18: =IF(X18=0,"",(W18)/(X18)) -> 1.3769057
B19: 5075 Employee Benefits | E19: =(C19)-(D19) -> 0 | F19: =IF(D19=0,"",(C19)/(D19)) | G19: =1920.46 -> 1920.46 | I19: =(G19)-(H19) -> 1920.46 | J19: =IF(H19=0,"",(G19)/(H19)) | K19: =0 -> 0 | M19: =(K19)-(L19) -> 0 | N19: =IF(L19=0,"",(K19)/(L19)) | O19: =1790.13 -> 1790.13 | P19: =3467.94 -> 3467.94 | Q19: =(O19)-(P19) -> -1677.81 | R19: =IF(P19=0,"",(O19)/(P19)) -> 0.51619405 | S19: =8347.3 -> 8347.3 | T19: =5707.92 -> 5707.92 | U19: =(S19)-(T19) -> 2639.38 | V19: =IF(T19=0,"",(S19)/(T19)) -> 1.4624066 | W19: =((((C19)+(G19))+(K19))+(O19))+(S19) -> 12057.89 | X19: =((((D19)+(H19))+(L19))+(P19))+(T19) -> 9175.86 | Y19: =(W19)-(X19) -> 2882.03 | Z19: =IF(X19=0,"",(W19)/(X19)) -> 1.3140883
B20: Total Cost of Goods Sold | C20: =((((C15)+(C16))+(C17))+(C18))+(C19) -> 293.54 | D20: =((((D15)+(D16))+(D17))+(D18))+(D19) -> 0 | E20: =(C20)-(D20) -> 293.54 | F20: =IF(D20=0,"",(C20)/(D20)) | G20: =((((G15)+(G16))+(G17))+(G18))+(G19) -> 77987.34 | H20: =((((H15)+(H16))+(H17))+(H18))+(H19) -> 42693.18 | I20: =(G20)-(H20) -> 35294.16 | J20: =IF(H20=0,"",(G20)/(H20)) -> 1.8266932 | K20: =((((K15)+(K16))+(K17))+(K18))+(K19) -> 0 | L20: =((((L15)+(L16))+(L17))+(L18))+(L19) -> 3249.99 | M20: =(K20)-(L20) -> -3249.99 | N20: =IF(L20=0,"",(K20)/(L20)) -> 0 | O20: =((((O15)+(O16))+(O17))+(O18))+(O19) -> 90094.11 | P20: =((((P15)+(P16))+(P17))+(P18))+(P19) -> 136331.52 | Q20: =(O20)-(P20) -> -46237.41 | R20: =IF(P20=0,"",(O20)/(P20)) -> 0.66084578 | S20: =((((S15)+(S16))+(S17))+(S18))+(S19) -> 230307.93 | T20: =((((T15)+(T16))+(T17))+(T18))+(T19) -> 209524.65 | U20: =(S20)-(T20) -> 20783.28 | V20: =IF(T20=0,"",(S20)/(T20)) -> 1.0991925 | W20: =((((C20)+(G20))+(K20))+(O20))+(S20) -> 398682.92 | X20: =((((D20)+(H20))+(L20))+(P20))+(T20) -> 391799.34 | Y20: =(W20)-(X20) -> 6883.58 | Z20: =IF(X20=0,"",(W20)/(X20)) -> 1.0175691
B21: Gross Profit | C21: =(C13)-(C20) -> -293.54 | D21: =(D13)-(D20) -> 0 | E21: =(C21)-(D21) -> -293.54 | F21: =IF(D21=0,"",(C21)/(D21)) | G21: =(G13)-(G20) -> 263716.17 | H21: =(H13)-(H20) -> 257306.82 | I21: =(G21)-(H21) -> 6409.35 | J21: =IF(H21=0,"",(G21)/(H21)) -> 1.0249094 | K21: =(K13)-(K20) -> 1189.19 | L21: =(L13)-(L20) -> 21750 | M21: =(K21)-(L21) -> -20560.81 | N21: =IF(L21=0,"",(K21)/(L21)) -> 0.054675402 | O21: =(O13)-(O20) -> 96910.97 | P21: =(P13)-(P20) -> 176168.49 | Q21: =(O21)-(P21) -> -79257.52 | R21: =IF(P21=0,"",(O21)/(P21)) -> 0.55010388 | S21: =(S13)-(S20) -> -45807.29 | T21: =(T13)-(T20) -> 190475.34 | U21: =(S21)-(T21) -> -236282.63 | V21: =IF(T21=0,"",(S21)/(T21)) -> -0.24048935 | W21: =((((C21)+(G21))+(K21))+(O21))+(S21) -> 315715.5 | X21: =((((D21)+(H21))+(L21))+(P21))+(T21) -> 645700.65 | Y21: =(W21)-(X21) -> -329985.15 | Z21: =IF(X21=0,"",(W21)/(X21)) -> 0.48895026
B22: Expenses
B23: 6100 Payroll Expenses | E23: =(C23)-(D23) -> 0 | F23: =IF(D23=0,"",(C23)/(D23)) | I23: =(G23)-(H23) -> 0 | J23: =IF(H23=0,"",(G23)/(H23)) | M23: =(K23)-(L23) -> 0 | N23: =IF(L23=0,"",(K23)/(L23)) | Q23: =(O23)-(P23) -> 0 | R23: =IF(P23=0,"",(O23)/(P23)) | U23: =(S23)-(T23) -> 0 | V23: =IF(T23=0,"",(S23)/(T23)) | W23: =((((C23)+(G23))+(K23))+(O23))+(S23) -> 0 | X23: =((((D23)+(H23))+(L23))+(P23))+(T23) -> 0 | Y23: =(W23)-(X23) -> 0 | Z23: =IF(X23=0,"",(W23)/(X23))
B24: 6105 Salaries & Wages | C24: =-439.18 -> -439.18 | D24: =0 -> 0 | E24: =(C24)-(D24) -> -439.18 | F24: =IF(D24=0,"",(C24)/(D24)) | G24: =42626.32 -> 42626.32 | H24: =41538.54 -> 41538.54 | I24: =(G24)-(H24) -> 1087.78 | J24: =IF(H24=0,"",(G24)/(H24)) -> 1.0261872 | K24: =3956.06 -> 3956.06 | L24: =2967.03 -> 2967.03 | M24: =(K24)-(L24) -> 989.03 | N24: =IF(L24=0,"",(K24)/(L24)) -> 1.3333401 | O24: =18193.08 -> 18193.08 | P24: =17802.24 -> 17802.24 | Q24: =(O24)-(P24) -> 390.84 | R24: =IF(P24=0,"",(O24)/(P24)) -> 1.0219545 | S24: =200 -> 200 | T24: =2571.51 -> 2571.51 | U24: =(S24)-(T24) -> -2371.51 | V24: =IF(T24=0,"",(S24)/(T24)) -> 0.077775315 | W24: =((((C24)+(G24))+(K24))+(O24))+(S24) -> 64536.28 | X24: =((((D24)+(H24))+(L24))+(P24))+(T24) -> 64879.32 | Y24: =(W24)-(X24) -> -343.04 | Z24: =IF(X24=0,"",(W24)/(X24)) -> 0.99471264
B25: 6115 Payroll Tax Expense | C25: =71.32 -> 71.32 | D25: =0 -> 0 | E25: =(C25)-(D25) -> 71.32 | F25: =IF(D25=0,"",(C25)/(D25)) | G25: =3381.06 -> 3381.06 | H25: =3323.1 -> 3323.1 | I25: =(G25)-(H25) -> 57.96 | J25: =IF(H25=0,"",(G25)/(H25)) -> 1.0174415 | K25: =608.1 -> 608.1 | L25: =237.36 -> 237.36 | M25: =(K25)-(L25) -> 370.74 | N25: =IF(L25=0,"",(K25)/(L25)) -> 2.5619312 | O25: =1863.72 -> 1863.72 | P25: =1424.19 -> 1424.19 | Q25: =(O25)-(P25) -> 439.53 | R25: =IF(P25=0,"",(O25)/(P25)) -> 1.3086175 | S25: =1332.96 -> 1332.96 | T25: =205.71 -> 205.71 | U25: =(S25)-(T25) -> 1127.25 | V25: =IF(T25=0,"",(S25)/(T25)) -> 6.4798017 | W25: =((((C25)+(G25))+(K25))+(O25))+(S25) -> 7257.16 | X25: =((((D25)+(H25))+(L25))+(P25))+(T25) -> 5190.36 | Y25: =(W25)-(X25) -> 2066.8 | Z25: =IF(X25=0,"",(W25)/(X25)) -> 1.3981997
B26: 6120 Employee Benefits | C26: =-15.37 -> -15.37 | D26: =0 -> 0 | E26: =(C26)-(D26) -> -15.37 | F26: =IF(D26=0,"",(C26)/(D26)) | G26: =1660.72 -> 1660.72 | H26: =1661.55 -> 1661.55 | I26: =(G26)-(H26) -> -0.83 | J26: =IF(H26=0,"",(G26)/(H26)) -> 0.99950047 | K26: =157.46 -> 157.46 | L26: =118.68 -> 118.68 | M26: =(K26)-(L26) -> 38.78 | N26: =IF(L26=0,"",(K26)/(L26)) -> 1.326761 | O26: =663.89 -> 663.89 | P26: =712.08 -> 712.08 | Q26: =(O26)-(P26) -> -48.19 | R26: =IF(P26=0,"",(O26)/(P26)) -> 0.93232502 | S26: =0 -> 0 | T26: =102.87 -> 102.87 | U26: =(S26)-(T26) -> -102.87 | V26: =IF(T26=0,"",(S26)/(T26)) -> 0 | W26: =((((C26)+(G26))+(K26))+(O26))+(S26) -> 2466.7 | X26: =((((D26)+(H26))+(L26))+(P26))+(T26) -> 2595.18 | Y26: =(W26)-(X26) -> -128.48 | Z26: =IF(X26=0,"",(W26)/(X26)) -> 0.95049284
B27: 6125 Employee Bonus | D27: =0 -> 0 | E27: =(C27)-(D27) -> 0 | F27: =IF(D27=0,"",(C27)/(D27)) | H27: =1578.48 -> 1578.48 | I27: =(G27)-(H27) -> -1578.48 | J27: =IF(H27=0,"",(G27)/(H27)) -> 0 | L27: =112.74 -> 112.74 | M27: =(K27)-(L27) -> -112.74 | N27: =IF(L27=0,"",(K27)/(L27)) -> 0 | P27: =676.5 -> 676.5 | Q27: =(O27)-(P27) -> -676.5 | R27: =IF(P27=0,"",(O27)/(P27)) -> 0 | T27: =97.71 -> 97.71 | U27: =(S27)-(T27) -> -97.71 | V27: =IF(T27=0,"",(S27)/(T27)) -> 0 | W27: =((((C27)+(G27))+(K27))+(O27))+(S27) -> 0 | X27: =((((D27)+(H27))+(L27))+(P27))+(T27) -> 2465.43 | Y27: =(W27)-(X27) -> -2465.43 | Z27: =IF(X27=0,"",(W27)/(X27)) -> 0
B28: Total 6100 Payroll Expenses | C28: =((((C23)+(C24))+(C25))+(C26))+(C27) -> -383.23 | D28: =((((D23)+(D24))+(D25))+(D26))+(D27) -> 0 | E28: =(C28)-(D28) -> -383.23 | F28: =IF(D28=0,"",(C28)/(D28)) | G28: =((((G23)+(G24))+(G25))+(G26))+(G27) -> 47668.1 | H28: =((((H23)+(H24))+(H25))+(H26))+(H27) -> 48101.67 | I28: =(G28)-(H28) -> -433.57 | J28: =IF(H28=0,"",(G28)/(H28)) -> 0.99098638 | K28: =((((K23)+(K24))+(K25))+(K26))+(K27) -> 4721.62 | L28: =((((L23)+(L24))+(L25))+(L26))+(L27) -> 3435.81 | M28: =(K28)-(L28) -> 1285.81 | N28: =IF(L28=0,"",(K28)/(L28)) -> 1.3742378 | O28: =((((O23)+(O24))+(O25))+(O26))+(O27) -> 20720.69 | P28: =((((P23)+(P24))+(P25))+(P26))+(P27) -> 20615.01 | Q28: =(O28)-(P28) -> 105.68 | R28: =IF(P28=0,"",(O28)/(P28)) -> 1.0051264 | S28: =((((S23)+(S24))+(S25))+(S26))+(S27) -> 1532.96 | T28: =((((T23)+(T24))+(T25))+(T26))+(T27) -> 2977.8 | U28: =(S28)-(T28) -> -1444.84 | V28: =IF(T28=0,"",(S28)/(T28)) -> 0.51479616 | W28: =((((C28)+(G28))+(K28))+(O28))+(S28) -> 74260.14 | X28: =((((D28)+(H28))+(L28))+(P28))+(T28) -> 75130.29 | Y28: =(W28)-(X28) -> -870.15 | Z28: =IF(X28=0,"",(W28)/(X28)) -> 0.98841812
B29: 6130 Staff Training & Development | C29: =3132.67 -> 3132.67 | D29: =300 -> 300 | E29: =(C29)-(D29) -> 2832.67 | F29: =IF(D29=0,"",(C29)/(D29)) -> 10.442233 | I29: =(G29)-(H29) -> 0 | J29: =IF(H29=0,"",(G29)/(H29)) | M29: =(K29)-(L29) -> 0 | N29: =IF(L29=0,"",(K29)/(L29)) | Q29: =(O29)-(P29) -> 0 | R29: =IF(P29=0,"",(O29)/(P29)) | U29: =(S29)-(T29) -> 0 | V29: =IF(T29=0,"",(S29)/(T29)) | W29: =((((C29)+(G29))+(K29))+(O29))+(S29) -> 3132.67 | X29: =((((D29)+(H29))+(L29))+(P29))+(T29) -> 300 | Y29: =(W29)-(X29) -> 2832.67 | Z29: =IF(X29=0,"",(W29)/(X29)) -> 10.442233
B30: 6135 Payroll Processing Fees | C30: =2758.4 -> 2758.4 | D30: =2490.42 -> 2490.42 | E30: =(C30)-(D30) -> 267.98 | F30: =IF(D30=0,"",(C30)/(D30)) -> 1.1076043 | I30: =(G30)-(H30) -> 0 | J30: =IF(H30=0,"",(G30)/(H30)) | M30: =(K30)-(L30) -> 0 | N30: =IF(L30=0,"",(K30)/(L30)) | Q30: =(O30)-(P30) -> 0 | R30: =IF(P30=0,"",(O30)/(P30)) | U30: =(S30)-(T30) -> 0 | V30: =IF(T30=0,"",(S30)/(T30)) | W30: =((((C30)+(G30))+(K30))+(O30))+(S30) -> 2758.4 | X30: =((((D30)+(H30))+(L30))+(P30))+(T30) -> 2490.42 | Y30: =(W30)-(X30) -> 267.98 | Z30: =IF(X30=0,"",(W30)/(X30)) -> 1.1076043
B31: 6150 Employee Reimbursements | C31: =0 -> 0 | D31: =4941.66 -> 4941.66 | E31: =(C31)-(D31) -> -4941.66 | F31: =IF(D31=0,"",(C31)/(D31)) -> 0 | G31: =607.1 -> 607.1 | I31: =(G31)-(H31) -> 607.1 | J31: =IF(H31=0,"",(G31)/(H31)) | K31: =11.03 -> 11.03 | M31: =(K31)-(L31) -> 11.03 | N31: =IF(L31=0,"",(K31)/(L31)) | O31: =65.56 -> 65.56 | Q31: =(O31)-(P31) -> 65.56 | R31: =IF(P31=0,"",(O31)/(P31)) | S31: =147.61 -> 147.61 | U31: =(S31)-(T31) -> 147.61 | V31: =IF(T31=0,"",(S31)/(T31)) | W31: =((((C31)+(G31))+(K31))+(O31))+(S31) -> 831.3 | X31: =((((D31)+(H31))+(L31))+(P31))+(T31) -> 4941.66 | Y31: =(W31)-(X31) -> -4110.36 | Z31: =IF(X31=0,"",(W31)/(X31)) -> 0.16822282
B32: 6155 Employee Gift | C32: =206 -> 206 | D32: =750 -> 750 | E32: =(C32)-(D32) -> -544 | F32: =IF(D32=0,"",(C32)/(D32)) -> 0.27466667 | I32: =(G32)-(H32) -> 0 | J32: =IF(H32=0,"",(G32)/(H32)) | M32: =(K32)-(L32) -> 0 | N32: =IF(L32=0,"",(K32)/(L32)) | Q32: =(O32)-(P32) -> 0 | R32: =IF(P32=0,"",(O32)/(P32)) | U32: =(S32)-(T32) -> 0 | V32: =IF(T32=0,"",(S32)/(T32)) | W32: =((((C32)+(G32))+(K32))+(O32))+(S32) -> 206 | X32: =((((D32)+(H32))+(L32))+(P32))+(T32) -> 750 | Y32: =(W32)-(X32) -> -544 | Z32: =IF(X32=0,"",(W32)/(X32)) -> 0.27466667
B33: 6200 Professional Fees | E33: =(C33)-(D33) -> 0 | F33: =IF(D33=0,"",(C33)/(D33)) | I33: =(G33)-(H33) -> 0 | J33: =IF(H33=0,"",(G33)/(H33)) | M33: =(K33)-(L33) -> 0 | N33: =IF(L33=0,"",(K33)/(L33)) | Q33: =(O33)-(P33) -> 0 | R33: =IF(P33=0,"",(O33)/(P33)) | U33: =(S33)-(T33) -> 0 | V33: =IF(T33=0,"",(S33)/(T33)) | W33: =((((C33)+(G33))+(K33))+(O33))+(S33) -> 0 | X33: =((((D33)+(H33))+(L33))+(P33))+(T33) -> 0 | Y33: =(W33)-(X33) -> 0 | Z33: =IF(X33=0,"",(W33)/(X33))
B34: 6205 Legal Fees | C34: =6338.82 -> 6338.82 | E34: =(C34)-(D34) -> 6338.82 | F34: =IF(D34=0,"",(C34)/(D34)) | I34: =(G34)-(H34) -> 0 | J34: =IF(H34=0,"",(G34)/(H34)) | M34: =(K34)-(L34) -> 0 | N34: =IF(L34=0,"",(K34)/(L34)) | Q34: =(O34)-(P34) -> 0 | R34: =IF(P34=0,"",(O34)/(P34)) | U34: =(S34)-(T34) -> 0 | V34: =IF(T34=0,"",(S34)/(T34)) | W34: =((((C34)+(G34))+(K34))+(O34))+(S34) -> 6338.82 | X34: =((((D34)+(H34))+(L34))+(P34))+(T34) -> 0 | Y34: =(W34)-(X34) -> 6338.82 | Z34: =IF(X34=0,"",(W34)/(X34))
B35: 6210 IT Fees | C35: =7200 -> 7200 | D35: =7200 -> 7200 | E35: =(C35)-(D35) -> 0 | F35: =IF(D35=0,"",(C35)/(D35)) -> 1 | I35: =(G35)-(H35) -> 0 | J35: =IF(H35=0,"",(G35)/(H35)) | M35: =(K35)-(L35) -> 0 | N35: =IF(L35=0,"",(K35)/(L35)) | Q35: =(O35)-(P35) -> 0 | R35: =IF(P35=0,"",(O35)/(P35)) | U35: =(S35)-(T35) -> 0 | V35: =IF(T35=0,"",(S35)/(T35)) | W35: =((((C35)+(G35))+(K35))+(O35))+(S35) -> 7200 | X35: =((((D35)+(H35))+(L35))+(P35))+(T35) -> 7200 | Y35: =(W35)-(X35) -> 0 | Z35: =IF(X35=0,"",(W35)/(X35)) -> 1
B36: 6215 Accounting Fees | C36: =3093 -> 3093 | D36: =3000 -> 3000 | E36: =(C36)-(D36) -> 93 | F36: =IF(D36=0,"",(C36)/(D36)) -> 1.031 | I36: =(G36)-(H36) -> 0 | J36: =IF(H36=0,"",(G36)/(H36)) | M36: =(K36)-(L36) -> 0 | N36: =IF(L36=0,"",(K36)/(L36)) | Q36: =(O36)-(P36) -> 0 | R36: =IF(P36=0,"",(O36)/(P36)) | U36: =(S36)-(T36) -> 0 | V36: =IF(T36=0,"",(S36)/(T36)) | W36: =((((C36)+(G36))+(K36))+(O36))+(S36) -> 3093 | X36: =((((D36)+(H36))+(L36))+(P36))+(T36) -> 3000 | Y36: =(W36)-(X36) -> 93 | Z36: =IF(X36=0,"",(W36)/(X36)) -> 1.031
B37: 6220 Professional and Consulting Fees | C37: =10639.99 -> 10639.99 | D37: =7500 -> 7500 | E37: =(C37)-(D37) -> 3139.99 | F37: =IF(D37=0,"",(C37)/(D37)) -> 1.4186653 | I37: =(G37)-(H37) -> 0 | J37: =IF(H37=0,"",(G37)/(H37)) | M37: =(K37)-(L37) -> 0 | N37: =IF(L37=0,"",(K37)/(L37)) | O37: =1500 -> 1500 | Q37: =(O37)-(P37) -> 1500 | R37: =IF(P37=0,"",(O37)/(P37)) | S37: =410 -> 410 | U37: =(S37)-(T37) -> 410 | V37: =IF(T37=0,"",(S37)/(T37)) | W37: =((((C37)+(G37))+(K37))+(O37))+(S37) -> 12549.99 | X37: =((((D37)+(H37))+(L37))+(P37))+(T37) -> 7500 | Y37: =(W37)-(X37) -> 5049.99 | Z37: =IF(X37=0,"",(W37)/(X37)) -> 1.673332
B38: Total 6200 Professional Fees | C38: =((((C33)+(C34))+(C35))+(C36))+(C37) -> 27271.81 | D38: =((((D33)+(D34))+(D35))+(D36))+(D37) -> 17700 | E38: =(C38)-(D38) -> 9571.81 | F38: =IF(D38=0,"",(C38)/(D38)) -> 1.5407802 | G38: =((((G33)+(G34))+(G35))+(G36))+(G37) -> 0 | H38: =((((H33)+(H34))+(H35))+(H36))+(H37) -> 0 | I38: =(G38)-(H38) -> 0 | J38: =IF(H38=0,"",(G38)/(H38)) | K38: =((((K33)+(K34))+(K35))+(K36))+(K37) -> 0 | L38: =((((L33)+(L34))+(L35))+(L36))+(L37) -> 0 | M38: =(K38)-(L38) -> 0 | N38: =IF(L38=0,"",(K38)/(L38)) | O38: =((((O33)+(O34))+(O35))+(O36))+(O37) -> 1500 | P38: =((((P33)+(P34))+(P35))+(P36))+(P37) -> 0 | Q38: =(O38)-(P38) -> 1500 | R38: =IF(P38=0,"",(O38)/(P38)) | S38: =((((S33)+(S34))+(S35))+(S36))+(S37) -> 410 | T38: =((((T33)+(T34))+(T35))+(T36))+(T37) -> 0 | U38: =(S38)-(T38) -> 410 | V38: =IF(T38=0,"",(S38)/(T38)) | W38: =((((C38)+(G38))+(K38))+(O38))+(S38) -> 29181.81 | X38: =((((D38)+(H38))+(L38))+(P38))+(T38) -> 17700 | Y38: =(W38)-(X38) -> 11481.81 | Z38: =IF(X38=0,"",(W38)/(X38)) -> 1.6486898
B39: 6300 Shareholder's Compensation | E39: =(C39)-(D39) -> 0 | F39: =IF(D39=0,"",(C39)/(D39)) | I39: =(G39)-(H39) -> 0 | J39: =IF(H39=0,"",(G39)/(H39)) | M39: =(K39)-(L39) -> 0 | N39: =IF(L39=0,"",(K39)/(L39)) | Q39: =(O39)-(P39) -> 0 | R39: =IF(P39=0,"",(O39)/(P39)) | U39: =(S39)-(T39) -> 0 | V39: =IF(T39=0,"",(S39)/(T39)) | W39: =((((C39)+(G39))+(K39))+(O39))+(S39) -> 0 | X39: =((((D39)+(H39))+(L39))+(P39))+(T39) -> 0 | Y39: =(W39)-(X39) -> 0 | Z39: =IF(X39=0,"",(W39)/(X39))
B40: 6305 Shareholder's Wages & Salaries | C40: =33571.43 -> 33571.43 | D40: =30000 -> 30000 | E40: =(C40)-(D40) -> 3571.43 | F40: =IF(D40=0,"",(C40)/(D40)) -> 1.1190477 | I40: =(G40)-(H40) -> 0 | J40: =IF(H40=0,"",(G40)/(H40)) | M40: =(K40)-(L40) -> 0 | N40: =IF(L40=0,"",(K40)/(L40)) | Q40: =(O40)-(P40) -> 0 | R40: =IF(P40=0,"",(O40)/(P40)) | U40: =(S40)-(T40) -> 0 | V40: =IF(T40=0,"",(S40)/(T40)) | W40: =((((C40)+(G40))+(K40))+(O40))+(S40) -> 33571.43 | X40: =((((D40)+(H40))+(L40))+(P40))+(T40) -> 30000 | Y40: =(W40)-(X40) -> 3571.43 | Z40: =IF(X40=0,"",(W40)/(X40)) -> 1.1190477
B41: 6310 Shareholder's Health Insurance | C41: =758.25 -> 758.25 | D41: =756 -> 756 | E41: =(C41)-(D41) -> 2.25 | F41: =IF(D41=0,"",(C41)/(D41)) -> 1.0029762 | I41: =(G41)-(H41) -> 0 | J41: =IF(H41=0,"",(G41)/(H41)) | M41: =(K41)-(L41) -> 0 | N41: =IF(L41=0,"",(K41)/(L41)) | Q41: =(O41)-(P41) -> 0 | R41: =IF(P41=0,"",(O41)/(P41)) | U41: =(S41)-(T41) -> 0 | V41: =IF(T41=0,"",(S41)/(T41)) | W41: =((((C41)+(G41))+(K41))+(O41))+(S41) -> 758.25 | X41: =((((D41)+(H41))+(L41))+(P41))+(T41) -> 756 | Y41: =(W41)-(X41) -> 2.25 | Z41: =IF(X41=0,"",(W41)/(X41)) -> 1.0029762
B42: 6315 Shareholder's Payroll Taxes | C42: =2603.11 -> 2603.11 | D42: =2400 -> 2400 | E42: =(C42)-(D42) -> 203.11 | F42: =IF(D42=0,"",(C42)/(D42)) -> 1.0846292 | I42: =(G42)-(H42) -> 0 | J42: =IF(H42=0,"",(G42)/(H42)) | M42: =(K42)-(L42) -> 0 | N42: =IF(L42=0,"",(K42)/(L42)) | Q42: =(O42)-(P42) -> 0 | R42: =IF(P42=0,"",(O42)/(P42)) | U42: =(S42)-(T42) -> 0 | V42: =IF(T42=0,"",(S42)/(T42)) | W42: =((((C42)+(G42))+(K42))+(O42))+(S42) -> 2603.11 | X42: =((((D42)+(H42))+(L42))+(P42))+(T42) -> 2400 | Y42: =(W42)-(X42) -> 203.11 | Z42: =IF(X42=0,"",(W42)/(X42)) -> 1.0846292
B43: 6320 Shareholder's 401(k) Employer Contributions | C43: =1175 -> 1175 | D43: =1137.51 -> 1137.51 | E43: =(C43)-(D43) -> 37.49 | F43: =IF(D43=0,"",(C43)/(D43)) -> 1.032958 | I43: =(G43)-(H43) -> 0 | J43: =IF(H43=0,"",(G43)/(H43)) | M43: =(K43)-(L43) -> 0 | N43: =IF(L43=0,"",(K43)/(L43)) | Q43: =(O43)-(P43) -> 0 | R43: =IF(P43=0,"",(O43)/(P43)) | U43: =(S43)-(T43) -> 0 | V43: =IF(T43=0,"",(S43)/(T43)) | W43: =((((C43)+(G43))+(K43))+(O43))+(S43) -> 1175 | X43: =((((D43)+(H43))+(L43))+(P43))+(T43) -> 1137.51 | Y43: =(W43)-(X43) -> 37.49 | Z43: =IF(X43=0,"",(W43)/(X43)) -> 1.032958
B44: Total 6300 Shareholder's Compensation | C44: =((((C39)+(C40))+(C41))+(C42))+(C43) -> 38107.79 | D44: =((((D39)+(D40))+(D41))+(D42))+(D43) -> 34293.51 | E44: =(C44)-(D44) -> 3814.28 | F44: =IF(D44=0,"",(C44)/(D44)) -> 1.1112245 | G44: =((((G39)+(G40))+(G41))+(G42))+(G43) -> 0 | H44: =((((H39)+(H40))+(H41))+(H42))+(H43) -> 0 | I44: =(G44)-(H44) -> 0 | J44: =IF(H44=0,"",(G44)/(H44)) | K44: =((((K39)+(K40))+(K41))+(K42))+(K43) -> 0 | L44: =((((L39)+(L40))+(L41))+(L42))+(L43) -> 0 | M44: =(K44)-(L44) -> 0 | N44: =IF(L44=0,"",(K44)/(L44)) | O44: =((((O39)+(O40))+(O41))+(O42))+(O43) -> 0 | P44: =((((P39)+(P40))+(P41))+(P42))+(P43) -> 0 | Q44: =(O44)-(P44) -> 0 | R44: =IF(P44=0,"",(O44)/(P44)) | S44: =((((S39)+(S40))+(S41))+(S42))+(S43) -> 0 | T44: =((((T39)+(T40))+(T41))+(T42))+(T43) -> 0 | U44: =(S44)-(T44) -> 0 | V44: =IF(T44=0,"",(S44)/(T44)) | W44: =((((C44)+(G44))+(K44))+(O44))+(S44) -> 38107.79 | X44: =((((D44)+(H44))+(L44))+(P44))+(T44) -> 34293.51 | Y44: =(W44)-(X44) -> 3814.28 | Z44: =IF(X44=0,"",(W44)/(X44)) -> 1.1112245
B45: 6400 Office Expense | E45: =(C45)-(D45) -> 0 | F45: =IF(D45=0,"",(C45)/(D45)) | I45: =(G45)-(H45) -> 0 | J45: =IF(H45=0,"",(G45)/(H45)) | M45: =(K45)-(L45) -> 0 | N45: =IF(L45=0,"",(K45)/(L45)) | Q45: =(O45)-(P45) -> 0 | R45: =IF(P45=0,"",(O45)/(P45)) | U45: =(S45)-(T45) -> 0 | V45: =IF(T45=0,"",(S45)/(T45)) | W45: =((((C45)+(G45))+(K45))+(O45))+(S45) -> 0 | X45: =((((D45)+(H45))+(L45))+(P45))+(T45) -> 0 | Y45: =(W45)-(X45) -> 0 | Z45: =IF(X45=0,"",(W45)/(X45))
B46: 6405 Office Equipment | C46: =15923.64 -> 15923.64 | D46: =10374.99 -> 10374.99 | E46: =(C46)-(D46) -> 5548.65 | F46: =IF(D46=0,"",(C46)/(D46)) -> 1.5348102 | G46: =1694.28 -> 1694.28 | I46: =(G46)-(H46) -> 1694.28 | J46: =IF(H46=0,"",(G46)/(H46)) | M46: =(K46)-(L46) -> 0 | N46: =IF(L46=0,"",(K46)/(L46)) | Q46: =(O46)-(P46) -> 0 | R46: =IF(P46=0,"",(O46)/(P46)) | S46: =3205.72 -> 3205.72 | U46: =(S46)-(T46) -> 3205.72 | V46: =IF(T46=0,"",(S46)/(T46)) | W46: =((((C46)+(G46))+(K46))+(O46))+(S46) -> 20823.64 | X46: =((((D46)+(H46))+(L46))+(P46))+(T46) -> 10374.99 | Y46: =(W46)-(X46) -> 10448.65 | Z46: =IF(X46=0,"",(W46)/(X46)) -> 2.0070998
B47: 6410 Office Supplies | C47: =5206.78 -> 5206.78 | D47: =7749.99 -> 7749.99 | E47: =(C47)-(D47) -> -2543.21 | F47: =IF(D47=0,"",(C47)/(D47)) -> 0.67184345 | H47: =9000 -> 9000 | I47: =(G47)-(H47) -> -9000 | J47: =IF(H47=0,"",(G47)/(H47)) -> 0 | M47: =(K47)-(L47) -> 0 | N47: =IF(L47=0,"",(K47)/(L47)) | O47: =923.75 -> 923.75 | Q47: =(O47)-(P47) -> 923.75 | R47: =IF(P47=0,"",(O47)/(P47)) | S47: =14.93 -> 14.93 | T47: =3999.99 -> 3999.99 | U47: =(S47)-(T47) -> -3985.06 | V47: =IF(T47=0,"",(S47)/(T47)) -> 0.0037325093 | W47: =((((C47)+(G47))+(K47))+(O47))+(S47) -> 6145.46 | X47: =((((D47)+(H47))+(L47))+(P47))+(T47) -> 20749.98 | Y47: =(W47)-(X47) -> -14604.52 | Z47: =IF(X47=0,"",(W47)/(X47)) -> 0.29616703
B48: 6415 Phone and Internet Expense - Office | C48: =926.65 -> 926.65 | D48: =1020 -> 1020 | E48: =(C48)-(D48) -> -93.35 | F48: =IF(D48=0,"",(C48)/(D48)) -> 0.90848039 | I48: =(G48)-(H48) -> 0 | J48: =IF(H48=0,"",(G48)/(H48)) | M48: =(K48)-(L48) -> 0 | N48: =IF(L48=0,"",(K48)/(L48)) | Q48: =(O48)-(P48) -> 0 | R48: =IF(P48=0,"",(O48)/(P48)) | U48: =(S48)-(T48) -> 0 | V48: =IF(T48=0,"",(S48)/(T48)) | W48: =((((C48)+(G48))+(K48))+(O48))+(S48) -> 926.65 | X48: =((((D48)+(H48))+(L48))+(P48))+(T48) -> 1020 | Y48: =(W48)-(X48) -> -93.35 | Z48: =IF(X48=0,"",(W48)/(X48)) -> 0.90848039
B49: 6420 Office Repairs & Maintenance | C49: =4030.22 -> 4030.22 | D49: =3187.5 -> 3187.5 | E49: =(C49)-(D49) -> 842.72 | F49: =IF(D49=0,"",(C49)/(D49)) -> 1.2643827 | G49: =2336.65 -> 2336.65 | I49: =(G49)-(H49) -> 2336.65 | J49: =IF(H49=0,"",(G49)/(H49)) | M49: =(K49)-(L49) -> 0 | N49: =IF(L49=0,"",(K49)/(L49)) | Q49: =(O49)-(P49) -> 0 | R49: =IF(P49=0,"",(O49)/(P49)) | S49: =1370 -> 1370 | T49: =2000.01 -> 2000.01 | U49: =(S49)-(T49) -> -630.01 | V49: =IF(T49=0,"",(S49)/(T49)) -> 0.68499658 | W49: =((((C49)+(G49))+(K49))+(O49))+(S49) -> 7736.87 | X49: =((((D49)+(H49))+(L49))+(P49))+(T49) -> 5187.51 | Y49: =(W49)-(X49) -> 2549.36 | Z49: =IF(X49=0,"",(W49)/(X49)) -> 1.4914419
B50: Total 6400 Office Expense | C50: =((((C45)+(C46))+(C47))+(C48))+(C49) -> 26087.29 | D50: =((((D45)+(D46))+(D47))+(D48))+(D49) -> 22332.48 | E50: =(C50)-(D50) -> 3754.81 | F50: =IF(D50=0,"",(C50)/(D50)) -> 1.1681322 | G50: =((((G45)+(G46))+(G47))+(G48))+(G49) -> 4030.93 | H50: =((((H45)+(H46))+(H47))+(H48))+(H49) -> 9000 | I50: =(G50)-(H50) -> -4969.07 | J50: =IF(H50=0,"",(G50)/(H50)) -> 0.44788111 | K50: =((((K45)+(K46))+(K47))+(K48))+(K49) -> 0 | L50: =((((L45)+(L46))+(L47))+(L48))+(L49) -> 0 | M50: =(K50)-(L50) -> 0 | N50: =IF(L50=0,"",(K50)/(L50)) | O50: =((((O45)+(O46))+(O47))+(O48))+(O49) -> 923.75 | P50: =((((P45)+(P46))+(P47))+(P48))+(P49) -> 0 | Q50: =(O50)-(P50) -> 923.75 | R50: =IF(P50=0,"",(O50)/(P50)) | S50: =((((S45)+(S46))+(S47))+(S48))+(S49) -> 4590.65 | T50: =((((T45)+(T46))+(T47))+(T48))+(T49) -> 6000 | U50: =(S50)-(T50) -> -1409.35 | V50: =IF(T50=0,"",(S50)/(T50)) -> 0.76510833 | W50: =((((C50)+(G50))+(K50))+(O50))+(S50) -> 35632.62 | X50: =((((D50)+(H50))+(L50))+(P50))+(T50) -> 37332.48 | Y50: =(W50)-(X50) -> -1699.86 | Z50: =IF(X50=0,"",(W50)/(X50)) -> 0.95446699
B51: 6500 Facility Expense | E51: =(C51)-(D51) -> 0 | F51: =IF(D51=0,"",(C51)/(D51)) | I51: =(G51)-(H51) -> 0 | J51: =IF(H51=0,"",(G51)/(H51)) | M51: =(K51)-(L51) -> 0 | N51: =IF(L51=0,"",(K51)/(L51)) | Q51: =(O51)-(P51) -> 0 | R51: =IF(P51=0,"",(O51)/(P51)) | U51: =(S51)-(T51) -> 0 | V51: =IF(T51=0,"",(S51)/(T51)) | W51: =((((C51)+(G51))+(K51))+(O51))+(S51) -> 0 | X51: =((((D51)+(H51))+(L51))+(P51))+(T51) -> 0 | Y51: =(W51)-(X51) -> 0 | Z51: =IF(X51=0,"",(W51)/(X51))
B52: 6505 Rent Expense | C52: =47857.68 -> 47857.68 | D52: =50280.18 -> 50280.18 | E52: =(C52)-(D52) -> -2422.5 | F52: =IF(D52=0,"",(C52)/(D52)) -> 0.95181998 | I52: =(G52)-(H52) -> 0 | J52: =IF(H52=0,"",(G52)/(H52)) | M52: =(K52)-(L52) -> 0 | N52: =IF(L52=0,"",(K52)/(L52)) | Q52: =(O52)-(P52) -> 0 | R52: =IF(P52=0,"",(O52)/(P52)) | U52: =(S52)-(T52) -> 0 | V52: =IF(T52=0,"",(S52)/(T52)) | W52: =((((C52)+(G52))+(K52))+(O52))+(S52) -> 47857.68 | X52: =((((D52)+(H52))+(L52))+(P52))+(T52) -> 50280.18 | Y52: =(W52)-(X52) -> -2422.5 | Z52: =IF(X52=0,"",(W52)/(X52)) -> 0.95181998
B53: 6510 CAM Charges | C53: =13564.32 -> 13564.32 | D53: =13024.44 -> 13024.44 | E53: =(C53)-(D53) -> 539.88 | F53: =IF(D53=0,"",(C53)/(D53)) -> 1.0414513 | I53: =(G53)-(H53) -> 0 | J53: =IF(H53=0,"",(G53)/(H53)) | M53: =(K53)-(L53) -> 0 | N53: =IF(L53=0,"",(K53)/(L53)) | Q53: =(O53)-(P53) -> 0 | R53: =IF(P53=0,"",(O53)/(P53)) | U53: =(S53)-(T53) -> 0 | V53: =IF(T53=0,"",(S53)/(T53)) | W53: =((((C53)+(G53))+(K53))+(O53))+(S53) -> 13564.32 | X53: =((((D53)+(H53))+(L53))+(P53))+(T53) -> 13024.44 | Y53: =(W53)-(X53) -> 539.88 | Z53: =IF(X53=0,"",(W53)/(X53)) -> 1.0414513
B54: 6515 Utilities | C54: =17840.02 -> 17840.02 | D54: =20750.01 -> 20750.01 | E54: =(C54)-(D54) -> -2909.99 | F54: =IF(D54=0,"",(C54)/(D54)) -> 0.85975959 | I54: =(G54)-(H54) -> 0 | J54: =IF(H54=0,"",(G54)/(H54)) | M54: =(K54)-(L54) -> 0 | N54: =IF(L54=0,"",(K54)/(L54)) | Q54: =(O54)-(P54) -> 0 | R54: =IF(P54=0,"",(O54)/(P54)) | U54: =(S54)-(T54) -> 0 | V54: =IF(T54=0,"",(S54)/(T54)) | W54: =((((C54)+(G54))+(K54))+(O54))+(S54) -> 17840.02 | X54: =((((D54)+(H54))+(L54))+(P54))+(T54) -> 20750.01 | Y54: =(W54)-(X54) -> -2909.99 | Z54: =IF(X54=0,"",(W54)/(X54)) -> 0.85975959
B55: 6520 Business Insurance | C55: =3743.21 -> 3743.21 | D55: =3696.33 -> 3696.33 | E55: =(C55)-(D55) -> 46.88 | F55: =IF(D55=0,"",(C55)/(D55)) -> 1.0126829 | I55: =(G55)-(H55) -> 0 | J55: =IF(H55=0,"",(G55)/(H55)) | M55: =(K55)-(L55) -> 0 | N55: =IF(L55=0,"",(K55)/(L55)) | Q55: =(O55)-(P55) -> 0 | R55: =IF(P55=0,"",(O55)/(P55)) | U55: =(S55)-(T55) -> 0 | V55: =IF(T55=0,"",(S55)/(T55)) | W55: =((((C55)+(G55))+(K55))+(O55))+(S55) -> 3743.21 | X55: =((((D55)+(H55))+(L55))+(P55))+(T55) -> 3696.33 | Y55: =(W55)-(X55) -> 46.88 | Z55: =IF(X55=0,"",(W55)/(X55)) -> 1.0126829
B56: 6540 HP Lease Expense | E56: =(C56)-(D56) -> 0 | F56: =IF(D56=0,"",(C56)/(D56)) | G56: =8503.67 -> 8503.67 | H56: =22500 -> 22500 | I56: =(G56)-(H56) -> -13996.33 | J56: =IF(H56=0,"",(G56)/(H56)) -> 0.37794089 | M56: =(K56)-(L56) -> 0 | N56: =IF(L56=0,"",(K56)/(L56)) | Q56: =(O56)-(P56) -> 0 | R56: =IF(P56=0,"",(O56)/(P56)) | T56: =0 -> 0 | U56: =(S56)-(T56) -> 0 | V56: =IF(T56=0,"",(S56)/(T56)) | W56: =((((C56)+(G56))+(K56))+(O56))+(S56) -> 8503.67 | X56: =((((D56)+(H56))+(L56))+(P56))+(T56) -> 22500 | Y56: =(W56)-(X56) -> -13996.33 | Z56: =IF(X56=0,"",(W56)/(X56)) -> 0.37794089
B57: Total 6500 Facility Expense | C57: =(((((C51)+(C52))+(C53))+(C54))+(C55))+(C56) -> 83005.23 | D57: =(((((D51)+(D52))+(D53))+(D54))+(D55))+(D56) -> 87750.96 | E57: =(C57)-(D57) -> -4745.73 | F57: =IF(D57=0,"",(C57)/(D57)) -> 0.9459182 | G57: =(((((G51)+(G52))+(G53))+(G54))+(G55))+(G56) -> 8503.67 | H57: =(((((H51)+(H52))+(H53))+(H54))+(H55))+(H56) -> 22500 | I57: =(G57)-(H57) -> -13996.33 | J57: =IF(H57=0,"",(G57)/(H57)) -> 0.37794089 | K57: =(((((K51)+(K52))+(K53))+(K54))+(K55))+(K56) -> 0 | L57: =(((((L51)+(L52))+(L53))+(L54))+(L55))+(L56) -> 0 | M57: =(K57)-(L57) -> 0 | N57: =IF(L57=0,"",(K57)/(L57)) | O57: =(((((O51)+(O52))+(O53))+(O54))+(O55))+(O56) -> 0 | P57: =(((((P51)+(P52))+(P53))+(P54))+(P55))+(P56) -> 0 | Q57: =(O57)-(P57) -> 0 | R57: =IF(P57=0,"",(O57)/(P57)) | S57: =(((((S51)+(S52))+(S53))+(S54))+(S55))+(S56) -> 0 | T57: =(((((T51)+(T52))+(T53))+(T54))+(T55))+(T56) -> 0 | U57: =(S57)-(T57) -> 0 | V57: =IF(T57=0,"",(S57)/(T57)) | W57: =((((C57)+(G57))+(K57))+(O57))+(S57) -> 91508.9 | X57: =((((D57)+(H57))+(L57))+(P57))+(T57) -> 110250.96 | Y57: =(W57)-(X57) -> -18742.06 | Z57: =IF(X57=0,"",(W57)/(X57)) -> 0.83000547
B58: 6600 Other Operating Expenses | E58: =(C58)-(D58) -> 0 | F58: =IF(D58=0,"",(C58)/(D58)) | I58: =(G58)-(H58) -> 0 | J58: =IF(H58=0,"",(G58)/(H58)) | M58: =(K58)-(L58) -> 0 | N58: =IF(L58=0,"",(K58)/(L58)) | Q58: =(O58)-(P58) -> 0 | R58: =IF(P58=0,"",(O58)/(P58)) | U58: =(S58)-(T58) -> 0 | V58: =IF(T58=0,"",(S58)/(T58)) | W58: =((((C58)+(G58))+(K58))+(O58))+(S58) -> 0 | X58: =((((D58)+(H58))+(L58))+(P58))+(T58) -> 0 | Y58: =(W58)-(X58) -> 0 | Z58: =IF(X58=0,"",(W58)/(X58))
B59: 6605 Advertising & Marketing | C59: =9507.38 -> 9507.38 | D59: =15562.5 -> 15562.5 | E59: =(C59)-(D59) -> -6055.12 | F59: =IF(D59=0,"",(C59)/(D59)) -> 0.61091598 | G59: =500 -> 500 | I59: =(G59)-(H59) -> 500 | J59: =IF(H59=0,"",(G59)/(H59)) | M59: =(K59)-(L59) -> 0 | N59: =IF(L59=0,"",(K59)/(L59)) | Q59: =(O59)-(P59) -> 0 | R59: =IF(P59=0,"",(O59)/(P59)) | S59: =500 -> 500 | U59: =(S59)-(T59) -> 500 | V59: =IF(T59=0,"",(S59)/(T59)) | W59: =((((C59)+(G59))+(K59))+(O59))+(S59) -> 10507.38 | X59: =((((D59)+(H59))+(L59))+(P59))+(T59) -> 15562.5 | Y59: =(W59)-(X59) -> -5055.12 | Z59: =IF(X59=0,"",(W59)/(X59)) -> 0.67517301
B60: 6610 Software Costs | C60: =12085.25 -> 12085.25 | D60: =7005.78 -> 7005.78 | E60: =(C60)-(D60) -> 5079.47 | F60: =IF(D60=0,"",(C60)/(D60)) -> 1.7250399 | G60: =5 -> 5 | I60: =(G60)-(H60) -> 5 | J60: =IF(H60=0,"",(G60)/(H60)) | M60: =(K60)-(L60) -> 0 | N60: =IF(L60=0,"",(K60)/(L60)) | O60: =185 -> 185 | P60: =3125.01 -> 3125.01 | Q60: =(O60)-(P60) -> -2940.01 | R60: =IF(P60=0,"",(O60)/(P60)) -> 0.059199811 | S60: =1004.76 -> 1004.76 | U60: =(S60)-(T60) -> 1004.76 | V60: =IF(T60=0,"",(S60)/(T60)) | W60: =((((C60)+(G60))+(K60))+(O60))+(S60) -> 13280.01 | X60: =((((D60)+(H60))+(L60))+(P60))+(T60) -> 10130.79 | Y60: =(W60)-(X60) -> 3149.22 | Z60: =IF(X60=0,"",(W60)/(X60)) -> 1.3108563
B61: 6615 Vehicle Expense | C61: =1561.45 -> 1561.45 | D61: =5187.51 -> 5187.51 | E61: =(C61)-(D61) -> -3626.06 | F61: =IF(D61=0,"",(C61)/(D61)) -> 0.30100183 | I61: =(G61)-(H61) -> 0 | J61: =IF(H61=0,"",(G61)/(H61)) | M61: =(K61)-(L61) -> 0 | N61: =IF(L61=0,"",(K61)/(L61)) | O61: 75 | Q61: =(O61)-(P61) -> 75 | R61: =IF(P61=0,"",(O61)/(P61)) | U61: =(S61)-(T61) -> 0 | V61: =IF(T61=0,"",(S61)/(T61)) | W61: =((((C61)+(G61))+(K61))+(O61))+(S61) -> 1636.45 | X61: =((((D61)+(H61))+(L61))+(P61))+(T61) -> 5187.51 | Y61: =(W61)-(X61) -> -3551.06 | Z61: =IF(X61=0,"",(W61)/(X61)) -> 0.31545963
B62: 6620 Auto Lease Expense | C62: =6961.92 -> 6961.92 | D62: =6961.92 -> 6961.92 | E62: =(C62)-(D62) -> 0 | F62: =IF(D62=0,"",(C62)/(D62)) -> 1 | I62: =(G62)-(H62) -> 0 | J62: =IF(H62=0,"",(G62)/(H62)) | M62: =(K62)-(L62) -> 0 | N62: =IF(L62=0,"",(K62)/(L62)) | Q62: =(O62)-(P62) -> 0 | R62: =IF(P62=0,"",(O62)/(P62)) | U62: =(S62)-(T62) -> 0 | V62: =IF(T62=0,"",(S62)/(T62)) | W62: =((((C62)+(G62))+(K62))+(O62))+(S62) -> 6961.92 | X62: =((((D62)+(H62))+(L62))+(P62))+(T62) -> 6961.92 | Y62: =(W62)-(X62) -> 0 | Z62: =IF(X62=0,"",(W62)/(X62)) -> 1
B63: 6625 Client Gifts | D63: =1275 -> 1275 | E63: =(C63)-(D63) -> -1275 | F63: =IF(D63=0,"",(C63)/(D63)) -> 0 | I63: =(G63)-(H63) -> 0 | J63: =IF(H63=0,"",(G63)/(H63)) | M63: =(K63)-(L63) -> 0 | N63: =IF(L63=0,"",(K63)/(L63)) | Q63: =(O63)-(P63) -> 0 | R63: =IF(P63=0,"",(O63)/(P63)) | U63: =(S63)-(T63) -> 0 | V63: =IF(T63=0,"",(S63)/(T63)) | W63: =((((C63)+(G63))+(K63))+(O63))+(S63) -> 0 | X63: =((((D63)+(H63))+(L63))+(P63))+(T63) -> 1275 | Y63: =(W63)-(X63) -> -1275 | Z63: =IF(X63=0,"",(W63)/(X63)) -> 0
B64: 6630 Shipping & Postage | C64: =3064.97 -> 3064.97 | D64: =2075.01 -> 2075.01 | E64: =(C64)-(D64) -> 989.96 | F64: =IF(D64=0,"",(C64)/(D64)) -> 1.4770869 | I64: =(G64)-(H64) -> 0 | J64: =IF(H64=0,"",(G64)/(H64)) | M64: =(K64)-(L64) -> 0 | N64: =IF(L64=0,"",(K64)/(L64)) | Q64: =(O64)-(P64) -> 0 | R64: =IF(P64=0,"",(O64)/(P64)) | U64: =(S64)-(T64) -> 0 | V64: =IF(T64=0,"",(S64)/(T64)) | W64: =((((C64)+(G64))+(K64))+(O64))+(S64) -> 3064.97 | X64: =((((D64)+(H64))+(L64))+(P64))+(T64) -> 2075.01 | Y64: =(W64)-(X64) -> 989.96 | Z64: =IF(X64=0,"",(W64)/(X64)) -> 1.4770869
B65: 6635 Travel - Management | C65: =5788.43 -> 5788.43 | D65: =1550.01 -> 1550.01 | E65: =(C65)-(D65) -> 4238.42 | F65: =IF(D65=0,"",(C65)/(D65)) -> 3.7344469 | G65: =491.81 -> 491.81 | I65: =(G65)-(H65) -> 491.81 | J65: =IF(H65=0,"",(G65)/(H65)) | M65: =(K65)-(L65) -> 0 | N65: =IF(L65=0,"",(K65)/(L65)) | O65: =193.18 -> 193.18 | P65: =1562.49 -> 1562.49 | Q65: =(O65)-(P65) -> -1369.31 | R65: =IF(P65=0,"",(O65)/(P65)) -> 0.12363599 | U65: =(S65)-(T65) -> 0 | V65: =IF(T65=0,"",(S65)/(T65)) | W65: =((((C65)+(G65))+(K65))+(O65))+(S65) -> 6473.42 | X65: =((((D65)+(H65))+(L65))+(P65))+(T65) -> 3112.5 | Y65: =(W65)-(X65) -> 3360.92 | Z65: =IF(X65=0,"",(W65)/(X65)) -> 2.0798137
B66: 6640 Bank Service Charges | C66: =734.74 -> 734.74 | D66: =1037.49 -> 1037.49 | E66: =(C66)-(D66) -> -302.75 | F66: =IF(D66=0,"",(C66)/(D66)) -> 0.70818996 | G66: =4155.72 -> 4155.72 | I66: =(G66)-(H66) -> 4155.72 | J66: =IF(H66=0,"",(G66)/(H66)) | M66: =(K66)-(L66) -> 0 | N66: =IF(L66=0,"",(K66)/(L66)) | Q66: =(O66)-(P66) -> 0 | R66: =IF(P66=0,"",(O66)/(P66)) | S66: =23.1 -> 23.1 | U66: =(S66)-(T66) -> 23.1 | V66: =IF(T66=0,"",(S66)/(T66)) | W66: =((((C66)+(G66))+(K66))+(O66))+(S66) -> 4913.56 | X66: =((((D66)+(H66))+(L66))+(P66))+(T66) -> 1037.49 | Y66: =(W66)-(X66) -> 3876.07 | Z66: =IF(X66=0,"",(W66)/(X66)) -> 4.7360071
B67: 6645 Disability & Life Insurance | C67: =514.62 -> 514.62 | D67: =514.62 -> 514.62 | E67: =(C67)-(D67) -> 0 | F67: =IF(D67=0,"",(C67)/(D67)) -> 1 | I67: =(G67)-(H67) -> 0 | J67: =IF(H67=0,"",(G67)/(H67)) | M67: =(K67)-(L67) -> 0 | N67: =IF(L67=0,"",(K67)/(L67)) | Q67: =(O67)-(P67) -> 0 | R67: =IF(P67=0,"",(O67)/(P67)) | U67: =(S67)-(T67) -> 0 | V67: =IF(T67=0,"",(S67)/(T67)) | W67: =((((C67)+(G67))+(K67))+(O67))+(S67) -> 514.62 | X67: =((((D67)+(H67))+(L67))+(P67))+(T67) -> 514.62 | Y67: =(W67)-(X67) -> 0 | Z67: =IF(X67=0,"",(W67)/(X67)) -> 1
B68: 6650 Business Tax & Licenses | D68: =1037.49 -> 1037.49 | E68: =(C68)-(D68) -> -1037.49 | F68: =IF(D68=0,"",(C68)/(D68)) -> 0 | I68: =(G68)-(H68) -> 0 | J68: =IF(H68=0,"",(G68)/(H68)) | M68: =(K68)-(L68) -> 0 | N68: =IF(L68=0,"",(K68)/(L68)) | Q68: =(O68)-(P68) -> 0 | R68: =IF(P68=0,"",(O68)/(P68)) | U68: =(S68)-(T68) -> 0 | V68: =IF(T68=0,"",(S68)/(T68)) | W68: =((((C68)+(G68))+(K68))+(O68))+(S68) -> 0 | X68: =((((D68)+(H68))+(L68))+(P68))+(T68) -> 1037.49 | Y68: =(W68)-(X68) -> -1037.49 | Z68: =IF(X68=0,"",(W68)/(X68)) -> 0
B69: 6660 Meals and Entertainment | C69: =2037.2 -> 2037.2 | D69: =5187.51 -> 5187.51 | E69: =(C69)-(D69) -> -3150.31 | F69: =IF(D69=0,"",(C69)/(D69)) -> 0.3927125 | I69: =(G69)-(H69) -> 0 | J69: =IF(H69=0,"",(G69)/(H69)) | M69: =(K69)-(L69) -> 0 | N69: =IF(L69=0,"",(K69)/(L69)) | O69: =1347.83 -> 1347.83 | Q69: =(O69)-(P69) -> 1347.83 | R69: =IF(P69=0,"",(O69)/(P69)) | U69: =(S69)-(T69) -> 0 | V69: =IF(T69=0,"",(S69)/(T69)) | W69: =((((C69)+(G69))+(K69))+(O69))+(S69) -> 3385.03 | X69: =((((D69)+(H69))+(L69))+(P69))+(T69) -> 5187.51 | Y69: =(W69)-(X69) -> -1802.48 | Z69: =IF(X69=0,"",(W69)/(X69)) -> 0.65253465
B70: 6665 Dues & Subscriptions | C70: =1577.97 -> 1577.97 | D70: =936.96 -> 936.96 | E70: =(C70)-(D70) -> 641.01 | F70: =IF(D70=0,"",(C70)/(D70)) -> 1.6841381 | G70: =500.25 -> 500.25 | I70: =(G70)-(H70) -> 500.25 | J70: =IF(H70=0,"",(G70)/(H70)) | M70: =(K70)-(L70) -> 0 | N70: =IF(L70=0,"",(K70)/(L70)) | Q70: =(O70)-(P70) -> 0 | R70: =IF(P70=0,"",(O70)/(P70)) | U70: =(S70)-(T70) -> 0 | V70: =IF(T70=0,"",(S70)/(T70)) | W70: =((((C70)+(G70))+(K70))+(O70))+(S70) -> 2078.22 | X70: =((((D70)+(H70))+(L70))+(P70))+(T70) -> 936.96 | Y70: =(W70)-(X70) -> 1141.26 | Z70: =IF(X70=0,"",(W70)/(X70)) -> 2.2180456
B71: 6670 QuickBooks Payments Fees | C71: =736.07 -> 736.07 | D71: =518.76 -> 518.76 | E71: =(C71)-(D71) -> 217.31 | F71: =IF(D71=0,"",(C71)/(D71)) -> 1.4189028 | I71: =(G71)-(H71) -> 0 | J71: =IF(H71=0,"",(G71)/(H71)) | M71: =(K71)-(L71) -> 0 | N71: =IF(L71=0,"",(K71)/(L71)) | Q71: =(O71)-(P71) -> 0 | R71: =IF(P71=0,"",(O71)/(P71)) | U71: =(S71)-(T71) -> 0 | V71: =IF(T71=0,"",(S71)/(T71)) | W71: =((((C71)+(G71))+(K71))+(O71))+(S71) -> 736.07 | X71: =((((D71)+(H71))+(L71))+(P71))+(T71) -> 518.76 | Y71: =(W71)-(X71) -> 217.31 | Z71: =IF(X71=0,"",(W71)/(X71)) -> 1.4189028
B72: 6690 Vehicle Insurance | C72: =1464.66 -> 1464.66 | D72: =1608 -> 1608 | E72: =(C72)-(D72) -> -143.34 | F72: =IF(D72=0,"",(C72)/(D72)) -> 0.91085821 | I72: =(G72)-(H72) -> 0 | J72: =IF(H72=0,"",(G72)/(H72)) | M72: =(K72)-(L72) -> 0 | N72: =IF(L72=0,"",(K72)/(L72)) | Q72: =(O72)-(P72) -> 0 | R72: =IF(P72=0,"",(O72)/(P72)) | U72: =(S72)-(T72) -> 0 | V72: =IF(T72=0,"",(S72)/(T72)) | W72: =((((C72)+(G72))+(K72))+(O72))+(S72) -> 1464.66 | X72: =((((D72)+(H72))+(L72))+(P72))+(T72) -> 1608 | Y72: =(W72)-(X72) -> -143.34 | Z72: =IF(X72=0,"",(W72)/(X72)) -> 0.91085821
B73: 6700 Donations | D73: =518.76 -> 518.76 | E73: =(C73)-(D73) -> -518.76 | F73: =IF(D73=0,"",(C73)/(D73)) -> 0 | I73: =(G73)-(H73) -> 0 | J73: =IF(H73=0,"",(G73)/(H73)) | M73: =(K73)-(L73) -> 0 | N73: =IF(L73=0,"",(K73)/(L73)) | Q73: =(O73)-(P73) -> 0 | R73: =IF(P73=0,"",(O73)/(P73)) | U73: =(S73)-(T73) -> 0 | V73: =IF(T73=0,"",(S73)/(T73)) | W73: =((((C73)+(G73))+(K73))+(O73))+(S73) -> 0 | X73: =((((D73)+(H73))+(L73))+(P73))+(T73) -> 518.76 | Y73: =(W73)-(X73) -> -518.76 | Z73: =IF(X73=0,"",(W73)/(X73)) -> 0
B74: 6705 Bad Debt Expense | D74: =5187.51 -> 5187.51 | E74: =(C74)-(D74) -> -5187.51 | F74: =IF(D74=0,"",(C74)/(D74)) -> 0 | I74: =(G74)-(H74) -> 0 | J74: =IF(H74=0,"",(G74)/(H74)) | M74: =(K74)-(L74) -> 0 | N74: =IF(L74=0,"",(K74)/(L74)) | Q74: =(O74)-(P74) -> 0 | R74: =IF(P74=0,"",(O74)/(P74)) | U74: =(S74)-(T74) -> 0 | V74: =IF(T74=0,"",(S74)/(T74)) | W74: =((((C74)+(G74))+(K74))+(O74))+(S74) -> 0 | X74: =((((D74)+(H74))+(L74))+(P74))+(T74) -> 5187.51 | Y74: =(W74)-(X74) -> -5187.51 | Z74: =IF(X74=0,"",(W74)/(X74)) -> 0
B75: 6715 Other Miscellaneous Expense | C75: =4867.35 -> 4867.35 | D75: =103.74 -> 103.74 | E75: =(C75)-(D75) -> 4763.61 | F75: =IF(D75=0,"",(C75)/(D75)) -> 46.918739 | I75: =(G75)-(H75) -> 0 | J75: =IF(H75=0,"",(G75)/(H75)) | K75: =-334.75 -> -334.75 | M75: =(K75)-(L75) -> -334.75 | N75: =IF(L75=0,"",(K75)/(L75)) | Q75: =(O75)-(P75) -> 0 | R75: =IF(P75=0,"",(O75)/(P75)) | U75: =(S75)-(T75) -> 0 | V75: =IF(T75=0,"",(S75)/(T75)) | W75: =((((C75)+(G75))+(K75))+(O75))+(S75) -> 4532.6 | X75: =((((D75)+(H75))+(L75))+(P75))+(T75) -> 103.74 | Y75: =(W75)-(X75) -> 4428.86 | Z75: =IF(X75=0,"",(W75)/(X75)) -> 43.691922
B76: Total 6600 Other Operating Expenses | C76: =(((((((((((((((((C58)+(C59))+(C60))+(C61))+(C62))+(C63))+(C64))+(C65))+(C66))+(C67))+(C68))+(C69))+(C70))+(C71))+(C72))+(C73))+(C74))+(C75) -> 50902.01 | D76: =(((((((((((((((((D58)+(D59))+(D60))+(D61))+(D62))+(D63))+(D64))+(D65))+(D66))+(D67))+(D68))+(D69))+(D70))+(D71))+(D72))+(D73))+(D74))+(D75) -> 56268.57 | E76: =(C76)-(D76) -> -5366.56 | F76: =IF(D76=0,"",(C76)/(D76)) -> 0.90462598 | G76: =(((((((((((((((((G58)+(G59))+(G60))+(G61))+(G62))+(G63))+(G64))+(G65))+(G66))+(G67))+(G68))+(G69))+(G70))+(G71))+(G72))+(G73))+(G74))+(G75) -> 5652.78 | H76: =(((((((((((((((((H58)+(H59))+(H60))+(H61))+(H62))+(H63))+(H64))+(H65))+(H66))+(H67))+(H68))+(H69))+(H70))+(H71))+(H72))+(H73))+(H74))+(H75) -> 0 | I76: =(G76)-(H76) -> 5652.78 | J76: =IF(H76=0,"",(G76)/(H76)) | K76: =(((((((((((((((((K58)+(K59))+(K60))+(K61))+(K62))+(K63))+(K64))+(K65))+(K66))+(K67))+(K68))+(K69))+(K70))+(K71))+(K72))+(K73))+(K74))+(K75) -> -334.75 | L76: =(((((((((((((((((L58)+(L59))+(L60))+(L61))+(L62))+(L63))+(L64))+(L65))+(L66))+(L67))+(L68))+(L69))+(L70))+(L71))+(L72))+(L73))+(L74))+(L75) -> 0 | M76: =(K76)-(L76) -> -334.75 | N76: =IF(L76=0,"",(K76)/(L76)) | O76: =(((((((((((((((((O58)+(O59))+(O60))+(O61))+(O62))+(O63))+(O64))+(O65))+(O66))+(O67))+(O68))+(O69))+(O70))+(O71))+(O72))+(O73))+(O74))+(O75) -> 1801.01 | P76: =(((((((((((((((((P58)+(P59))+(P60))+(P61))+(P62))+(P63))+(P64))+(P65))+(P66))+(P67))+(P68))+(P69))+(P70))+(P71))+(P72))+(P73))+(P74))+(P75) -> 4687.5 | Q76: =(O76)-(P76) -> -2886.49 | R76: =IF(P76=0,"",(O76)/(P76)) -> 0.38421547 | S76: =(((((((((((((((((S58)+(S59))+(S60))+(S61))+(S62))+(S63))+(S64))+(S65))+(S66))+(S67))+(S68))+(S69))+(S70))+(S71))+(S72))+(S73))+(S74))+(S75) -> 1527.86 | T76: =(((((((((((((((((T58)+(T59))+(T60))+(T61))+(T62))+(T63))+(T64))+(T65))+(T66))+(T67))+(T68))+(T69))+(T70))+(T71))+(T72))+(T73))+(T74))+(T75) -> 0 | U76: =(S76)-(T76) -> 1527.86 | V76: =IF(T76=0,"",(S76)/(T76)) | W76: =((((C76)+(G76))+(K76))+(O76))+(S76) -> 59548.91 | X76: =((((D76)+(H76))+(L76))+(P76))+(T76) -> 60956.07 | Y76: =(W76)-(X76) -> -1407.16 | Z76: =IF(X76=0,"",(W76)/(X76)) -> 0.97691518
B77: Total Expenses | C77: =(((((((((C28)+(C29))+(C30))+(C31))+(C32))+(C38))+(C44))+(C50))+(C57))+(C76) -> 231087.97 | D77: =(((((((((D28)+(D29))+(D30))+(D31))+(D32))+(D38))+(D44))+(D50))+(D57))+(D76) -> 226827.6 | E77: =(C77)-(D77) -> 4260.37 | F77: =IF(D77=0,"",(C77)/(D77)) -> 1.0187824 | G77: =(((((((((G28)+(G29))+(G30))+(G31))+(G32))+(G38))+(G44))+(G50))+(G57))+(G76) -> 66462.58 | H77: =(((((((((H28)+(H29))+(H30))+(H31))+(H32))+(H38))+(H44))+(H50))+(H57))+(H76) -> 79601.67 | I77: =(G77)-(H77) -> -13139.09 | J77: =IF(H77=0,"",(G77)/(H77)) -> 0.83493952 | K77: =(((((((((K28)+(K29))+(K30))+(K31))+(K32))+(K38))+(K44))+(K50))+(K57))+(K76) -> 4397.9 | L77: =(((((((((L28)+(L29))+(L30))+(L31))+(L32))+(L38))+(L44))+(L50))+(L57))+(L76) -> 3435.81 | M77: =(K77)-(L77) -> 962.09 | N77: =IF(L77=0,"",(K77)/(L77)) -> 1.2800184 | O77: =(((((((((O28)+(O29))+(O30))+(O31))+(O32))+(O38))+(O44))+(O50))+(O57))+(O76) -> 25011.01 | P77: =(((((((((P28)+(P29))+(P30))+(P31))+(P32))+(P38))+(P44))+(P50))+(P57))+(P76) -> 25302.51 | Q77: =(O77)-(P77) -> -291.5 | R77: =IF(P77=0,"",(O77)/(P77)) -> 0.9884794 | S77: =(((((((((S28)+(S29))+(S30))+(S31))+(S32))+(S38))+(S44))+(S50))+(S57))+(S76) -> 8209.08 | T77: =(((((((((T28)+(T29))+(T30))+(T31))+(T32))+(T38))+(T44))+(T50))+(T57))+(T76) -> 8977.8 | U77: =(S77)-(T77) -> -768.72 | V77: =IF(T77=0,"",(S77)/(T77)) -> 0.91437546 | W77: =((((C77)+(G77))+(K77))+(O77))+(S77) -> 335168.54 | X77: =((((D77)+(H77))+(L77))+(P77))+(T77) -> 344145.39 | Y77: =(W77)-(X77) -> -8976.85 | Z77: =IF(X77=0,"",(W77)/(X77)) -> 0.97391553
B78: Net Operating Income | C78: =(C21)-(C77) -> -231381.51 | D78: =(D21)-(D77) -> -226827.6 | E78: =(C78)-(D78) -> -4553.91 | F78: =IF(D78=0,"",(C78)/(D78)) -> 1.0200765 | G78: =(G21)-(G77) -> 197253.59 | H78: =(H21)-(H77) -> 177705.15 | I78: =(G78)-(H78) -> 19548.44 | J78: =IF(H78=0,"",(G78)/(H78)) -> 1.1100049 | K78: =(K21)-(K77) -> -3208.71 | L78: =(L21)-(L77) -> 18314.19 | M78: =(K78)-(L78) -> -21522.9 | N78: =IF(L78=0,"",(K78)/(L78)) -> -0.17520349 | O78: =(O21)-(O77) -> 71899.96 | P78: =(P21)-(P77) -> 150865.98 | Q78: =(O78)-(P78) -> -78966.02 | R78: =IF(P78=0,"",(O78)/(P78)) -> 0.47658167 | S78: =(S21)-(S77) -> -54016.37 | T78: =(T21)-(T77) -> 181497.54 | U78: =(S78)-(T78) -> -235513.91 | V78: =IF(T78=0,"",(S78)/(T78)) -> -0.29761489 | W78: =((((C78)+(G78))+(K78))+(O78))+(S78) -> -19453.04 | X78: =((((D78)+(H78))+(L78))+(P78))+(T78) -> 301555.26 | Y78: =(W78)-(X78) -> -321008.3 | Z78: =IF(X78=0,"",(W78)/(X78)) -> -0.064509039
B79: Other Income
B80: 7005 Other Miscellaneous Income | C80: =15689.99 -> 15689.99 | E80: =(C80)-(D80) -> 15689.99 | F80: =IF(D80=0,"",(C80)/(D80)) | I80: =(G80)-(H80) -> 0 | J80: =IF(H80=0,"",(G80)/(H80)) | M80: =(K80)-(L80) -> 0 | N80: =IF(L80=0,"",(K80)/(L80)) | Q80: =(O80)-(P80) -> 0 | R80: =IF(P80=0,"",(O80)/(P80)) | U80: =(S80)-(T80) -> 0 | V80: =IF(T80=0,"",(S80)/(T80)) | W80: =((((C80)+(G80))+(K80))+(O80))+(S80) -> 15689.99 | X80: =((((D80)+(H80))+(L80))+(P80))+(T80) -> 0 | Y80: =(W80)-(X80) -> 15689.99 | Z80: =IF(X80=0,"",(W80)/(X80))
B81: 7010 Other Income – Insurance Proceeds | C81: =12897.29 -> 12897.29 | E81: =(C81)-(D81) -> 12897.29 | F81: =IF(D81=0,"",(C81)/(D81)) | I81: =(G81)-(H81) -> 0 | J81: =IF(H81=0,"",(G81)/(H81)) | M81: =(K81)-(L81) -> 0 | N81: =IF(L81=0,"",(K81)/(L81)) | Q81: =(O81)-(P81) -> 0 | R81: =IF(P81=0,"",(O81)/(P81)) | U81: =(S81)-(T81) -> 0 | V81: =IF(T81=0,"",(S81)/(T81)) | W81: =((((C81)+(G81))+(K81))+(O81))+(S81) -> 12897.29 | X81: =((((D81)+(H81))+(L81))+(P81))+(T81) -> 0 | Y81: =(W81)-(X81) -> 12897.29 | Z81: =IF(X81=0,"",(W81)/(X81))
B82: Total Other Income | C82: =(C80)+(C81) -> 28587.28 | D82: =(D80)+(D81) -> 0 | E82: =(C82)-(D82) -> 28587.28 | F82: =IF(D82=0,"",(C82)/(D82)) | G82: =(G80)+(G81) -> 0 | H82: =(H80)+(H81) -> 0 | I82: =(G82)-(H82) -> 0 | J82: =IF(H82=0,"",(G82)/(H82)) | K82: =(K80)+(K81) -> 0 | L82: =(L80)+(L81) -> 0 | M82: =(K82)-(L82) -> 0 | N82: =IF(L82=0,"",(K82)/(L82)) | O82: =(O80)+(O81) -> 0 | P82: =(P80)+(P81) -> 0 | Q82: =(O82)-(P82) -> 0 | R82: =IF(P82=0,"",(O82)/(P82)) | S82: =(S80)+(S81) -> 0 | T82: =(T80)+(T81) -> 0 | U82: =(S82)-(T82) -> 0 | V82: =IF(T82=0,"",(S82)/(T82)) | W82: =((((C82)+(G82))+(K82))+(O82))+(S82) -> 28587.28 | X82: =((((D82)+(H82))+(L82))+(P82))+(T82) -> 0 | Y82: =(W82)-(X82) -> 28587.28 | Z82: =IF(X82=0,"",(W82)/(X82))
B83: Other Expenses
B84: 6195 Late Fees | C84: =1800.15 -> 1800.15 | E84: =(C84)-(D84) -> 1800.15 | F84: =IF(D84=0,"",(C84)/(D84)) | G84: =33.68 -> 33.68 | I84: =(G84)-(H84) -> 33.68 | J84: =IF(H84=0,"",(G84)/(H84)) | M84: =(K84)-(L84) -> 0 | N84: =IF(L84=0,"",(K84)/(L84)) | Q84: =(O84)-(P84) -> 0 | R84: =IF(P84=0,"",(O84)/(P84)) | U84: =(S84)-(T84) -> 0 | V84: =IF(T84=0,"",(S84)/(T84)) | W84: =((((C84)+(G84))+(K84))+(O84))+(S84) -> 1833.83 | X84: =((((D84)+(H84))+(L84))+(P84))+(T84) -> 0 | Y84: =(W84)-(X84) -> 1833.83 | Z84: =IF(X84=0,"",(W84)/(X84))
B85: 7100 Interest Expense | C85: =69309.22 -> 69309.22 | D85: =50645.96 -> 50645.96 | E85: =(C85)-(D85) -> 18663.26 | F85: =IF(D85=0,"",(C85)/(D85)) -> 1.3685044 | I85: =(G85)-(H85) -> 0 | J85: =IF(H85=0,"",(G85)/(H85)) | M85: =(K85)-(L85) -> 0 | N85: =IF(L85=0,"",(K85)/(L85)) | Q85: =(O85)-(P85) -> 0 | R85: =IF(P85=0,"",(O85)/(P85)) | U85: =(S85)-(T85) -> 0 | V85: =IF(T85=0,"",(S85)/(T85)) | W85: =((((C85)+(G85))+(K85))+(O85))+(S85) -> 69309.22 | X85: =((((D85)+(H85))+(L85))+(P85))+(T85) -> 50645.96 | Y85: =(W85)-(X85) -> 18663.26 | Z85: =IF(X85=0,"",(W85)/(X85)) -> 1.3685044
B86: 7105 Interest Expense - Shareholder's Loan | C86: =28776.71 -> 28776.71 | D86: 26924.73 | E86: =(C86)-(D86) -> 1851.98 | F86: =IF(D86=0,"",(C86)/(D86)) -> 1.0687836 | I86: =(G86)-(H86) -> 0 | J86: =IF(H86=0,"",(G86)/(H86)) | M86: =(K86)-(L86) -> 0 | N86: =IF(L86=0,"",(K86)/(L86)) | Q86: =(O86)-(P86) -> 0 | R86: =IF(P86=0,"",(O86)/(P86)) | U86: =(S86)-(T86) -> 0 | V86: =IF(T86=0,"",(S86)/(T86)) | W86: =((((C86)+(G86))+(K86))+(O86))+(S86) -> 28776.71 | X86: =((((D86)+(H86))+(L86))+(P86))+(T86) -> 26924.73 | Y86: =(W86)-(X86) -> 1851.98 | Z86: =IF(X86=0,"",(W86)/(X86)) -> 1.0687836
B87: 7200 Depreciation Expense | C87: =13992.6 -> 13992.6 | D87: =10865.7 -> 10865.7 | E87: =(C87)-(D87) -> 3126.9 | F87: =IF(D87=0,"",(C87)/(D87)) -> 1.2877771 | I87: =(G87)-(H87) -> 0 | J87: =IF(H87=0,"",(G87)/(H87)) | M87: =(K87)-(L87) -> 0 | N87: =IF(L87=0,"",(K87)/(L87)) | Q87: =(O87)-(P87) -> 0 | R87: =IF(P87=0,"",(O87)/(P87)) | U87: =(S87)-(T87) -> 0 | V87: =IF(T87=0,"",(S87)/(T87)) | W87: =((((C87)+(G87))+(K87))+(O87))+(S87) -> 13992.6 | X87: =((((D87)+(H87))+(L87))+(P87))+(T87) -> 10865.7 | Y87: =(W87)-(X87) -> 3126.9 | Z87: =IF(X87=0,"",(W87)/(X87)) -> 1.2877771
B88: 7205 Amortization Expense | C88: =38966.4 -> 38966.4 | D88: =38966.4 -> 38966.4 | E88: =(C88)-(D88) -> 0 | F88: =IF(D88=0,"",(C88)/(D88)) -> 1 | I88: =(G88)-(H88) -> 0 | J88: =IF(H88=0,"",(G88)/(H88)) | M88: =(K88)-(L88) -> 0 | N88: =IF(L88=0,"",(K88)/(L88)) | Q88: =(O88)-(P88) -> 0 | R88: =IF(P88=0,"",(O88)/(P88)) | U88: =(S88)-(T88) -> 0 | V88: =IF(T88=0,"",(S88)/(T88)) | W88: =((((C88)+(G88))+(K88))+(O88))+(S88) -> 38966.4 | X88: =((((D88)+(H88))+(L88))+(P88))+(T88) -> 38966.4 | Y88: =(W88)-(X88) -> 0 | Z88: =IF(X88=0,"",(W88)/(X88)) -> 1
B89: Total Other Expenses | C89: =((((C84)+(C85))+(C86))+(C87))+(C88) -> 152845.08 | D89: =((((D84)+(D85))+(D86))+(D87))+(D88) -> 127402.79 | E89: =(C89)-(D89) -> 25442.29 | F89: =IF(D89=0,"",(C89)/(D89)) -> 1.1996996 | G89: =((((G84)+(G85))+(G86))+(G87))+(G88) -> 33.68 | H89: =((((H84)+(H85))+(H86))+(H87))+(H88) -> 0 | I89: =(G89)-(H89) -> 33.68 | J89: =IF(H89=0,"",(G89)/(H89)) | K89: =((((K84)+(K85))+(K86))+(K87))+(K88) -> 0 | L89: =((((L84)+(L85))+(L86))+(L87))+(L88) -> 0 | M89: =(K89)-(L89) -> 0 | N89: =IF(L89=0,"",(K89)/(L89)) | O89: =((((O84)+(O85))+(O86))+(O87))+(O88) -> 0 | P89: =((((P84)+(P85))+(P86))+(P87))+(P88) -> 0 | Q89: =(O89)-(P89) -> 0 | R89: =IF(P89=0,"",(O89)/(P89)) | S89: =((((S84)+(S85))+(S86))+(S87))+(S88) -> 0 | T89: =((((T84)+(T85))+(T86))+(T87))+(T88) -> 0 | U89: =(S89)-(T89) -> 0 | V89: =IF(T89=0,"",(S89)/(T89)) | W89: =((((C89)+(G89))+(K89))+(O89))+(S89) -> 152878.76 | X89: =((((D89)+(H89))+(L89))+(P89))+(T89) -> 127402.79 | Y89: =(W89)-(X89) -> 25475.97 | Z89: =IF(X89=0,"",(W89)/(X89)) -> 1.199964
B90: Net Other Income | C90: =(C82)-(C89) -> -124257.8 | D90: =(D82)-(D89) -> -127402.79 | E90: =(C90)-(D90) -> 3144.99 | F90: =IF(D90=0,"",(C90)/(D90)) -> 0.97531459 | G90: =(G82)-(G89) -> -33.68 | H90: =(H82)-(H89) -> 0 | I90: =(G90)-(H90) -> -33.68 | J90: =IF(H90=0,"",(G90)/(H90)) | K90: =(K82)-(K89) -> 0 | L90: =(L82)-(L89) -> 0 | M90: =(K90)-(L90) -> 0 | N90: =IF(L90=0,"",(K90)/(L90)) | O90: =(O82)-(O89) -> 0 | P90: =(P82)-(P89) -> 0 | Q90: =(O90)-(P90) -> 0 | R90: =IF(P90=0,"",(O90)/(P90)) | S90: =(S82)-(S89) -> 0 | T90: =(T82)-(T89) -> 0 | U90: =(S90)-(T90) -> 0 | V90: =IF(T90=0,"",(S90)/(T90)) | W90: =((((C90)+(G90))+(K90))+(O90))+(S90) -> -124291.48 | X90: =((((D90)+(H90))+(L90))+(P90))+(T90) -> -127402.79 | Y90: =(W90)-(X90) -> 3111.31 | Z90: =IF(X90=0,"",(W90)/(X90)) -> 0.97557895
B91: Net Income | C91: =(C78)+(C90) -> -355639.31 | D91: =(D78)+(D90) -> -354230.39 | E91: =(C91)-(D91) -> -1408.92 | F91: =IF(D91=0,"",(C91)/(D91)) -> 1.0039774 | G91: =(G78)+(G90) -> 197219.91 | H91: =(H78)+(H90) -> 177705.15 | I91: =(G91)-(H91) -> 19514.76 | J91: =IF(H91=0,"",(G91)/(H91)) -> 1.1098154 | K91: =(K78)+(K90) -> -3208.71 | L91: =(L78)+(L90) -> 18314.19 | M91: =(K91)-(L91) -> -21522.9 | N91: =IF(L91=0,"",(K91)/(L91)) -> -0.17520349 | O91: =(O78)+(O90) -> 71899.96 | P91: =(P78)+(P90) -> 150865.98 | Q91: =(O91)-(P91) -> -78966.02 | R91: =IF(P91=0,"",(O91)/(P91)) -> 0.47658167 | S91: =(S78)+(S90) -> -54016.37 | T91: =(T78)+(T90) -> 181497.54 | U91: =(S91)-(T91) -> -235513.91 | V91: =IF(T91=0,"",(S91)/(T91)) -> -0.29761489 | W91: =((((C91)+(G91))+(K91))+(O91))+(S91) -> -143744.52 | X91: =((((D91)+(H91))+(L91))+(P91))+(T91) -> 174152.47 | Y91: =(W91)-(X91) -> -317896.99 | Z91: =IF(X91=0,"",(W91)/(X91)) -> -0.82539467
B93: Net Operating Income + Other Income = EBITDA | C93: =+C78+C82 -> -202794.23 | D93: =+D78+D82 -> -226827.6 | E93: =+E78+E82 -> 24033.37 | F93: =C93/D93 -> 0.89404565 | G93: =+G78+G82 -> 197253.59 | H93: =+H78+H82 -> 177705.15 | I93: =+I78+I82 -> 19548.44 | J93: =G93/H93 -> 1.1100049 | K93: =+K78+K82 -> -3208.71 | L93: =+L78+L82 -> 18314.19 | M93: =+M78+M82 -> -21522.9 | N93: =K93/L93 -> -0.17520349 | O93: =+O78+O82 -> 71899.96 | P93: =+P78+P82 -> 150865.98 | Q93: =+Q78+Q82 -> -78966.02 | R93: =O93/P93 -> 0.47658167 | S93: =+S78+S82 -> -54016.37 | T93: =+T78+T82 -> 181497.54 | U93: =+U78+U82 -> -235513.91 | V93: =S93/T93 -> -0.29761489 | W93: =+W78+W82 -> 9134.24 | X93: =+X78+X82 -> 301555.26 | Y93: =+Y78+Y82 -> -292421.02 | Z93: =W93/X93 -> 0.030290435
B95: Less: Depreciation & Amortization | C95: =C87+C88 -> 52959 | D95: =D87+D88 -> 49832.1 | E95: =E87+E88 -> 3126.9 | F95: =C95/D95 -> 1.0627487 | G95: =G87+G88 -> 0 | H95: =H87+H88 -> 0 | I95: =I87+I88 -> 0 | J95: 0 | K95: =K87+K88 -> 0 | L95: =L87+L88 -> 0 | M95: =M87+M88 -> 0 | N95: 0 | O95: =O87+O88 -> 0 | P95: =P87+P88 -> 0 | Q95: =Q87+Q88 -> 0 | R95: 0 | S95: =S87+S88 -> 0 | T95: =T87+T88 -> 0 | U95: =U87+U88 -> 0 | V95: 0 | W95: =W87+W88 -> 52959 | X95: =X87+X88 -> 49832.1 | Y95: =Y87+Y88 -> 3126.9 | Z95: 0
B96: EBIT (Operating Profit) | C96: =++C93-C95 -> -255753.23 | D96: =++D93-D95 -> -276659.7 | E96: =++E93-E95 -> 20906.47 | F96: =C96/D96 -> 0.92443254 | G96: =++G93-G95 -> 197253.59 | H96: =++H93-H95 -> 177705.15 | I96: =++I93-I95 -> 19548.44 | J96: =G96/H96 -> 1.1100049 | K96: =++K93-K95 -> -3208.71 | L96: =++L93-L95 -> 18314.19 | M96: =++M93-M95 -> -21522.9 | N96: =K96/L96 -> -0.17520349 | O96: =++O93-O95 -> 71899.96 | P96: =++P93-P95 -> 150865.98 | Q96: =++Q93-Q95 -> -78966.02 | R96: =O96/P96 -> 0.47658167 | S96: =++S93-S95 -> -54016.37 | T96: =++T93-T95 -> 181497.54 | U96: =++U93-U95 -> -235513.91 | V96: =S96/T96 -> -0.29761489 | W96: =++W93-W95 -> -43824.76 | X96: =++X93-X95 -> 251723.16 | Y96: =++Y93-Y95 -> -295547.92 | Z96: =W96/X96 -> -0.17409904
B98: Less: Interest Expense + Late Fees | C98: =++C85+C86+C84 -> 99886.08 | D98: =++D85+D86+D84 -> 77570.69 | E98: =++E85+E86+E84 -> 22315.39 | F98: =C98/D98 -> 1.2876781 | G98: =++G85+G86+G84 -> 33.68 | H98: =++H85+H86+H84 -> 0 | I98: =++I85+I86+I84 -> 33.68 | J98: 0 | K98: =++K85+K86+K84 -> 0 | L98: =++L85+L86+L84 -> 0 | M98: =++M85+M86+M84 -> 0 | N98: 0 | O98: =++O85+O86+O84 -> 0 | P98: =++P85+P86+P84 -> 0 | Q98: =++Q85+Q86+Q84 -> 0 | R98: 0 | S98: =++S85+S86+S84 -> 0 | T98: =++T85+T86+T84 -> 0 | U98: =++U85+U86+U84 -> 0 | V98: 0 | W98: =++W85+W86+W84 -> 99919.76 | X98: =++X85+X86+X84 -> 77570.69 | Y98: =++Y85+Y86+Y84 -> 22349.07 | Z98: 0
B99: Profit Before Tax (PBT) | C99: =++C96-C98 -> -355639.31 | D99: =++D96-D98 -> -354230.39 | E99: =++E96-E98 -> -1408.92 | F99: =C99/D99 -> 1.0039774 | G99: =++G96-G98 -> 197219.91 | H99: =++H96-H98 -> 177705.15 | I99: =++I96-I98 -> 19514.76 | J99: =G99/H99 -> 1.1098154 | K99: =++K96-K98 -> -3208.71 | L99: =++L96-L98 -> 18314.19 | M99: =++M96-M98 -> -21522.9 | N99: =K99/L99 -> -0.17520349 | O99: =++O96-O98 -> 71899.96 | P99: =++P96-P98 -> 150865.98 | Q99: =++Q96-Q98 -> -78966.02 | R99: =O99/P99 -> 0.47658167 | S99: =++S96-S98 -> -54016.37 | T99: =++T96-T98 -> 181497.54 | U99: =++U96-U98 -> -235513.91 | V99: =S99/T99 -> -0.29761489 | W99: =++W96-W98 -> -143744.52 | X99: =++X96-X98 -> 174152.47 | Y99: =++Y96-Y98 -> -317896.99 | Z99: =W99/X99 -> -0.82539467
B101: Less: Tax
B102: Profit After Tax (PAT) | C102: =++C99-C101 -> -355639.31 | D102: =++D99-D101 -> -354230.39 | E102: =++E99-E101 -> -1408.92 | F102: =C102/D102 -> 1.0039774 | G102: =++G99-G101 -> 197219.91 | H102: =++H99-H101 -> 177705.15 | I102: =++I99-I101 -> 19514.76 | J102: =G102/H102 -> 1.1098154 | K102: =++K99-K101 -> -3208.71 | L102: =++L99-L101 -> 18314.19 | M102: =++M99-M101 -> -21522.9 | N102: =K102/L102 -> -0.17520349 | O102: =++O99-O101 -> 71899.96 | P102: =++P99-P101 -> 150865.98 | Q102: =++Q99-Q101 -> -78966.02 | R102: =O102/P102 -> 0.47658167 | S102: =++S99-S101 -> -54016.37 | T102: =++T99-T101 -> 181497.54 | U102: =++U99-U101 -> -235513.91 | V102: =S102/T102 -> -0.29761489 | W102: =++W99-W101 -> -143744.52 | X102: =++X99-X101 -> 174152.47 | Y102: =++Y99-Y101 -> -317896.99 | Z102: =W102/X102 -> -0.82539467
B105: Check Point | C105: =++C102-C91 -> 0 | D105: =++D102-D91 -> 0 | E105: =++E102-E91 -> 3.2741809e-11 | F105: =++F102-F91 -> 0 | G105: =++G102-G91 -> 0 | H105: =++H102-H91 -> 0 | I105: =++I102-I91 -> 0 | J105: =++J102-J91 -> 0 | ... Z105: =++Z102-Z91 -> 0

Sheet Statement of Cash Flows
B2: =Cover!A3 -> Pacific Nexus | G2: Home
B3: Statement of CashFlow | G3: Balance Sheet
B4: =Index!A2 -> Period Ending 03/31/2026 | G4: Profit & Loss
G5: PL-Division (YTD)
C6: Jan 26 | D6: Feb 26 | E6: Mar 26 | F6: Total | G6: PL-Division (Month)
B7: OPERATING ACTIVITIES
B8: Net Income | C8: -58177.41 | D8: -60887.48 | E8: -24679.63 | F8: =C8+D8+E8 -> -143744.52
B9: Adjustments to reconcile Net Income to Net Cash provided by operations:
B10: 1100 Accounts Receivable | C10: -33488.69 | D10: 47128.97 | E10: -10283.04 | F10: =C10+D10+E10 -> 3357.24
B11: 1300 Prepaid Expenses | C11: -2161.08 | D11: -4393.25 | E11: -1830.66 | F11: =C11+D11+E11 -> -8384.99
B12: 1380 Accrued Income | C12: 62127.79 | D12: -42283.58 | E12: -12535.36 | F12: =C12+D12+E12 -> 7308.85
B13: 1430 Computer & Office Equipment:Accumulated Depreciation - Computer & Office Equipment | C13: 2464.74 | D13: 2464.74 | E13: 2588.34 | F13: =C13+D13+E13 -> 7517.82
B14: 1440 Leasehold Improvements:Accumulated Depreciation - Leasehold Improvements | C14: 302.12 | D14: 302.12 | E14: 302.12 | F14: =C14+D14+E14 -> 906.36
B15: 1510 Goodwill:Accumulated Amortization - Goodwill | C15: 12425.23 | D15: 12425.23 | E15: 12425.23 | F15: =C15+D15+E15 -> 37275.69
B16: 1520 Loan Closing Costs:Accumulated Amortization - Loan Closing Costs | C16: 563.57 | D16: 563.57 | E16: 563.57 | F16: =C16+D16+E16 -> 1690.71
B17: 1545 Purchase Cost - NS Printing:Accumulated Amortization - Purchase Cost - NS Printing | C17: 1856.14 | D17: 1856.14 | E17: 1856.14 | F17: =C17+D17+E17 -> 5568.42
B18: 2000 Accounts Payable | C18: -16501.2 | D18: -1577.56 | E18: 10613.91 | F18: =C18+D18+E18 -> -7464.85
B19: 2105 AMEX #1000 | C19: -17176.96 | D19: 27655.28 | E19: 27660.36 | F19: =C19+D19+E19 -> 38138.68
B20: 2110 AMEX #1003 | C20: -63.25 | F20: =C20+D20+E20 -> -63.25
B21: 2115 VISA #7547 | C21: 6300.78 | D21: 1117.79 | E21: -6640.28 | F21: =C21+D21+E21 -> 778.29
B22: 2205 Accrued Expenses | C22: 30429.21 | D22: 16320.59 | E22: 13777.62 | F22: =C22+D22+E22 -> 60527.42
B23: 2215 Accrued Interest on Shareholder's Loan - Zaheer | C23: 9720.17 | D23: 8887.16 | E23: 10169.38 | F23: =C23+D23+E23 -> 28776.71
B24: 2241 Payroll liabilities:Payroll Clearing | C24: 0 | D24: 0 | E24: 2494.31 | F24: =C24+D24+E24 -> 2494.31
B25: 2243 Payroll liabilities:Health Deduction payable | C25: -2590.17 | D25: -2349.51 | E25: -1031.77 | F25: =C25+D25+E25 -> -5971.45
B26: 2244 Payroll liabilities:401K Withholding | C26: -4704.51 | D26: 778.96 | E26: -3070.4 | F26: =C26+D26+E26 -> -6995.95
B27: 2250 Intuit Loan | C27: 2773.08 | F27: =C27+D27+E27 -> 2773.08
B28: 2300 California Department of Tax and Fee Administration Payable | C28: 7073.81 | D28: -837.86 | E28: 10872.27 | F28: =C28+D28+E28 -> 17108.22
B29: 2350 Overdraft - CNB Checking #2640 | C29: -3000 | F29: =C29+D29+E29 -> -3000
B30: Total for Adjustments to reconcile Net Income to Net Cash provided by operations: | C30: =C9+C10+C11+C12+C13+C14+C15+C16+C17+C18+C19+C20+C21+C22+C23+C24+C25+C26+C27+C28+C29 -> 56350.78 | D30: =D9+D10+D11+D12+D13+D14+D15+D16+D17+D18+D19+D20+D21+D22+D23+D24+D25+D26+D27+D28+D29 -> 68058.79 | E30: =E9+E10+E11+E12+E13+E14+E15+E16+E17+E18+E19+E20+E21+E22+E23+E24+E25+E26+E27+E28+E29 -> 57931.74 | F30: =C30+D30+E30 -> 182341.31
B31: Net cash provided by operating activities | C31: =C8+C30 -> -1826.63 | D31: =D8+D30 -> 7171.31 | E31: =E8+E30 -> 33252.11 | F31: =C31+D31+E31 -> 38596.79
B32: INVESTING ACTIVITIES
B33: 1425 Computer & Office Equipment | D33: -7417.45 | E33: -8725 | F33: =C33+D33+E33 -> -16142.45
B34: 1540 Purchase Cost - NS Printing | C34: -16250 | F34: =C34+D34+E34 -> -16250
B35: 1600 Security Deposit | C35: -3229.82 | F35: =C35+D35+E35 -> -3229.82
B36: Net cash provided by investing activities | C36: =C33+C34+C35 -> -19479.82 | D36: =D33+D34+D35 -> -7417.45 | E36: =E33+E34+E35 -> -8725 | F36: =C36+D36+E36 -> -35622.27
B37: FINANCING ACTIVITIES
B38: 2515 AMEX Loan #3344 | C38: -5833.34 | D38: -5833.34 | E38: -5833.34 | F38: =C38+D38+E38 -> -17500.02
B39: 2535 Ricoh Lease - 5120 | C39: -1250 | D39: -1250 | E39: -1250 | F39: =C39+D39+E39 -> -3750
B40: 2705 Shareholder Loan - Zaheer | C40: 50350 | D40: -15273.12 | E40: 57425.26 | F40: =C40+D40+E40 -> 92502.14
B41: Net cash provided by financing activities | C41: =C38+C39+C40 -> 43266.66 | D41: =D38+D39+D40 -> -22356.46 | E41: =E38+E39+E40 -> 50341.92 | F41: =C41+D41+E41 -> 71252.12
B42: NET CASH INCREASE FOR PERIOD | C42: =C31+C36+C41 -> 21960.21 | D42: =D31+D36+D41 -> -22602.6 | E42: =E31+E36+E41 -> 74869.03 | F42: =C42+D42+E42 -> 74226.64

Sheet Profit and Loss - YOY Summary
B2: =Cover!A3 -> Pacific Nexus
B3: YOY Revenue and Net Income Comaprision
C4: 2024 | E4: 2025 | G4: 2026 | I4: 2025 vs 2026 Change | K4: 2025 vs 2026 Change
B5: Month | C5: Revenue | D5: Profit/Loss | E5: Revenue | F5: Profit/Loss | G5: Revenue | H5: Profit/Loss | I5: Revenue | J5: % Change | K5: Profit/Loss | L5: % Change
B6: January | C6: ='Profit and Loss-MOM'!B$9 -> 0 | D6: ='Profit and Loss-MOM'!B$96 -> 0 | E6: ='Profit and Loss-MOM'!N$9 -> 206276.98 | F6: ='Profit and Loss-MOM'!N$96 -> -97938.46 | G6: ='Profit and Loss-MOM'!Z$9 -> 204784.56 | H6: =+-58177.41 -> -58177.41 | I6: =G6-E6 -> -1492.42 | J6: =I6/E6 -> -0.0072350293 | K6: =H6-F6 -> 39761.05 | L6: =F6/H6 -> 1.6834448
B7: February | C7: ='Profit and Loss-MOM'!C$9 -> 0 | D7: ='Profit and Loss-MOM'!C$96 -> 0 | E7: ='Profit and Loss-MOM'!O$9 -> 176404.39 | F7: ='Profit and Loss-MOM'!O$96 -> -99539.45 | G7: 220946 | H7: =+-60887.48 -> -60887.48 | I7: =G7-E7 -> 44541.61 | J7: =I7/E7 -> 0.25249717 | K7: =H7-F7 -> 38651.97 | L7: =F7/H7 -> 1.6348098
B8: March | C8: ='Profit and Loss-MOM'!D$9 -> 160800 | D8: ='Profit and Loss-MOM'!D$96 -> -15181.78 | E8: ='Profit and Loss-MOM'!P$9 -> 132652.14 | F8: ='Profit and Loss-MOM'!P$96 -> -169715 | G8: 288667.86 | H8: =+-24679.53 -> -24679.53 | I8: =G8-E8 -> 156015.72 | J8: =I8/E8 -> 1.1761267 | K8: =H8-F8 -> 145035.47 | L8: =F8/H8 -> 6.8767517
B9: April | C9: ='Profit and Loss-MOM'!E$9 -> 86405.81 | D9: ='Profit and Loss-MOM'!E$96 -> -231915.75 | E9: ='Profit and Loss-MOM'!Q$9 -> 334731.7 | F9: ='Profit and Loss-MOM'!Q$96 -> 10818.48
B10: May | C10: ='Profit and Loss-MOM'!F$9 -> 281575.41 | D10: ='Profit and Loss-MOM'!F$96 -> 55988.31 | E10: ='Profit and Loss-MOM'!R$9 -> 157416.55 | F10: ='Profit and Loss-MOM'!R$96 -> -120325.33
B11: June | C11: ='Profit and Loss-MOM'!G$9 -> 205524.58 | D11: ='Profit and Loss-MOM'!G$96 -> -76409.54 | E11: ='Profit and Loss-MOM'!S$9 -> 285232.66 | F11: ='Profit and Loss-MOM'!S$96 -> 59415.3
B12: July | C12: ='Profit and Loss-MOM'!H$9 -> 52713.5 | D12: ='Profit and Loss-MOM'!H$96 -> -193012.04 | E12: ='Profit and Loss-MOM'!T$9 -> 233288.8 | F12: ='Profit and Loss-MOM'!T$96 -> -73144.63
B13: August | C13: ='Profit and Loss-MOM'!I$9 -> 268575.34 | D13: ='Profit and Loss-MOM'!I$96 -> 21063.55 | E13: ='Profit and Loss-MOM'!U$9 -> 203671.25 | F13: ='Profit and Loss-MOM'!U$96 -> -28977.16
B14: September | C14: ='Profit and Loss-MOM'!J$9 -> 273942.93 | D14: ='Profit and Loss-MOM'!J$96 -> 40140.09 | E14: ='Profit and Loss-MOM'!V$9 -> 264826.99 | F14: ='Profit and Loss-MOM'!V$96 -> 49447.84
B15: October | C15: ='Profit and Loss-MOM'!K$9 -> 92722.64 | D15: ='Profit and Loss-MOM'!K$96 -> -118294.76 | E15: ='Profit and Loss-MOM'!W$9 -> 185366.07 | F15: ='Profit and Loss-MOM'!W$96 -> -61277.23
B16: November | C16: ='Profit and Loss-MOM'!L$9 -> 200189.59 | D16: ='Profit and Loss-MOM'!L$96 -> -19908.13 | E16: ='Profit and Loss-MOM'!X$9 -> 179961.35 | F16: ='Profit and Loss-MOM'!X$96 -> -11673.96
B17: December | C17: ='Profit and Loss-MOM'!M$9 -> 259565.22 | D17: ='Profit and Loss-MOM'!M$96 -> -151618.81 | E17: ='Profit and Loss-MOM'!Y$9 -> 352608.23 | F17: 91518.46
B19: Total | C19: =SUM(C6:C17) -> 1882015 | D19: =SUM(D6:D17) -> -689148.86 | E19: =SUM(E6:E17) -> 2712437.1 | F19: =SUM(F6:F17) -> -451391.14 | G19: =SUM(G6:G17) -> 714398.42 | H19: =SUM(H6:H17) -> -143744.42 | I19: =SUM(I6:I17) -> 199064.91 | J19: =SUM(J6:J17) -> 1.4213888 | ... L19: =SUM(L6:L17) -> 10.195006

Sheet Profit and Loss - YOY Detail
A1: Profit and Loss
A2: Pacific Media Holdings
A3: January 1-March 31, 2026
A5: Distribution account | B5: January 2026 | F5: February 2026 | J5: March 2026 | N5: Total
B6: CURRENT | C6: January 2025 (PY) | D6: $ Change (PY) | E6: % Change (PY) | F6: CURRENT | G6: February 2025 (PY) | H6: $ Change (PY) | I6: % Change (PY) | J6: CURRENT | K6: Mar 2025 (PY) | L6: $ Change (PY) | M6: % Change (PY) | N6: Jan 1 - Feb 28 2026 | O6: Jan 1 - Feb 28 2025 (PY) | P6: $ Change (PY) | Q6: % Change (PY)
A7: Income
A8: 4005 Sales Revenue | B8: 206737.15 | C8: 207696.48 | D8: =(B8-C8) -> -959.33 | E8: =IFERROR((((B8-C8)/IF(C8<0,-1*C8,C8))*100),"") -> -0.46189035 | F8: 221461.62 | G8: 177054.69 | H8: =(F8-G8) -> 44406.93 | I8: =IFERROR((((F8-G8)/IF(G8<0,-1*G8,G8))*100),"") -> 25.080911 | J8: 289563.38 | K8: 133247.2 | L8: =(J8-K8) -> 156316.18 | M8: =IFERROR((((J8-K8)/IF(K8<0,-1*K8,K8))*100),"") -> 117.31292 | N8: =B8+F8+J8 -> 717762.15 | O8: =C8+G8+K8 -> 517998.37 | P8: =(N8-O8) -> 199763.78 | Q8: =IFERROR((((N8-O8)/IF(O8<0,-1*O8,O8))*100),"") -> 38.564558
A9: 4010 Sales Discount | B9: -1952.59 | C9: -1419.5 | D9: =(B9-C9) -> -533.09 | E9: =IFERROR((((B9-C9)/IF(C9<0,-1*C9,C9))*100),"") -> -37.554773 | F9: -515.62 | G9: -650.3 | H9: =(F9-G9) -> 134.68 | I9: =IFERROR((((F9-G9)/IF(G9<0,-1*G9,G9))*100),"") -> 20.710441 | J9: -895.52 | K9: -595.06 | L9: =(J9-K9) -> -300.46 | M9: =IFERROR((((J9-K9)/IF(K9<0,-1*K9,K9))*100),"") -> -50.492387 | N9: =B9+F9+J9 -> -3363.73 | O9: =C9+G9+K9 -> -2664.86 | P9: =(N9-O9) -> -698.87 | Q9: =IFERROR((((N9-O9)/IF(O9<0,-1*O9,O9))*100),"") -> -26.225393
A10: Total for Income | B10: =B8+B9 -> 204784.56 | C10: =C8+C9 -> 206276.98 | D10: =(B10-C10) -> -1492.42 | E10: =IFERROR((((B10-C10)/IF(C10<0,-1*C10,C10))*100),"") -> -0.72350293 | F10: =F8+F9 -> 220946 | G10: =G8+G9 -> 176404.39 | H10: =(F10-G10) -> 44541.61 | I10: =IFERROR((((F10-G10)/IF(G10<0,-1*G10,G10))*100),"") -> 25.249717 | J10: =J8+J9 -> 288667.86 | K10: =K8+K9 -> 132652.14 | L10: =(J10-K10) -> 156015.72 | M10: =IFERROR((((J10-K10)/IF(K10<0,-1*K10,K10))*100),"") -> 117.61267 | N10: =B10+F10+J10 -> 714398.42 | O10: =C10+G10+K10 -> 515333.51 | P10: =(N10-O10) -> 199064.91 | Q10: =IFERROR((((N10-O10)/IF(O10<0,-1*O10,O10))*100),"") -> 38.628365
A11: Cost of Goods Sold
A12: 5005 Cost of Materials | B12: 29209.55 | C12: 28964.88 | D12: =(B12-C12) -> 244.67 | E12: =IFERROR((((B12-C12)/IF(C12<0,-1*C12,C12))*100),"") -> 0.84471263 | F12: 23283.51 | G12: 20756.25 | H12: =(F12-G12) -> 2527.26 | I12: =IFERROR((((F12-G12)/IF(G12<0,-1*G12,G12))*100),"") -> 12.175899 | J12: 34847.91 | K12: 58522.3 | L12: =(J12-K12) -> -23674.39 | M12: =IFERROR((((J12-K12)/IF(K12<0,-1*K12,K12))*100),"") -> -40.453622 | N12: =B12+F12+J12 -> 87340.97 | O12: =C12+G12+K12 -> 108243.43 | P12: =(N12-O12) -> -20902.46 | Q12: =IFERROR((((N12-O12)/IF(O12<0,-1*O12,O12))*100),"") -> -19.310604
A13: 5010 Cost of Labor | B13: 0 | C13: 0 | D13: =(B13-C13) -> 0 | F13: 0 | G13: 0 | H13: =(F13-G13) -> 0 | J13: 0 | K13: 0 | L13: =(J13-K13) -> 0 | N13: =B13+F13+J13 -> 0 | O13: =C13+G13+K13 -> 0 | P13: =(N13-O13) -> 0
A14: 5015 Travels and Meals | C14: 671.42 | D14: =(B14-C14) -> -671.42 | E14: =IFERROR((((B14-C14)/IF(C14<0,-1*C14,C14))*100),"") -> -100 | G14: 1342.1 | H14: =(F14-G14) -> -1342.1 | I14: =IFERROR((((F14-G14)/IF(G14<0,-1*G14,G14))*100),"") -> -100 | J14: 0 | K14: 1915.16 | L14: =(J14-K14) -> -1915.16 | M14: =IFERROR((((J14-K14)/IF(K14<0,-1*K14,K14))*100),"") -> -100 | N14: =B14+F14+J14 -> 0 | O14: =C14+G14+K14 -> 3928.68 | P14: =(N14-O14) -> -3928.68 | Q14: =IFERROR((((N14-O14)/IF(O14<0,-1*O14,O14))*100),"") -> -100
A15: 5065 Wages | B15: 90285.21 | C15: 73276.92 | D15: =(B15-C15) -> 17008.29 | E15: =IFERROR((((B15-C15)/IF(C15<0,-1*C15,C15))*100),"") -> 23.210978 | F15: 86016.39 | G15: 61729.67 | H15: =(F15-G15) -> 24286.72 | I15: =IFERROR((((F15-G15)/IF(G15<0,-1*G15,G15))*100),"") -> 39.343674 | J15: 97713.83 | K15: 74367.5 | L15: =(J15-K15) -> 23346.33 | M15: =IFERROR((((J15-K15)/IF(K15<0,-1*K15,K15))*100),"") -> 31.393189 | N15: =B15+F15+J15 -> 274015.43 | O15: =C15+G15+K15 -> 209374.09 | P15: =(N15-O15) -> 64641.34 | Q15: =IFERROR((((N15-O15)/IF(O15<0,-1*O15,O15))*100),"") -> 30.87361
A16: 5070 Payroll Tax Expense | B16: 9791.27 | C16: 7193.64 | D16: =(B16-C16) -> 2597.63 | E16: =IFERROR((((B16-C16)/IF(C16<0,-1*C16,C16))*100),"") -> 36.110092 | F16: 7407.13 | G16: 4363.63 | H16: =(F16-G16) -> 3043.5 | I16: =IFERROR((((F16-G16)/IF(G16<0,-1*G16,G16))*100),"") -> 69.746977 | J16: 8070.23 | K16: 5305.6 | L16: =(J16-K16) -> 2764.63 | M16: =IFERROR((((J16-K16)/IF(K16<0,-1*K16,K16))*100),"") -> 52.107773 | N16: =B16+F16+J16 -> 25268.63 | O16: =C16+G16+K16 -> 16862.87 | P16: =(N16-O16) -> 8405.76 | Q16: =IFERROR((((N16-O16)/IF(O16<0,-1*O16,O16))*100),"") -> 49.847742
A17: 5075 Employee Benefits | B17: 3351.49 | C17: 2815 | D17: =(B17-C17) -> 536.49 | E17: =IFERROR((((B17-C17)/IF(C17<0,-1*C17,C17))*100),"") -> 19.058259 | F17: 3877.27 | G17: 2712.55 | H17: =(F17-G17) -> 1164.72 | I17: =IFERROR((((F17-G17)/IF(G17<0,-1*G17,G17))*100),"") -> 42.938195 | J17: 4829.13 | K17: 2996.17 | L17: =(J17-K17) -> 1832.96 | M17: =IFERROR((((J17-K17)/IF(K17<0,-1*K17,K17))*100),"") -> 61.176769 | N17: =B17+F17+J17 -> 12057.89 | O17: =C17+G17+K17 -> 8523.72 | P17: =(N17-O17) -> 3534.17 | Q17: =IFERROR((((N17-O17)/IF(O17<0,-1*O17,O17))*100),"") -> 41.462765
A18: Total for Cost of Goods Sold | B18: =B12+B13+B14+B15+B16+B17 -> 132637.52 | C18: =C12+C13+C14+C15+C16+C17 -> 112921.86 | D18: =(B18-C18) -> 19715.66 | E18: =IFERROR((((B18-C18)/IF(C18<0,-1*C18,C18))*100),"") -> 17.45956 | F18: =F12+F13+F14+F15+F16+F17 -> 120584.3 | G18: =G12+G13+G14+G15+G16+G17 -> 90904.2 | H18: =(F18-G18) -> 29680.1 | I18: =IFERROR((((F18-G18)/IF(G18<0,-1*G18,G18))*100),"") -> 32.649867 | J18: =J12+J13+J14+J15+J16+J17 -> 145461.1 | K18: =K12+K13+K14+K15+K16+K17 -> 143106.73 | L18: =(J18-K18) -> 2354.37 | M18: =IFERROR((((J18-K18)/IF(K18<0,-1*K18,K18))*100),"") -> 1.6451847 | N18: =B18+F18+J18 -> 398682.92 | O18: =C18+G18+K18 -> 346932.79 | P18: =(N18-O18) -> 51750.13 | Q18: =IFERROR((((N18-O18)/IF(O18<0,-1*O18,O18))*100),"") -> 14.916471
A19: Gross Profit | B19: =B10-B18 -> 72147.04 | C19: =C10-C18 -> 93355.12 | D19: =(B19-C19) -> -21208.08 | E19: =IFERROR((((B19-C19)/IF(C19<0,-1*C19,C19))*100),"") -> -22.71764 | F19: =F10-F18 -> 100361.7 | G19: =G10-G18 -> 85500.19 | H19: =(F19-G19) -> 14861.51 | I19: =IFERROR((((F19-G19)/IF(G19<0,-1*G19,G19))*100),"") -> 17.381844 | J19: =J10-J18 -> 143206.76 | K19: =K10-K18 -> -10454.59 | L19: =(J19-K19) -> 153661.35 | M19: =IFERROR((((J19-K19)/IF(K19<0,-1*K19,K19))*100),"") -> 1469.798 | N19: =B19+F19+J19 -> 315715.5 | O19: =C19+G19+K19 -> 168400.72 | P19: =(N19-O19) -> 147314.78 | Q19: =IFERROR((((N19-O19)/IF(O19<0,-1*O19,O19))*100),"") -> 87.478711
A20: Expenses
A21: 6100 Payroll Expenses
A22: 6105 Salaries & Wages | B22: 23690.14 | C22: 21679.69 | D22: =(B22-C22) -> 2010.45 | E22: =IFERROR((((B22-C22)/IF(C22<0,-1*C22,C22))*100),"") -> 9.273426 | F22: 19384.61 | G22: 19512.65 | H22: =(F22-G22) -> -128.04 | I22: =IFERROR((((F22-G22)/IF(G22<0,-1*G22,G22))*100),"") -> -0.6561897 | J22: 21461.53 | K22: 27867.34 | L22: =(J22-K22) -> -6405.81 | M22: =IFERROR((((J22-K22)/IF(K22<0,-1*K22,K22))*100),"") -> -22.986801 | N22: =B22+F22+J22 -> 64536.28 | O22: =C22+G22+K22 -> 69059.68 | P22: =(N22-O22) -> -4523.4 | Q22: =IFERROR((((N22-O22)/IF(O22<0,-1*O22,O22))*100),"") -> -6.5499869
A23: 6115 Payroll Tax Expense | B23: 1899.81 | C23: 2117.37 | D23: =(B23-C23) -> -217.56 | E23: =IFERROR((((B23-C23)/IF(C23<0,-1*C23,C23))*100),"") -> -10.275011 | F23: 1358.66 | G23: 1475.72 | H23: =(F23-G23) -> -117.06 | I23: =IFERROR((((F23-G23)/IF(G23<0,-1*G23,G23))*100),"") -> -7.9323991 | J23: 3998.69 | K23: 2273.97 | L23: =(J23-K23) -> 1724.72 | M23: =IFERROR((((J23-K23)/IF(K23<0,-1*K23,K23))*100),"") -> 75.846207 | N23: =B23+F23+J23 -> 7257.16 | O23: =C23+G23+K23 -> 5867.06 | P23: =(N23-O23) -> 1390.1 | Q23: =IFERROR((((N23-O23)/IF(O23<0,-1*O23,O23))*100),"") -> 23.693298
A24: 6120 Employee Benefits | B24: 525.64 | C24: 907.69 | D24: =(B24-C24) -> -382.05 | E24: =IFERROR((((B24-C24)/IF(C24<0,-1*C24,C24))*100),"") -> -42.090361 | F24: 781.15 | G24: 881.71 | H24: =(F24-G24) -> -100.56 | I24: =IFERROR((((F24-G24)/IF(G24<0,-1*G24,G24))*100),"") -> -11.405111 | J24: 1159.91 | K24: 991.31 | L24: =(J24-K24) -> 168.6 | M24: =IFERROR((((J24-K24)/IF(K24<0,-1*K24,K24))*100),"") -> 17.007798 | N24: =B24+F24+J24 -> 2466.7 | O24: =C24+G24+K24 -> 2780.71 | P24: =(N24-O24) -> -314.01 | Q24: =IFERROR((((N24-O24)/IF(O24<0,-1*O24,O24))*100),"") -> -11.29244
A25: Total for 6100 Payroll Expenses | B25: =B21+B22+B23+B24 -> 26115.59 | C25: =C21+C22+C23+C24 -> 24704.75 | D25: =(B25-C25) -> 1410.84 | E25: =IFERROR((((B25-C25)/IF(C25<0,-1*C25,C25))*100),"") -> 5.7108046 | F25: =F21+F22+F23+F24 -> 21524.42 | G25: =G21+G22+G23+G24 -> 21870.08 | H25: =(F25-G25) -> -345.66 | I25: =IFERROR((((F25-G25)/IF(G25<0,-1*G25,G25))*100),"") -> -1.5805155 | J25: =J21+J22+J23+J24 -> 26620.13 | K25: =K21+K22+K23+K24 -> 31132.62 | L25: =(J25-K25) -> -4512.49 | M25: =IFERROR((((J25-K25)/IF(K25<0,-1*K25,K25))*100),"") -> -14.494411 | N25: =B25+F25+J25 -> 74260.14 | O25: =C25+G25+K25 -> 77707.45 | P25: =(N25-O25) -> -3447.31 | Q25: =IFERROR((((N25-O25)/IF(O25<0,-1*O25,O25))*100),"") -> -4.4362671
A26: 6130 Staff Training & Development | B26: 1583.92 | D26: =(B26-C26) -> 1583.92 | F26: -1083.92 | G26: 88.48 | H26: =(F26-G26) -> -1172.4 | I26: =IFERROR((((F26-G26)/IF(G26<0,-1*G26,G26))*100),"") -> -1325.0452 | J26: 2632.67 | L26: =(J26-K26) -> 2632.67 | N26: =B26+F26+J26 -> 3132.67 | O26: =C26+G26+K26 -> 88.48 | P26: =(N26-O26) -> 3044.19 | Q26: =IFERROR((((N26-O26)/IF(O26<0,-1*O26,O26))*100),"") -> 3440.5402
A27: 6135 Payroll Processing Fees | B27: 919.2 | C27: 714 | D27: =(B27-C27) -> 205.2 | E27: =IFERROR((((B27-C27)/IF(C27<0,-1*C27,C27))*100),"") -> 28.739496 | F27: 883.2 | G27: 674 | H27: =(F27-G27) -> 209.2 | I27: =IFERROR((((F27-G27)/IF(G27<0,-1*G27,G27))*100),"") -> 31.038576 | J27: 956 | K27: 953 | L27: =(J27-K27) -> 3 | M27: =IFERROR((((J27-K27)/IF(K27<0,-1*K27,K27))*100),"") -> 0.31479538 | N27: =B27+F27+J27 -> 2758.4 | O27: =C27+G27+K27 -> 2341 | P27: =(N27-O27) -> 417.4 | Q27: =IFERROR((((N27-O27)/IF(O27<0,-1*O27,O27))*100),"") -> 17.829987
